Workbook

Sheet FUNDED DEALS
A1: 2026 GRAND TOTAL | D1: =SUM(COUNT(C4:C103),COUNT(C106:C205),COUNT(C208:C307),COUNT(C310:C409),COUNT(C412:C511),COUNT(C514:C613),COUNT(C616:C715),COUNT(C718:C817),COUNT(C820:C919))&" units" -> 0 units | G1: =G104+G206+G308+G410+G512+G614+G716+G818+G920 -> 0 | N1: =N104+N206+N308+N410+N512+N614+N716+N818+N920 -> 0 | O1: =O104+O206+O308+O410+O512+O614+O716+O818+O920 -> 0 | R1: =R104+R206+R308+R410+R512+R614+R716+R818+R920 -> 0 | S1: =S104+S206+S308+S410+S512+S614+S716+S818+S920 -> 0 | AC1: =AC104+AC206+AC308+AC410+AC512+AC614+AC716+AC818+AC920 -> 0 | AD1: =AD104+AD206+AD308+AD410+AD512+AD614+AD716+AD818+AD920 -> 0 | AE1: =AE104+AE206+AE308+AE410+AE512+AE614+AE716+AE818+AE920 -> 0 | AJ1: =AJ104+AJ206+AJ308+AJ410+AJ512+AJ614+AJ716+AJ818+AJ920 -> 0 | AK1: =AK104+AK206+AK308+AK410+AK512+AK614+AK716+AK818+AK920 -> 0 | AL1: =AL104+AL206+AL308+AL410+AL512+AL614+AL716+AL818+AL920 -> 0
A2: Deal ID | B2: Parent Deal | C2: Date | D2: Business Name | E2: Lender | F2: Product | G2: Funded / Draw Amount ($) | H2: Factor Rate | I2: Term (bus. days) | J2: Payback ($) | K2: Frequency | L2: Comm % | M2: PSF (% or $) | N2: PSF $ (auto) | O2: Gross Commission ($) | P2: Referral Partner | Q2: Referral % | R2: Referral Fee ($) | S2: Net Comm After Referral ($) | T2: Opener | U2: Opener % | V2: Opener $ | W2: Closer | X2: Closer % | Y2: Closer $ | Z2: Override Rep | AA2: Override % | AB2: Override $ | AC2: Total Rep Payout ($) | AD2: HOUSE NET ($) | AE2: Clawback $ | AF2: Clawback Date | AG2: Opener CB $ | AH2: Closer CB $ | AI2: Override CB $ | AJ2: Rep Clawback $ | AK2: House Clawback $ | AL2: House Net After Clawback ($) | AM2: Commission Status | AN2: Lender Paid Date | AO2: Rep Paid Date | AP2: Est. Renewal (40% in) | AQ2: Deal Status | AR2: Maturity Date | AS2: Notes | AT2: CB Risk | AU2: Lead Source
A3: ▼ APRIL 2026 | AW3: 0 | AX3: 0
A4: =IF(C4<>"","F"&COUNT($C$4:C4),"") | B4: =IF(OR(F4="LOC - INITIAL",F4="CONSOLIDATION - UPFRONT COMM",F4="REVERSE - TOTAL FUNDING"),A4,"") | J4: =IF(AND(G4<>"",H4<>""),G4*H4,"") | N4: =IF(OR(G4="",M4=""),0,IF(M4>100,M4,G4*IF(M4>1,M4/100,M4))) -> 0 | O4: =IF(G4="","",G4*IF(L4="",0,IF(L4>1,L4/100,L4))+N4) | Q4: =IF(P4="","",IFERROR(VLOOKUP(P4,PARTNERS!$A$2:$B$30,2,0),"")) | R4: =IF(O4="","",IF(OR(P4="",Q4=""),0,(O4-N4)*IF(Q4>1,Q4/100,Q4))) | S4: =IF(O4="","",O4-R4) | U4: =IF(T4="","",IFERROR(VLOOKUP(T4,REPS!$A$2:$D$40,2,0),"")) | V4: =IF(O4="","",IF(U4="",0,O4*IF(U4>1,U4/100,U4))) | X4: =IF(W4="","",IFERROR(VLOOKUP(W4,REPS!$A$2:$D$40,3,0),"")) | Y4: =IF(O4="","",IF(X4="",0,O4*IF(X4>1,X4/100,X4))) | AA4: =IF(Z4="","",IFERROR(VLOOKUP(Z4,REPS!$A$2:$D$40,4,0),"")) | AB4: =IF(O4="","",IF(AA4="",0,O4*IF(AA4>1,AA4/100,AA4))) | AC4: =IF(O4="","",V4+Y4+AB4) | AD4: =IF(O4="","",O4-R4-AC4) | AG4: =IF(OR(AE4="",AE4=0),0,AE4*IF(U4="",0,IF(U4>1,U4/100,U4))) -> 0 | AH4: =IF(OR(AE4="",AE4=0),0,AE4*IF(X4="",0,IF(X4>1,X4/100,X4))) -> 0 | AI4: =IF(OR(AE4="",AE4=0),0,AE4*IF(AA4="",0,IF(AA4>1,AA4/100,AA4))) -> 0 | AJ4: =AG4+AH4+AI4 -> 0 | AK4: =IF(OR(AE4="",AE4=0),0,AE4-AJ4) -> 0 | AL4: =IF(AD4="","",AD4-AK4) | AM4: =IF(C4="","","Waiting for payment") | AP4: =IF(OR(C4="",I4="",K4=""),"",IF(K4="Monthly",EDATE(C4,ROUND(I4*SETTINGS!$I$8,0)),WORKDAY(C4,ROUND(I4*SETTINGS!$I$8,0)))) | AQ4: =IF(C4="","",IF(AND(AP4<>"",TODAY()>=AP4),"Refi Ready",IF(TODAY()-C4>=SETTINGS!$I$11,"Prospecting","Performing"))) | AR4: =IF(OR(C4="",I4="",K4=""),"",IF(K4="Monthly",EDATE(C4,I4),WORKDAY(C4,I4))) | AT4: =IF(C4="","",IF(AM4="Clawed Back","CLAWED",IF(TODAY()<=C4+SETTINGS!$I$2,"⚠ AT RISK","SAFE"))) | AW4: =AW3+IF(AND(C4<>"",AO4<>"",OR('REP COMMISSION'!$B$3="",T4='REP COMMISSION'!$B$3,W4='REP COMMISSION'!$B$3,Z4='REP COMMISSION'!$B$3)),1,0) -> 0 | AX4: =AX3+IF(AND(C4<>"",OR(F4="LOC - INITIAL",F4="CONSOLIDATION - UPFRONT COMM",F4="REVERSE - TOTAL FUNDING")),1,0) -> 0
A5: =IF(C5<>"","F"&COUNT($C$4:C5),"") | B5: =IF(OR(F5="LOC - INITIAL",F5="CONSOLIDATION - UPFRONT COMM",F5="REVERSE - TOTAL FUNDING"),A5,"") | J5: =IF(AND(G5<>"",H5<>""),G5*H5,"") | N5: =IF(OR(G5="",M5=""),0,IF(M5>100,M5,G5*IF(M5>1,M5/100,M5))) -> 0 | O5: =IF(G5="","",G5*IF(L5="",0,IF(L5>1,L5/100,L5))+N5) | Q5: =IF(P5="","",IFERROR(VLOOKUP(P5,PARTNERS!$A$2:$B$30,2,0),"")) | R5: =IF(O5="","",IF(OR(P5="",Q5=""),0,(O5-N5)*IF(Q5>1,Q5/100,Q5))) | S5: =IF(O5="","",O5-R5) | U5: =IF(T5="","",IFERROR(VLOOKUP(T5,REPS!$A$2:$D$40,2,0),"")) | V5: =IF(O5="","",IF(U5="",0,O5*IF(U5>1,U5/100,U5))) | X5: =IF(W5="","",IFERROR(VLOOKUP(W5,REPS!$A$2:$D$40,3,0),"")) | Y5: =IF(O5="","",IF(X5="",0,O5*IF(X5>1,X5/100,X5))) | AA5: =IF(Z5="","",IFERROR(VLOOKUP(Z5,REPS!$A$2:$D$40,4,0),"")) | AB5: =IF(O5="","",IF(AA5="",0,O5*IF(AA5>1,AA5/100,AA5))) | AC5: =IF(O5="","",V5+Y5+AB5) | AD5: =IF(O5="","",O5-R5-AC5) | AG5: =IF(OR(AE5="",AE5=0),0,AE5*IF(U5="",0,IF(U5>1,U5/100,U5))) -> 0 | AH5: =IF(OR(AE5="",AE5=0),0,AE5*IF(X5="",0,IF(X5>1,X5/100,X5))) -> 0 | AI5: =IF(OR(AE5="",AE5=0),0,AE5*IF(AA5="",0,IF(AA5>1,AA5/100,AA5))) -> 0 | AJ5: =AG5+AH5+AI5 -> 0 | AK5: =IF(OR(AE5="",AE5=0),0,AE5-AJ5) -> 0 | AL5: =IF(AD5="","",AD5-AK5) | AM5: =IF(C5="","","Waiting for payment") | AP5: =IF(OR(C5="",I5="",K5=""),"",IF(K5="Monthly",EDATE(C5,ROUND(I5*SETTINGS!$I$8,0)),WORKDAY(C5,ROUND(I5*SETTINGS!$I$8,0)))) | AQ5: =IF(C5="","",IF(AND(AP5<>"",TODAY()>=AP5),"Refi Ready",IF(TODAY()-C5>=SETTINGS!$I$11,"Prospecting","Performing"))) | AR5: =IF(OR(C5="",I5="",K5=""),"",IF(K5="Monthly",EDATE(C5,I5),WORKDAY(C5,I5))) | AT5: =IF(C5="","",IF(AM5="Clawed Back","CLAWED",IF(TODAY()<=C5+SETTINGS!$I$2,"⚠ AT RISK","SAFE"))) | AW5: =AW4+IF(AND(C5<>"",AO5<>"",OR('REP COMMISSION'!$B$3="",T5='REP COMMISSION'!$B$3,W5='REP COMMISSION'!$B$3,Z5='REP COMMISSION'!$B$3)),1,0) -> 0 | AX5: =AX4+IF(AND(C5<>"",OR(F5="LOC - INITIAL",F5="CONSOLIDATION - UPFRONT COMM",F5="REVERSE - TOTAL FUNDING")),1,0) -> 0
A6: =IF(C6<>"","F"&COUNT($C$4:C6),"") | B6: =IF(OR(F6="LOC - INITIAL",F6="CONSOLIDATION - UPFRONT COMM",F6="REVERSE - TOTAL FUNDING"),A6,"") | J6: =IF(AND(G6<>"",H6<>""),G6*H6,"") | N6: =IF(OR(G6="",M6=""),0,IF(M6>100,M6,G6*IF(M6>1,M6/100,M6))) -> 0 | O6: =IF(G6="","",G6*IF(L6="",0,IF(L6>1,L6/100,L6))+N6) | Q6: =IF(P6="","",IFERROR(VLOOKUP(P6,PARTNERS!$A$2:$B$30,2,0),"")) | R6: =IF(O6="","",IF(OR(P6="",Q6=""),0,(O6-N6)*IF(Q6>1,Q6/100,Q6))) | S6: =IF(O6="","",O6-R6) | U6: =IF(T6="","",IFERROR(VLOOKUP(T6,REPS!$A$2:$D$40,2,0),"")) | V6: =IF(O6="","",IF(U6="",0,O6*IF(U6>1,U6/100,U6))) | X6: =IF(W6="","",IFERROR(VLOOKUP(W6,REPS!$A$2:$D$40,3,0),"")) | Y6: =IF(O6="","",IF(X6="",0,O6*IF(X6>1,X6/100,X6))) | AA6: =IF(Z6="","",IFERROR(VLOOKUP(Z6,REPS!$A$2:$D$40,4,0),"")) | AB6: =IF(O6="","",IF(AA6="",0,O6*IF(AA6>1,AA6/100,AA6))) | AC6: =IF(O6="","",V6+Y6+AB6) | AD6: =IF(O6="","",O6-R6-AC6) | AG6: =IF(OR(AE6="",AE6=0),0,AE6*IF(U6="",0,IF(U6>1,U6/100,U6))) -> 0 | AH6: =IF(OR(AE6="",AE6=0),0,AE6*IF(X6="",0,IF(X6>1,X6/100,X6))) -> 0 | AI6: =IF(OR(AE6="",AE6=0),0,AE6*IF(AA6="",0,IF(AA6>1,AA6/100,AA6))) -> 0 | AJ6: =AG6+AH6+AI6 -> 0 | AK6: =IF(OR(AE6="",AE6=0),0,AE6-AJ6) -> 0 | AL6: =IF(AD6="","",AD6-AK6) | AM6: =IF(C6="","","Waiting for payment") | AP6: =IF(OR(C6="",I6="",K6=""),"",IF(K6="Monthly",EDATE(C6,ROUND(I6*SETTINGS!$I$8,0)),WORKDAY(C6,ROUND(I6*SETTINGS!$I$8,0)))) | AQ6: =IF(C6="","",IF(AND(AP6<>"",TODAY()>=AP6),"Refi Ready",IF(TODAY()-C6>=SETTINGS!$I$11,"Prospecting","Performing"))) | AR6: =IF(OR(C6="",I6="",K6=""),"",IF(K6="Monthly",EDATE(C6,I6),WORKDAY(C6,I6))) | AT6: =IF(C6="","",IF(AM6="Clawed Back","CLAWED",IF(TODAY()<=C6+SETTINGS!$I$2,"⚠ AT RISK","SAFE"))) | AW6: =AW5+IF(AND(C6<>"",AO6<>"",OR('REP COMMISSION'!$B$3="",T6='REP COMMISSION'!$B$3,W6='REP COMMISSION'!$B$3,Z6='REP COMMISSION'!$B$3)),1,0) -> 0 | AX6: =AX5+IF(AND(C6<>"",OR(F6="LOC - INITIAL",F6="CONSOLIDATION - UPFRONT COMM",F6="REVERSE - TOTAL FUNDING")),1,0) -> 0
A7: =IF(C7<>"","F"&COUNT($C$4:C7),"") | B7: =IF(OR(F7="LOC - INITIAL",F7="CONSOLIDATION - UPFRONT COMM",F7="REVERSE - TOTAL FUNDING"),A7,"") | J7: =IF(AND(G7<>"",H7<>""),G7*H7,"") | N7: =IF(OR(G7="",M7=""),0,IF(M7>100,M7,G7*IF(M7>1,M7/100,M7))) -> 0 | O7: =IF(G7="","",G7*IF(L7="",0,IF(L7>1,L7/100,L7))+N7) | Q7: =IF(P7="","",IFERROR(VLOOKUP(P7,PARTNERS!$A$2:$B$30,2,0),"")) | R7: =IF(O7="","",IF(OR(P7="",Q7=""),0,(O7-N7)*IF(Q7>1,Q7/100,Q7))) | S7: =IF(O7="","",O7-R7) | U7: =IF(T7="","",IFERROR(VLOOKUP(T7,REPS!$A$2:$D$40,2,0),"")) | V7: =IF(O7="","",IF(U7="",0,O7*IF(U7>1,U7/100,U7))) | X7: =IF(W7="","",IFERROR(VLOOKUP(W7,REPS!$A$2:$D$40,3,0),"")) | Y7: =IF(O7="","",IF(X7="",0,O7*IF(X7>1,X7/100,X7))) | AA7: =IF(Z7="","",IFERROR(VLOOKUP(Z7,REPS!$A$2:$D$40,4,0),"")) | AB7: =IF(O7="","",IF(AA7="",0,O7*IF(AA7>1,AA7/100,AA7))) | AC7: =IF(O7="","",V7+Y7+AB7) | AD7: =IF(O7="","",O7-R7-AC7) | AG7: =IF(OR(AE7="",AE7=0),0,AE7*IF(U7="",0,IF(U7>1,U7/100,U7))) -> 0 | AH7: =IF(OR(AE7="",AE7=0),0,AE7*IF(X7="",0,IF(X7>1,X7/100,X7))) -> 0 | AI7: =IF(OR(AE7="",AE7=0),0,AE7*IF(AA7="",0,IF(AA7>1,AA7/100,AA7))) -> 0 | AJ7: =AG7+AH7+AI7 -> 0 | AK7: =IF(OR(AE7="",AE7=0),0,AE7-AJ7) -> 0 | AL7: =IF(AD7="","",AD7-AK7) | AM7: =IF(C7="","","Waiting for payment") | AP7: =IF(OR(C7="",I7="",K7=""),"",IF(K7="Monthly",EDATE(C7,ROUND(I7*SETTINGS!$I$8,0)),WORKDAY(C7,ROUND(I7*SETTINGS!$I$8,0)))) | AQ7: =IF(C7="","",IF(AND(AP7<>"",TODAY()>=AP7),"Refi Ready",IF(TODAY()-C7>=SETTINGS!$I$11,"Prospecting","Performing"))) | AR7: =IF(OR(C7="",I7="",K7=""),"",IF(K7="Monthly",EDATE(C7,I7),WORKDAY(C7,I7))) | AT7: =IF(C7="","",IF(AM7="Clawed Back","CLAWED",IF(TODAY()<=C7+SETTINGS!$I$2,"⚠ AT RISK","SAFE"))) | AW7: =AW6+IF(AND(C7<>"",AO7<>"",OR('REP COMMISSION'!$B$3="",T7='REP COMMISSION'!$B$3,W7='REP COMMISSION'!$B$3,Z7='REP COMMISSION'!$B$3)),1,0) -> 0 | AX7: =AX6+IF(AND(C7<>"",OR(F7="LOC - INITIAL",F7="CONSOLIDATION - UPFRONT COMM",F7="REVERSE - TOTAL FUNDING")),1,0) -> 0
A8: =IF(C8<>"","F"&COUNT($C$4:C8),"") | B8: =IF(OR(F8="LOC - INITIAL",F8="CONSOLIDATION - UPFRONT COMM",F8="REVERSE - TOTAL FUNDING"),A8,"") | J8: =IF(AND(G8<>"",H8<>""),G8*H8,"") | N8: =IF(OR(G8="",M8=""),0,IF(M8>100,M8,G8*IF(M8>1,M8/100,M8))) -> 0 | O8: =IF(G8="","",G8*IF(L8="",0,IF(L8>1,L8/100,L8))+N8) | Q8: =IF(P8="","",IFERROR(VLOOKUP(P8,PARTNERS!$A$2:$B$30,2,0),"")) | R8: =IF(O8="","",IF(OR(P8="",Q8=""),0,(O8-N8)*IF(Q8>1,Q8/100,Q8))) | S8: =IF(O8="","",O8-R8) | U8: =IF(T8="","",IFERROR(VLOOKUP(T8,REPS!$A$2:$D$40,2,0),"")) | V8: =IF(O8="","",IF(U8="",0,O8*IF(U8>1,U8/100,U8))) | X8: =IF(W8="","",IFERROR(VLOOKUP(W8,REPS!$A$2:$D$40,3,0),"")) | Y8: =IF(O8="","",IF(X8="",0,O8*IF(X8>1,X8/100,X8))) | AA8: =IF(Z8="","",IFERROR(VLOOKUP(Z8,REPS!$A$2:$D$40,4,0),"")) | AB8: =IF(O8="","",IF(AA8="",0,O8*IF(AA8>1,AA8/100,AA8))) | AC8: =IF(O8="","",V8+Y8+AB8) | AD8: =IF(O8="","",O8-R8-AC8) | AG8: =IF(OR(AE8="",AE8=0),0,AE8*IF(U8="",0,IF(U8>1,U8/100,U8))) -> 0 | AH8: =IF(OR(AE8="",AE8=0),0,AE8*IF(X8="",0,IF(X8>1,X8/100,X8))) -> 0 | AI8: =IF(OR(AE8="",AE8=0),0,AE8*IF(AA8="",0,IF(AA8>1,AA8/100,AA8))) -> 0 | AJ8: =AG8+AH8+AI8 -> 0 | AK8: =IF(OR(AE8="",AE8=0),0,AE8-AJ8) -> 0 | AL8: =IF(AD8="","",AD8-AK8) | AM8: =IF(C8="","","Waiting for payment") | AP8: =IF(OR(C8="",I8="",K8=""),"",IF(K8="Monthly",EDATE(C8,ROUND(I8*SETTINGS!$I$8,0)),WORKDAY(C8,ROUND(I8*SETTINGS!$I$8,0)))) | AQ8: =IF(C8="","",IF(AND(AP8<>"",TODAY()>=AP8),"Refi Ready",IF(TODAY()-C8>=SETTINGS!$I$11,"Prospecting","Performing"))) | AR8: =IF(OR(C8="",I8="",K8=""),"",IF(K8="Monthly",EDATE(C8,I8),WORKDAY(C8,I8))) | AT8: =IF(C8="","",IF(AM8="Clawed Back","CLAWED",IF(TODAY()<=C8+SETTINGS!$I$2,"⚠ AT RISK","SAFE"))) | AW8: =AW7+IF(AND(C8<>"",AO8<>"",OR('REP COMMISSION'!$B$3="",T8='REP COMMISSION'!$B$3,W8='REP COMMISSION'!$B$3,Z8='REP COMMISSION'!$B$3)),1,0) -> 0 | AX8: =AX7+IF(AND(C8<>"",OR(F8="LOC - INITIAL",F8="CONSOLIDATION - UPFRONT COMM",F8="REVERSE - TOTAL FUNDING")),1,0) -> 0
A9: =IF(C9<>"","F"&COUNT($C$4:C9),"") | B9: =IF(OR(F9="LOC - INITIAL",F9="CONSOLIDATION - UPFRONT COMM",F9="REVERSE - TOTAL FUNDING"),A9,"") | J9: =IF(AND(G9<>"",H9<>""),G9*H9,"") | N9: =IF(OR(G9="",M9=""),0,IF(M9>100,M9,G9*IF(M9>1,M9/100,M9))) -> 0 | O9: =IF(G9="","",G9*IF(L9="",0,IF(L9>1,L9/100,L9))+N9) | Q9: =IF(P9="","",IFERROR(VLOOKUP(P9,PARTNERS!$A$2:$B$30,2,0),"")) | R9: =IF(O9="","",IF(OR(P9="",Q9=""),0,(O9-N9)*IF(Q9>1,Q9/100,Q9))) | S9: =IF(O9="","",O9-R9) | U9: =IF(T9="","",IFERROR(VLOOKUP(T9,REPS!$A$2:$D$40,2,0),"")) | V9: =IF(O9="","",IF(U9="",0,O9*IF(U9>1,U9/100,U9))) | X9: =IF(W9="","",IFERROR(VLOOKUP(W9,REPS!$A$2:$D$40,3,0),"")) | Y9: =IF(O9="","",IF(X9="",0,O9*IF(X9>1,X9/100,X9))) | AA9: =IF(Z9="","",IFERROR(VLOOKUP(Z9,REPS!$A$2:$D$40,4,0),"")) | AB9: =IF(O9="","",IF(AA9="",0,O9*IF(AA9>1,AA9/100,AA9))) | AC9: =IF(O9="","",V9+Y9+AB9) | AD9: =IF(O9="","",O9-R9-AC9) | AG9: =IF(OR(AE9="",AE9=0),0,AE9*IF(U9="",0,IF(U9>1,U9/100,U9))) -> 0 | AH9: =IF(OR(AE9="",AE9=0),0,AE9*IF(X9="",0,IF(X9>1,X9/100,X9))) -> 0 | AI9: =IF(OR(AE9="",AE9=0),0,AE9*IF(AA9="",0,IF(AA9>1,AA9/100,AA9))) -> 0 | AJ9: =AG9+AH9+AI9 -> 0 | AK9: =IF(OR(AE9="",AE9=0),0,AE9-AJ9) -> 0 | AL9: =IF(AD9="","",AD9-AK9) | AM9: =IF(C9="","","Waiting for payment") | AP9: =IF(OR(C9="",I9="",K9=""),"",IF(K9="Monthly",EDATE(C9,ROUND(I9*SETTINGS!$I$8,0)),WORKDAY(C9,ROUND(I9*SETTINGS!$I$8,0)))) | AQ9: =IF(C9="","",IF(AND(AP9<>"",TODAY()>=AP9),"Refi Ready",IF(TODAY()-C9>=SETTINGS!$I$11,"Prospecting","Performing"))) | AR9: =IF(OR(C9="",I9="",K9=""),"",IF(K9="Monthly",EDATE(C9,I9),WORKDAY(C9,I9))) | AT9: =IF(C9="","",IF(AM9="Clawed Back","CLAWED",IF(TODAY()<=C9+SETTINGS!$I$2,"⚠ AT RISK","SAFE"))) | AW9: =AW8+IF(AND(C9<>"",AO9<>"",OR('REP COMMISSION'!$B$3="",T9='REP COMMISSION'!$B$3,W9='REP COMMISSION'!$B$3,Z9='REP COMMISSION'!$B$3)),1,0) -> 0 | AX9: =AX8+IF(AND(C9<>"",OR(F9="LOC - INITIAL",F9="CONSOLIDATION - UPFRONT COMM",F9="REVERSE - TOTAL FUNDING")),1,0) -> 0
A10: =IF(C10<>"","F"&COUNT($C$4:C10),"") | B10: =IF(OR(F10="LOC - INITIAL",F10="CONSOLIDATION - UPFRONT COMM",F10="REVERSE - TOTAL FUNDING"),A10,"") | J10: =IF(AND(G10<>"",H10<>""),G10*H10,"") | N10: =IF(OR(G10="",M10=""),0,IF(M10>100,M10,G10*IF(M10>1,M10/100,M10))) -> 0 | O10: =IF(G10="","",G10*IF(L10="",0,IF(L10>1,L10/100,L10))+N10) | Q10: =IF(P10="","",IFERROR(VLOOKUP(P10,PARTNERS!$A$2:$B$30,2,0),"")) | R10: =IF(O10="","",IF(OR(P10="",Q10=""),0,(O10-N10)*IF(Q10>1,Q10/100,Q10))) | S10: =IF(O10="","",O10-R10) | U10: =IF(T10="","",IFERROR(VLOOKUP(T10,REPS!$A$2:$D$40,2,0),"")) | V10: =IF(O10="","",IF(U10="",0,O10*IF(U10>1,U10/100,U10))) | X10: =IF(W10="","",IFERROR(VLOOKUP(W10,REPS!$A$2:$D$40,3,0),"")) | Y10: =IF(O10="","",IF(X10="",0,O10*IF(X10>1,X10/100,X10))) | AA10: =IF(Z10="","",IFERROR(VLOOKUP(Z10,REPS!$A$2:$D$40,4,0),"")) | AB10: =IF(O10="","",IF(AA10="",0,O10*IF(AA10>1,AA10/100,AA10))) | AC10: =IF(O10="","",V10+Y10+AB10) | AD10: =IF(O10="","",O10-R10-AC10) | AG10: =IF(OR(AE10="",AE10=0),0,AE10*IF(U10="",0,IF(U10>1,U10/100,U10))) -> 0 | AH10: =IF(OR(AE10="",AE10=0),0,AE10*IF(X10="",0,IF(X10>1,X10/100,X10))) -> 0 | AI10: =IF(OR(AE10="",AE10=0),0,AE10*IF(AA10="",0,IF(AA10>1,AA10/100,AA10))) -> 0 | AJ10: =AG10+AH10+AI10 -> 0 | AK10: =IF(OR(AE10="",AE10=0),0,AE10-AJ10) -> 0 | AL10: =IF(AD10="","",AD10-AK10) | AM10: =IF(C10="","","Waiting for payment") | AP10: =IF(OR(C10="",I10="",K10=""),"",IF(K10="Monthly",EDATE(C10,ROUND(I10*SETTINGS!$I$8,0)),WORKDAY(C10,ROUND(I10*SETTINGS!$I$8,0)))) | AQ10: =IF(C10="","",IF(AND(AP10<>"",TODAY()>=AP10),"Refi Ready",IF(TODAY()-C10>=SETTINGS!$I$11,"Prospecting","Performing"))) | AR10: =IF(OR(C10="",I10="",K10=""),"",IF(K10="Monthly",EDATE(C10,I10),WORKDAY(C10,I10))) | AT10: =IF(C10="","",IF(AM10="Clawed Back","CLAWED",IF(TODAY()<=C10+SETTINGS!$I$2,"⚠ AT RISK","SAFE"))) | AW10: =AW9+IF(AND(C10<>"",AO10<>"",OR('REP COMMISSION'!$B$3="",T10='REP COMMISSION'!$B$3,W10='REP COMMISSION'!$B$3,Z10='REP COMMISSION'!$B$3)),1,0) -> 0 | AX10: =AX9+IF(AND(C10<>"",OR(F10="LOC - INITIAL",F10="CONSOLIDATION - UPFRONT COMM",F10="REVERSE - TOTAL FUNDING")),1,0) -> 0
A11: =IF(C11<>"","F"&COUNT($C$4:C11),"") | B11: =IF(OR(F11="LOC - INITIAL",F11="CONSOLIDATION - UPFRONT COMM",F11="REVERSE - TOTAL FUNDING"),A11,"") | J11: =IF(AND(G11<>"",H11<>""),G11*H11,"") | N11: =IF(OR(G11="",M11=""),0,IF(M11>100,M11,G11*IF(M11>1,M11/100,M11))) -> 0 | O11: =IF(G11="","",G11*IF(L11="",0,IF(L11>1,L11/100,L11))+N11) | Q11: =IF(P11="","",IFERROR(VLOOKUP(P11,PARTNERS!$A$2:$B$30,2,0),"")) | R11: =IF(O11="","",IF(OR(P11="",Q11=""),0,(O11-N11)*IF(Q11>1,Q11/100,Q11))) | S11: =IF(O11="","",O11-R11) | U11: =IF(T11="","",IFERROR(VLOOKUP(T11,REPS!$A$2:$D$40,2,0),"")) | V11: =IF(O11="","",IF(U11="",0,O11*IF(U11>1,U11/100,U11))) | X11: =IF(W11="","",IFERROR(VLOOKUP(W11,REPS!$A$2:$D$40,3,0),"")) | Y11: =IF(O11="","",IF(X11="",0,O11*IF(X11>1,X11/100,X11))) | AA11: =IF(Z11="","",IFERROR(VLOOKUP(Z11,REPS!$A$2:$D$40,4,0),"")) | AB11: =IF(O11="","",IF(AA11="",0,O11*IF(AA11>1,AA11/100,AA11))) | AC11: =IF(O11="","",V11+Y11+AB11) | AD11: =IF(O11="","",O11-R11-AC11) | AG11: =IF(OR(AE11="",AE11=0),0,AE11*IF(U11="",0,IF(U11>1,U11/100,U11))) -> 0 | AH11: =IF(OR(AE11="",AE11=0),0,AE11*IF(X11="",0,IF(X11>1,X11/100,X11))) -> 0 | AI11: =IF(OR(AE11="",AE11=0),0,AE11*IF(AA11="",0,IF(AA11>1,AA11/100,AA11))) -> 0 | AJ11: =AG11+AH11+AI11 -> 0 | AK11: =IF(OR(AE11="",AE11=0),0,AE11-AJ11) -> 0 | AL11: =IF(AD11="","",AD11-AK11) | AM11: =IF(C11="","","Waiting for payment") | AP11: =IF(OR(C11="",I11="",K11=""),"",IF(K11="Monthly",EDATE(C11,ROUND(I11*SETTINGS!$I$8,0)),WORKDAY(C11,ROUND(I11*SETTINGS!$I$8,0)))) | AQ11: =IF(C11="","",IF(AND(AP11<>"",TODAY()>=AP11),"Refi Ready",IF(TODAY()-C11>=SETTINGS!$I$11,"Prospecting","Performing"))) | AR11: =IF(OR(C11="",I11="",K11=""),"",IF(K11="Monthly",EDATE(C11,I11),WORKDAY(C11,I11))) | AT11: =IF(C11="","",IF(AM11="Clawed Back","CLAWED",IF(TODAY()<=C11+SETTINGS!$I$2,"⚠ AT RISK","SAFE"))) | AW11: =AW10+IF(AND(C11<>"",AO11<>"",OR('REP COMMISSION'!$B$3="",T11='REP COMMISSION'!$B$3,W11='REP COMMISSION'!$B$3,Z11='REP COMMISSION'!$B$3)),1,0) -> 0 | AX11: =AX10+IF(AND(C11<>"",OR(F11="LOC - INITIAL",F11="CONSOLIDATION - UPFRONT COMM",F11="REVERSE - TOTAL FUNDING")),1,0) -> 0
A12: =IF(C12<>"","F"&COUNT($C$4:C12),"") | B12: =IF(OR(F12="LOC - INITIAL",F12="CONSOLIDATION - UPFRONT COMM",F12="REVERSE - TOTAL FUNDING"),A12,"") | J12: =IF(AND(G12<>"",H12<>""),G12*H12,"") | N12: =IF(OR(G12="",M12=""),0,IF(M12>100,M12,G12*IF(M12>1,M12/100,M12))) -> 0 | O12: =IF(G12="","",G12*IF(L12="",0,IF(L12>1,L12/100,L12))+N12) | Q12: =IF(P12="","",IFERROR(VLOOKUP(P12,PARTNERS!$A$2:$B$30,2,0),"")) | R12: =IF(O12="","",IF(OR(P12="",Q12=""),0,(O12-N12)*IF(Q12>1,Q12/100,Q12))) | S12: =IF(O12="","",O12-R12) | U12: =IF(T12="","",IFERROR(VLOOKUP(T12,REPS!$A$2:$D$40,2,0),"")) | V12: =IF(O12="","",IF(U12="",0,O12*IF(U12>1,U12/100,U12))) | X12: =IF(W12="","",IFERROR(VLOOKUP(W12,REPS!$A$2:$D$40,3,0),"")) | Y12: =IF(O12="","",IF(X12="",0,O12*IF(X12>1,X12/100,X12))) | AA12: =IF(Z12="","",IFERROR(VLOOKUP(Z12,REPS!$A$2:$D$40,4,0),"")) | AB12: =IF(O12="","",IF(AA12="",0,O12*IF(AA12>1,AA12/100,AA12))) | AC12: =IF(O12="","",V12+Y12+AB12) | AD12: =IF(O12="","",O12-R12-AC12) | AG12: =IF(OR(AE12="",AE12=0),0,AE12*IF(U12="",0,IF(U12>1,U12/100,U12))) -> 0 | AH12: =IF(OR(AE12="",AE12=0),0,AE12*IF(X12="",0,IF(X12>1,X12/100,X12))) -> 0 | AI12: =IF(OR(AE12="",AE12=0),0,AE12*IF(AA12="",0,IF(AA12>1,AA12/100,AA12))) -> 0 | AJ12: =AG12+AH12+AI12 -> 0 | AK12: =IF(OR(AE12="",AE12=0),0,AE12-AJ12) -> 0 | AL12: =IF(AD12="","",AD12-AK12) | AM12: =IF(C12="","","Waiting for payment") | AP12: =IF(OR(C12="",I12="",K12=""),"",IF(K12="Monthly",EDATE(C12,ROUND(I12*SETTINGS!$I$8,0)),WORKDAY(C12,ROUND(I12*SETTINGS!$I$8,0)))) | AQ12: =IF(C12="","",IF(AND(AP12<>"",TODAY()>=AP12),"Refi Ready",IF(TODAY()-C12>=SETTINGS!$I$11,"Prospecting","Performing"))) | AR12: =IF(OR(C12="",I12="",K12=""),"",IF(K12="Monthly",EDATE(C12,I12),WORKDAY(C12,I12))) | AT12: =IF(C12="","",IF(AM12="Clawed Back","CLAWED",IF(TODAY()<=C12+SETTINGS!$I$2,"⚠ AT RISK","SAFE"))) | AW12: =AW11+IF(AND(C12<>"",AO12<>"",OR('REP COMMISSION'!$B$3="",T12='REP COMMISSION'!$B$3,W12='REP COMMISSION'!$B$3,Z12='REP COMMISSION'!$B$3)),1,0) -> 0 | AX12: =AX11+IF(AND(C12<>"",OR(F12="LOC - INITIAL",F12="CONSOLIDATION - UPFRONT COMM",F12="REVERSE - TOTAL FUNDING")),1,0) -> 0
A13: =IF(C13<>"","F"&COUNT($C$4:C13),"") | B13: =IF(OR(F13="LOC - INITIAL",F13="CONSOLIDATION - UPFRONT COMM",F13="REVERSE - TOTAL FUNDING"),A13,"") | J13: =IF(AND(G13<>"",H13<>""),G13*H13,"") | N13: =IF(OR(G13="",M13=""),0,IF(M13>100,M13,G13*IF(M13>1,M13/100,M13))) -> 0 | O13: =IF(G13="","",G13*IF(L13="",0,IF(L13>1,L13/100,L13))+N13) | Q13: =IF(P13="","",IFERROR(VLOOKUP(P13,PARTNERS!$A$2:$B$30,2,0),"")) | R13: =IF(O13="","",IF(OR(P13="",Q13=""),0,(O13-N13)*IF(Q13>1,Q13/100,Q13))) | S13: =IF(O13="","",O13-R13) | U13: =IF(T13="","",IFERROR(VLOOKUP(T13,REPS!$A$2:$D$40,2,0),"")) | V13: =IF(O13="","",IF(U13="",0,O13*IF(U13>1,U13/100,U13))) | X13: =IF(W13="","",IFERROR(VLOOKUP(W13,REPS!$A$2:$D$40,3,0),"")) | Y13: =IF(O13="","",IF(X13="",0,O13*IF(X13>1,X13/100,X13))) | AA13: =IF(Z13="","",IFERROR(VLOOKUP(Z13,REPS!$A$2:$D$40,4,0),"")) | AB13: =IF(O13="","",IF(AA13="",0,O13*IF(AA13>1,AA13/100,AA13))) | AC13: =IF(O13="","",V13+Y13+AB13) | AD13: =IF(O13="","",O13-R13-AC13) | AG13: =IF(OR(AE13="",AE13=0),0,AE13*IF(U13="",0,IF(U13>1,U13/100,U13))) -> 0 | AH13: =IF(OR(AE13="",AE13=0),0,AE13*IF(X13="",0,IF(X13>1,X13/100,X13))) -> 0 | AI13: =IF(OR(AE13="",AE13=0),0,AE13*IF(AA13="",0,IF(AA13>1,AA13/100,AA13))) -> 0 | AJ13: =AG13+AH13+AI13 -> 0 | AK13: =IF(OR(AE13="",AE13=0),0,AE13-AJ13) -> 0 | AL13: =IF(AD13="","",AD13-AK13) | AM13: =IF(C13="","","Waiting for payment") | AP13: =IF(OR(C13="",I13="",K13=""),"",IF(K13="Monthly",EDATE(C13,ROUND(I13*SETTINGS!$I$8,0)),WORKDAY(C13,ROUND(I13*SETTINGS!$I$8,0)))) | AQ13: =IF(C13="","",IF(AND(AP13<>"",TODAY()>=AP13),"Refi Ready",IF(TODAY()-C13>=SETTINGS!$I$11,"Prospecting","Performing"))) | AR13: =IF(OR(C13="",I13="",K13=""),"",IF(K13="Monthly",EDATE(C13,I13),WORKDAY(C13,I13))) | AT13: =IF(C13="","",IF(AM13="Clawed Back","CLAWED",IF(TODAY()<=C13+SETTINGS!$I$2,"⚠ AT RISK","SAFE"))) | AW13: =AW12+IF(AND(C13<>"",AO13<>"",OR('REP COMMISSION'!$B$3="",T13='REP COMMISSION'!$B$3,W13='REP COMMISSION'!$B$3,Z13='REP COMMISSION'!$B$3)),1,0) -> 0 | AX13: =AX12+IF(AND(C13<>"",OR(F13="LOC - INITIAL",F13="CONSOLIDATION - UPFRONT COMM",F13="REVERSE - TOTAL FUNDING")),1,0) -> 0
A14: =IF(C14<>"","F"&COUNT($C$4:C14),"") | B14: =IF(OR(F14="LOC - INITIAL",F14="CONSOLIDATION - UPFRONT COMM",F14="REVERSE - TOTAL FUNDING"),A14,"") | J14: =IF(AND(G14<>"",H14<>""),G14*H14,"") | N14: =IF(OR(G14="",M14=""),0,IF(M14>100,M14,G14*IF(M14>1,M14/100,M14))) -> 0 | O14: =IF(G14="","",G14*IF(L14="",0,IF(L14>1,L14/100,L14))+N14) | Q14: =IF(P14="","",IFERROR(VLOOKUP(P14,PARTNERS!$A$2:$B$30,2,0),"")) | R14: =IF(O14="","",IF(OR(P14="",Q14=""),0,(O14-N14)*IF(Q14>1,Q14/100,Q14))) | S14: =IF(O14="","",O14-R14) | U14: =IF(T14="","",IFERROR(VLOOKUP(T14,REPS!$A$2:$D$40,2,0),"")) | V14: =IF(O14="","",IF(U14="",0,O14*IF(U14>1,U14/100,U14))) | X14: =IF(W14="","",IFERROR(VLOOKUP(W14,REPS!$A$2:$D$40,3,0),"")) | Y14: =IF(O14="","",IF(X14="",0,O14*IF(X14>1,X14/100,X14))) | AA14: =IF(Z14="","",IFERROR(VLOOKUP(Z14,REPS!$A$2:$D$40,4,0),"")) | AB14: =IF(O14="","",IF(AA14="",0,O14*IF(AA14>1,AA14/100,AA14))) | AC14: =IF(O14="","",V14+Y14+AB14) | AD14: =IF(O14="","",O14-R14-AC14) | AG14: =IF(OR(AE14="",AE14=0),0,AE14*IF(U14="",0,IF(U14>1,U14/100,U14))) -> 0 | AH14: =IF(OR(AE14="",AE14=0),0,AE14*IF(X14="",0,IF(X14>1,X14/100,X14))) -> 0 | AI14: =IF(OR(AE14="",AE14=0),0,AE14*IF(AA14="",0,IF(AA14>1,AA14/100,AA14))) -> 0 | AJ14: =AG14+AH14+AI14 -> 0 | AK14: =IF(OR(AE14="",AE14=0),0,AE14-AJ14) -> 0 | AL14: =IF(AD14="","",AD14-AK14) | AM14: =IF(C14="","","Waiting for payment") | AP14: =IF(OR(C14="",I14="",K14=""),"",IF(K14="Monthly",EDATE(C14,ROUND(I14*SETTINGS!$I$8,0)),WORKDAY(C14,ROUND(I14*SETTINGS!$I$8,0)))) | AQ14: =IF(C14="","",IF(AND(AP14<>"",TODAY()>=AP14),"Refi Ready",IF(TODAY()-C14>=SETTINGS!$I$11,"Prospecting","Performing"))) | AR14: =IF(OR(C14="",I14="",K14=""),"",IF(K14="Monthly",EDATE(C14,I14),WORKDAY(C14,I14))) | AT14: =IF(C14="","",IF(AM14="Clawed Back","CLAWED",IF(TODAY()<=C14+SETTINGS!$I$2,"⚠ AT RISK","SAFE"))) | AW14: =AW13+IF(AND(C14<>"",AO14<>"",OR('REP COMMISSION'!$B$3="",T14='REP COMMISSION'!$B$3,W14='REP COMMISSION'!$B$3,Z14='REP COMMISSION'!$B$3)),1,0) -> 0 | AX14: =AX13+IF(AND(C14<>"",OR(F14="LOC - INITIAL",F14="CONSOLIDATION - UPFRONT COMM",F14="REVERSE - TOTAL FUNDING")),1,0) -> 0
A15: =IF(C15<>"","F"&COUNT($C$4:C15),"") | B15: =IF(OR(F15="LOC - INITIAL",F15="CONSOLIDATION - UPFRONT COMM",F15="REVERSE - TOTAL FUNDING"),A15,"") | J15: =IF(AND(G15<>"",H15<>""),G15*H15,"") | N15: =IF(OR(G15="",M15=""),0,IF(M15>100,M15,G15*IF(M15>1,M15/100,M15))) -> 0 | O15: =IF(G15="","",G15*IF(L15="",0,IF(L15>1,L15/100,L15))+N15) | Q15: =IF(P15="","",IFERROR(VLOOKUP(P15,PARTNERS!$A$2:$B$30,2,0),"")) | R15: =IF(O15="","",IF(OR(P15="",Q15=""),0,(O15-N15)*IF(Q15>1,Q15/100,Q15))) | S15: =IF(O15="","",O15-R15) | U15: =IF(T15="","",IFERROR(VLOOKUP(T15,REPS!$A$2:$D$40,2,0),"")) | V15: =IF(O15="","",IF(U15="",0,O15*IF(U15>1,U15/100,U15))) | X15: =IF(W15="","",IFERROR(VLOOKUP(W15,REPS!$A$2:$D$40,3,0),"")) | Y15: =IF(O15="","",IF(X15="",0,O15*IF(X15>1,X15/100,X15))) | AA15: =IF(Z15="","",IFERROR(VLOOKUP(Z15,REPS!$A$2:$D$40,4,0),"")) | AB15: =IF(O15="","",IF(AA15="",0,O15*IF(AA15>1,AA15/100,AA15))) | AC15: =IF(O15="","",V15+Y15+AB15) | AD15: =IF(O15="","",O15-R15-AC15) | AG15: =IF(OR(AE15="",AE15=0),0,AE15*IF(U15="",0,IF(U15>1,U15/100,U15))) -> 0 | AH15: =IF(OR(AE15="",AE15=0),0,AE15*IF(X15="",0,IF(X15>1,X15/100,X15))) -> 0 | AI15: =IF(OR(AE15="",AE15=0),0,AE15*IF(AA15="",0,IF(AA15>1,AA15/100,AA15))) -> 0 | AJ15: =AG15+AH15+AI15 -> 0 | AK15: =IF(OR(AE15="",AE15=0),0,AE15-AJ15) -> 0 | AL15: =IF(AD15="","",AD15-AK15) | AM15: =IF(C15="","","Waiting for payment") | AP15: =IF(OR(C15="",I15="",K15=""),"",IF(K15="Monthly",EDATE(C15,ROUND(I15*SETTINGS!$I$8,0)),WORKDAY(C15,ROUND(I15*SETTINGS!$I$8,0)))) | AQ15: =IF(C15="","",IF(AND(AP15<>"",TODAY()>=AP15),"Refi Ready",IF(TODAY()-C15>=SETTINGS!$I$11,"Prospecting","Performing"))) | AR15: =IF(OR(C15="",I15="",K15=""),"",IF(K15="Monthly",EDATE(C15,I15),WORKDAY(C15,I15))) | AT15: =IF(C15="","",IF(AM15="Clawed Back","CLAWED",IF(TODAY()<=C15+SETTINGS!$I$2,"⚠ AT RISK","SAFE"))) | AW15: =AW14+IF(AND(C15<>"",AO15<>"",OR('REP COMMISSION'!$B$3="",T15='REP COMMISSION'!$B$3,W15='REP COMMISSION'!$B$3,Z15='REP COMMISSION'!$B$3)),1,0) -> 0 | AX15: =AX14+IF(AND(C15<>"",OR(F15="LOC - INITIAL",F15="CONSOLIDATION - UPFRONT COMM",F15="REVERSE - TOTAL FUNDING")),1,0) -> 0
... A103: =IF(C103<>"","F"&COUNT($C$4:C103),"") | B103: =IF(OR(F103="LOC - INITIAL",F103="CONSOLIDATION - UPFRONT COMM",F103="REVERSE - TOTAL FUNDING"),A103,"") | J103: =IF(AND(G103<>"",H103<>""),G103*H103,"") | N103: =IF(OR(G103="",M103=""),0,IF(M103>100,M103,G103*IF(M103>1,M103/100,M103))) -> 0 | O103: =IF(G103="","",G103*IF(L103="",0,IF(L103>1,L103/100,L103))+N103) | Q103: =IF(P103="","",IFERROR(VLOOKUP(P103,PARTNERS!$A$2:$B$30,2,0),"")) | R103: =IF(O103="","",IF(OR(P103="",Q103=""),0,(O103-N103)*IF(Q103>1,Q103/100,Q103))) | S103: =IF(O103="","",O103-R103) | U103: =IF(T103="","",IFERROR(VLOOKUP(T103,REPS!$A$2:$D$40,2,0),"")) | V103: =IF(O103="","",IF(U103="",0,O103*IF(U103>1,U103/100,U103))) | X103: =IF(W103="","",IFERROR(VLOOKUP(W103,REPS!$A$2:$D$40,3,0),"")) | Y103: =IF(O103="","",IF(X103="",0,O103*IF(X103>1,X103/100,X103))) | AA103: =IF(Z103="","",IFERROR(VLOOKUP(Z103,REPS!$A$2:$D$40,4,0),"")) | AB103: =IF(O103="","",IF(AA103="",0,O103*IF(AA103>1,AA103/100,AA103))) | AC103: =IF(O103="","",V103+Y103+AB103) | AD103: =IF(O103="","",O103-R103-AC103) | AG103: =IF(OR(AE103="",AE103=0),0,AE103*IF(U103="",0,IF(U103>1,U103/100,U103))) -> 0 | AH103: =IF(OR(AE103="",AE103=0),0,AE103*IF(X103="",0,IF(X103>1,X103/100,X103))) -> 0 | AI103: =IF(OR(AE103="",AE103=0),0,AE103*IF(AA103="",0,IF(AA103>1,AA103/100,AA103))) -> 0 | AJ103: =AG103+AH103+AI103 -> 0 | AK103: =IF(OR(AE103="",AE103=0),0,AE103-AJ103) -> 0 | AL103: =IF(AD103="","",AD103-AK103) | AM103: =IF(C103="","","Waiting for payment") | AP103: =IF(OR(C103="",I103="",K103=""),"",IF(K103="Monthly",EDATE(C103,ROUND(I103*SETTINGS!$I$8,0)),WORKDAY(C103,ROUND(I103*SETTINGS!$I$8,0)))) | AQ103: =IF(C103="","",IF(AND(AP103<>"",TODAY()>=AP103),"Refi Ready",IF(TODAY()-C103>=SETTINGS!$I$11,"Prospecting","Performing"))) | AR103: =IF(OR(C103="",I103="",K103=""),"",IF(K103="Monthly",EDATE(C103,I103),WORKDAY(C103,I103))) | AT103: =IF(C103="","",IF(AM103="Clawed Back","CLAWED",IF(TODAY()<=C103+SETTINGS!$I$2,"⚠ AT RISK","SAFE"))) | AW103: =AW102+IF(AND(C103<>"",AO103<>"",OR('REP COMMISSION'!$B$3="",T103='REP COMMISSION'!$B$3,W103='REP COMMISSION'!$B$3,Z103='REP COMMISSION'!$B$3)),1,0) -> 0 | AX103: =AX102+IF(AND(C103<>"",OR(F103="LOC - INITIAL",F103="CONSOLIDATION - UPFRONT COMM",F103="REVERSE - TOTAL FUNDING")),1,0) -> 0
A104: APRIL TOTAL | D104: =COUNT(C4:C103)&" units" -> 0 units | G104: =SUM(G4:G103) -> 0 | N104: =SUM(N4:N103) -> 0 | O104: =SUM(O4:O103) -> 0 | R104: =SUM(R4:R103) -> 0 | S104: =SUM(S4:S103) -> 0 | AC104: =SUM(AC4:AC103) -> 0 | AD104: =SUM(AD4:AD103) -> 0 | AE104: =SUM(AE4:AE103) -> 0 | AJ104: =SUM(AJ4:AJ103) -> 0 | AK104: =SUM(AK4:AK103) -> 0 | AL104: =SUM(AL4:AL103) -> 0 | AW104: =AW103 -> 0 | AX104: =AX103 -> 0
A105: ▼ MAY 2026 | AW105: =AW104 -> 0 | AX105: =AX104 -> 0
A106: =IF(C106<>"","F"&COUNT($C$4:C106),"") | B106: =IF(OR(F106="LOC - INITIAL",F106="CONSOLIDATION - UPFRONT COMM",F106="REVERSE - TOTAL FUNDING"),A106,"") | J106: =IF(AND(G106<>"",H106<>""),G106*H106,"") | N106: =IF(OR(G106="",M106=""),0,IF(M106>100,M106,G106*IF(M106>1,M106/100,M106))) -> 0 | O106: =IF(G106="","",G106*IF(L106="",0,IF(L106>1,L106/100,L106))+N106) | Q106: =IF(P106="","",IFERROR(VLOOKUP(P106,PARTNERS!$A$2:$B$30,2,0),"")) | R106: =IF(O106="","",IF(OR(P106="",Q106=""),0,(O106-N106)*IF(Q106>1,Q106/100,Q106))) | S106: =IF(O106="","",O106-R106) | U106: =IF(T106="","",IFERROR(VLOOKUP(T106,REPS!$A$2:$D$40,2,0),"")) | V106: =IF(O106="","",IF(U106="",0,O106*IF(U106>1,U106/100,U106))) | X106: =IF(W106="","",IFERROR(VLOOKUP(W106,REPS!$A$2:$D$40,3,0),"")) | Y106: =IF(O106="","",IF(X106="",0,O106*IF(X106>1,X106/100,X106))) | AA106: =IF(Z106="","",IFERROR(VLOOKUP(Z106,REPS!$A$2:$D$40,4,0),"")) | AB106: =IF(O106="","",IF(AA106="",0,O106*IF(AA106>1,AA106/100,AA106))) | AC106: =IF(O106="","",V106+Y106+AB106) | AD106: =IF(O106="","",O106-R106-AC106) | AG106: =IF(OR(AE106="",AE106=0),0,AE106*IF(U106="",0,IF(U106>1,U106/100,U106))) -> 0 | AH106: =IF(OR(AE106="",AE106=0),0,AE106*IF(X106="",0,IF(X106>1,X106/100,X106))) -> 0 | AI106: =IF(OR(AE106="",AE106=0),0,AE106*IF(AA106="",0,IF(AA106>1,AA106/100,AA106))) -> 0 | AJ106: =AG106+AH106+AI106 -> 0 | AK106: =IF(OR(AE106="",AE106=0),0,AE106-AJ106) -> 0 | AL106: =IF(AD106="","",AD106-AK106) | AM106: =IF(C106="","","Waiting for payment") | AP106: =IF(OR(C106="",I106="",K106=""),"",IF(K106="Monthly",EDATE(C106,ROUND(I106*SETTINGS!$I$8,0)),WORKDAY(C106,ROUND(I106*SETTINGS!$I$8,0)))) | AQ106: =IF(C106="","",IF(AND(AP106<>"",TODAY()>=AP106),"Refi Ready",IF(TODAY()-C106>=SETTINGS!$I$11,"Prospecting","Performing"))) | AR106: =IF(OR(C106="",I106="",K106=""),"",IF(K106="Monthly",EDATE(C106,I106),WORKDAY(C106,I106))) | AT106: =IF(C106="","",IF(AM106="Clawed Back","CLAWED",IF(TODAY()<=C106+SETTINGS!$I$2,"⚠ AT RISK","SAFE"))) | AW106: =AW105+IF(AND(C106<>"",AO106<>"",OR('REP COMMISSION'!$B$3="",T106='REP COMMISSION'!$B$3,W106='REP COMMISSION'!$B$3,Z106='REP COMMISSION'!$B$3)),1,0) -> 0 | AX106: =AX105+IF(AND(C106<>"",OR(F106="LOC - INITIAL",F106="CONSOLIDATION - UPFRONT COMM",F106="REVERSE - TOTAL FUNDING")),1,0) -> 0
A107: =IF(C107<>"","F"&COUNT($C$4:C107),"") | B107: =IF(OR(F107="LOC - INITIAL",F107="CONSOLIDATION - UPFRONT COMM",F107="REVERSE - TOTAL FUNDING"),A107,"") | J107: =IF(AND(G107<>"",H107<>""),G107*H107,"") | N107: =IF(OR(G107="",M107=""),0,IF(M107>100,M107,G107*IF(M107>1,M107/100,M107))) -> 0 | O107: =IF(G107="","",G107*IF(L107="",0,IF(L107>1,L107/100,L107))+N107) | Q107: =IF(P107="","",IFERROR(VLOOKUP(P107,PARTNERS!$A$2:$B$30,2,0),"")) | R107: =IF(O107="","",IF(OR(P107="",Q107=""),0,(O107-N107)*IF(Q107>1,Q107/100,Q107))) | S107: =IF(O107="","",O107-R107) | U107: =IF(T107="","",IFERROR(VLOOKUP(T107,REPS!$A$2:$D$40,2,0),"")) | V107: =IF(O107="","",IF(U107="",0,O107*IF(U107>1,U107/100,U107))) | X107: =IF(W107="","",IFERROR(VLOOKUP(W107,REPS!$A$2:$D$40,3,0),"")) | Y107: =IF(O107="","",IF(X107="",0,O107*IF(X107>1,X107/100,X107))) | AA107: =IF(Z107="","",IFERROR(VLOOKUP(Z107,REPS!$A$2:$D$40,4,0),"")) | AB107: =IF(O107="","",IF(AA107="",0,O107*IF(AA107>1,AA107/100,AA107))) | AC107: =IF(O107="","",V107+Y107+AB107) | AD107: =IF(O107="","",O107-R107-AC107) | AG107: =IF(OR(AE107="",AE107=0),0,AE107*IF(U107="",0,IF(U107>1,U107/100,U107))) -> 0 | AH107: =IF(OR(AE107="",AE107=0),0,AE107*IF(X107="",0,IF(X107>1,X107/100,X107))) -> 0 | AI107: =IF(OR(AE107="",AE107=0),0,AE107*IF(AA107="",0,IF(AA107>1,AA107/100,AA107))) -> 0 | AJ107: =AG107+AH107+AI107 -> 0 | AK107: =IF(OR(AE107="",AE107=0),0,AE107-AJ107) -> 0 | AL107: =IF(AD107="","",AD107-AK107) | AM107: =IF(C107="","","Waiting for payment") | AP107: =IF(OR(C107="",I107="",K107=""),"",IF(K107="Monthly",EDATE(C107,ROUND(I107*SETTINGS!$I$8,0)),WORKDAY(C107,ROUND(I107*SETTINGS!$I$8,0)))) | AQ107: =IF(C107="","",IF(AND(AP107<>"",TODAY()>=AP107),"Refi Ready",IF(TODAY()-C107>=SETTINGS!$I$11,"Prospecting","Performing"))) | AR107: =IF(OR(C107="",I107="",K107=""),"",IF(K107="Monthly",EDATE(C107,I107),WORKDAY(C107,I107))) | AT107: =IF(C107="","",IF(AM107="Clawed Back","CLAWED",IF(TODAY()<=C107+SETTINGS!$I$2,"⚠ AT RISK","SAFE"))) | AW107: =AW106+IF(AND(C107<>"",AO107<>"",OR('REP COMMISSION'!$B$3="",T107='REP COMMISSION'!$B$3,W107='REP COMMISSION'!$B$3,Z107='REP COMMISSION'!$B$3)),1,0) -> 0 | AX107: =AX106+IF(AND(C107<>"",OR(F107="LOC - INITIAL",F107="CONSOLIDATION - UPFRONT COMM",F107="REVERSE - TOTAL FUNDING")),1,0) -> 0
A108: =IF(C108<>"","F"&COUNT($C$4:C108),"") | B108: =IF(OR(F108="LOC - INITIAL",F108="CONSOLIDATION - UPFRONT COMM",F108="REVERSE - TOTAL FUNDING"),A108,"") | J108: =IF(AND(G108<>"",H108<>""),G108*H108,"") | N108: =IF(OR(G108="",M108=""),0,IF(M108>100,M108,G108*IF(M108>1,M108/100,M108))) -> 0 | O108: =IF(G108="","",G108*IF(L108="",0,IF(L108>1,L108/100,L108))+N108) | Q108: =IF(P108="","",IFERROR(VLOOKUP(P108,PARTNERS!$A$2:$B$30,2,0),"")) | R108: =IF(O108="","",IF(OR(P108="",Q108=""),0,(O108-N108)*IF(Q108>1,Q108/100,Q108))) | S108: =IF(O108="","",O108-R108) | U108: =IF(T108="","",IFERROR(VLOOKUP(T108,REPS!$A$2:$D$40,2,0),"")) | V108: =IF(O108="","",IF(U108="",0,O108*IF(U108>1,U108/100,U108))) | X108: =IF(W108="","",IFERROR(VLOOKUP(W108,REPS!$A$2:$D$40,3,0),"")) | Y108: =IF(O108="","",IF(X108="",0,O108*IF(X108>1,X108/100,X108))) | AA108: =IF(Z108="","",IFERROR(VLOOKUP(Z108,REPS!$A$2:$D$40,4,0),"")) | AB108: =IF(O108="","",IF(AA108="",0,O108*IF(AA108>1,AA108/100,AA108))) | AC108: =IF(O108="","",V108+Y108+AB108) | AD108: =IF(O108="","",O108-R108-AC108) | AG108: =IF(OR(AE108="",AE108=0),0,AE108*IF(U108="",0,IF(U108>1,U108/100,U108))) -> 0 | AH108: =IF(OR(AE108="",AE108=0),0,AE108*IF(X108="",0,IF(X108>1,X108/100,X108))) -> 0 | AI108: =IF(OR(AE108="",AE108=0),0,AE108*IF(AA108="",0,IF(AA108>1,AA108/100,AA108))) -> 0 | AJ108: =AG108+AH108+AI108 -> 0 | AK108: =IF(OR(AE108="",AE108=0),0,AE108-AJ108) -> 0 | AL108: =IF(AD108="","",AD108-AK108) | AM108: =IF(C108="","","Waiting for payment") | AP108: =IF(OR(C108="",I108="",K108=""),"",IF(K108="Monthly",EDATE(C108,ROUND(I108*SETTINGS!$I$8,0)),WORKDAY(C108,ROUND(I108*SETTINGS!$I$8,0)))) | AQ108: =IF(C108="","",IF(AND(AP108<>"",TODAY()>=AP108),"Refi Ready",IF(TODAY()-C108>=SETTINGS!$I$11,"Prospecting","Performing"))) | AR108: =IF(OR(C108="",I108="",K108=""),"",IF(K108="Monthly",EDATE(C108,I108),WORKDAY(C108,I108))) | AT108: =IF(C108="","",IF(AM108="Clawed Back","CLAWED",IF(TODAY()<=C108+SETTINGS!$I$2,"⚠ AT RISK","SAFE"))) | AW108: =AW107+IF(AND(C108<>"",AO108<>"",OR('REP COMMISSION'!$B$3="",T108='REP COMMISSION'!$B$3,W108='REP COMMISSION'!$B$3,Z108='REP COMMISSION'!$B$3)),1,0) -> 0 | AX108: =AX107+IF(AND(C108<>"",OR(F108="LOC - INITIAL",F108="CONSOLIDATION - UPFRONT COMM",F108="REVERSE - TOTAL FUNDING")),1,0) -> 0
A109: =IF(C109<>"","F"&COUNT($C$4:C109),"") | B109: =IF(OR(F109="LOC - INITIAL",F109="CONSOLIDATION - UPFRONT COMM",F109="REVERSE - TOTAL FUNDING"),A109,"") | J109: =IF(AND(G109<>"",H109<>""),G109*H109,"") | N109: =IF(OR(G109="",M109=""),0,IF(M109>100,M109,G109*IF(M109>1,M109/100,M109))) -> 0 | O109: =IF(G109="","",G109*IF(L109="",0,IF(L109>1,L109/100,L109))+N109) | Q109: =IF(P109="","",IFERROR(VLOOKUP(P109,PARTNERS!$A$2:$B$30,2,0),"")) | R109: =IF(O109="","",IF(OR(P109="",Q109=""),0,(O109-N109)*IF(Q109>1,Q109/100,Q109))) | S109: =IF(O109="","",O109-R109) | U109: =IF(T109="","",IFERROR(VLOOKUP(T109,REPS!$A$2:$D$40,2,0),"")) | V109: =IF(O109="","",IF(U109="",0,O109*IF(U109>1,U109/100,U109))) | X109: =IF(W109="","",IFERROR(VLOOKUP(W109,REPS!$A$2:$D$40,3,0),"")) | Y109: =IF(O109="","",IF(X109="",0,O109*IF(X109>1,X109/100,X109))) | AA109: =IF(Z109="","",IFERROR(VLOOKUP(Z109,REPS!$A$2:$D$40,4,0),"")) | AB109: =IF(O109="","",IF(AA109="",0,O109*IF(AA109>1,AA109/100,AA109))) | AC109: =IF(O109="","",V109+Y109+AB109) | AD109: =IF(O109="","",O109-R109-AC109) | AG109: =IF(OR(AE109="",AE109=0),0,AE109*IF(U109="",0,IF(U109>1,U109/100,U109))) -> 0 | AH109: =IF(OR(AE109="",AE109=0),0,AE109*IF(X109="",0,IF(X109>1,X109/100,X109))) -> 0 | AI109: =IF(OR(AE109="",AE109=0),0,AE109*IF(AA109="",0,IF(AA109>1,AA109/100,AA109))) -> 0 | AJ109: =AG109+AH109+AI109 -> 0 | AK109: =IF(OR(AE109="",AE109=0),0,AE109-AJ109) -> 0 | AL109: =IF(AD109="","",AD109-AK109) | AM109: =IF(C109="","","Waiting for payment") | AP109: =IF(OR(C109="",I109="",K109=""),"",IF(K109="Monthly",EDATE(C109,ROUND(I109*SETTINGS!$I$8,0)),WORKDAY(C109,ROUND(I109*SETTINGS!$I$8,0)))) | AQ109: =IF(C109="","",IF(AND(AP109<>"",TODAY()>=AP109),"Refi Ready",IF(TODAY()-C109>=SETTINGS!$I$11,"Prospecting","Performing"))) | AR109: =IF(OR(C109="",I109="",K109=""),"",IF(K109="Monthly",EDATE(C109,I109),WORKDAY(C109,I109))) | AT109: =IF(C109="","",IF(AM109="Clawed Back","CLAWED",IF(TODAY()<=C109+SETTINGS!$I$2,"⚠ AT RISK","SAFE"))) | AW109: =AW108+IF(AND(C109<>"",AO109<>"",OR('REP COMMISSION'!$B$3="",T109='REP COMMISSION'!$B$3,W109='REP COMMISSION'!$B$3,Z109='REP COMMISSION'!$B$3)),1,0) -> 0 | AX109: =AX108+IF(AND(C109<>"",OR(F109="LOC - INITIAL",F109="CONSOLIDATION - UPFRONT COMM",F109="REVERSE - TOTAL FUNDING")),1,0) -> 0
A110: =IF(C110<>"","F"&COUNT($C$4:C110),"") | B110: =IF(OR(F110="LOC - INITIAL",F110="CONSOLIDATION - UPFRONT COMM",F110="REVERSE - TOTAL FUNDING"),A110,"") | J110: =IF(AND(G110<>"",H110<>""),G110*H110,"") | N110: =IF(OR(G110="",M110=""),0,IF(M110>100,M110,G110*IF(M110>1,M110/100,M110))) -> 0 | O110: =IF(G110="","",G110*IF(L110="",0,IF(L110>1,L110/100,L110))+N110) | Q110: =IF(P110="","",IFERROR(VLOOKUP(P110,PARTNERS!$A$2:$B$30,2,0),"")) | R110: =IF(O110="","",IF(OR(P110="",Q110=""),0,(O110-N110)*IF(Q110>1,Q110/100,Q110))) | S110: =IF(O110="","",O110-R110) | U110: =IF(T110="","",IFERROR(VLOOKUP(T110,REPS!$A$2:$D$40,2,0),"")) | V110: =IF(O110="","",IF(U110="",0,O110*IF(U110>1,U110/100,U110))) | X110: =IF(W110="","",IFERROR(VLOOKUP(W110,REPS!$A$2:$D$40,3,0),"")) | Y110: =IF(O110="","",IF(X110="",0,O110*IF(X110>1,X110/100,X110))) | AA110: =IF(Z110="","",IFERROR(VLOOKUP(Z110,REPS!$A$2:$D$40,4,0),"")) | AB110: =IF(O110="","",IF(AA110="",0,O110*IF(AA110>1,AA110/100,AA110))) | AC110: =IF(O110="","",V110+Y110+AB110) | AD110: =IF(O110="","",O110-R110-AC110) | AG110: =IF(OR(AE110="",AE110=0),0,AE110*IF(U110="",0,IF(U110>1,U110/100,U110))) -> 0 | AH110: =IF(OR(AE110="",AE110=0),0,AE110*IF(X110="",0,IF(X110>1,X110/100,X110))) -> 0 | AI110: =IF(OR(AE110="",AE110=0),0,AE110*IF(AA110="",0,IF(AA110>1,AA110/100,AA110))) -> 0 | AJ110: =AG110+AH110+AI110 -> 0 | AK110: =IF(OR(AE110="",AE110=0),0,AE110-AJ110) -> 0 | AL110: =IF(AD110="","",AD110-AK110) | AM110: =IF(C110="","","Waiting for payment") | AP110: =IF(OR(C110="",I110="",K110=""),"",IF(K110="Monthly",EDATE(C110,ROUND(I110*SETTINGS!$I$8,0)),WORKDAY(C110,ROUND(I110*SETTINGS!$I$8,0)))) | AQ110: =IF(C110="","",IF(AND(AP110<>"",TODAY()>=AP110),"Refi Ready",IF(TODAY()-C110>=SETTINGS!$I$11,"Prospecting","Performing"))) | AR110: =IF(OR(C110="",I110="",K110=""),"",IF(K110="Monthly",EDATE(C110,I110),WORKDAY(C110,I110))) | AT110: =IF(C110="","",IF(AM110="Clawed Back","CLAWED",IF(TODAY()<=C110+SETTINGS!$I$2,"⚠ AT RISK","SAFE"))) | AW110: =AW109+IF(AND(C110<>"",AO110<>"",OR('REP COMMISSION'!$B$3="",T110='REP COMMISSION'!$B$3,W110='REP COMMISSION'!$B$3,Z110='REP COMMISSION'!$B$3)),1,0) -> 0 | AX110: =AX109+IF(AND(C110<>"",OR(F110="LOC - INITIAL",F110="CONSOLIDATION - UPFRONT COMM",F110="REVERSE - TOTAL FUNDING")),1,0) -> 0
A111: =IF(C111<>"","F"&COUNT($C$4:C111),"") | B111: =IF(OR(F111="LOC - INITIAL",F111="CONSOLIDATION - UPFRONT COMM",F111="REVERSE - TOTAL FUNDING"),A111,"") | J111: =IF(AND(G111<>"",H111<>""),G111*H111,"") | N111: =IF(OR(G111="",M111=""),0,IF(M111>100,M111,G111*IF(M111>1,M111/100,M111))) -> 0 | O111: =IF(G111="","",G111*IF(L111="",0,IF(L111>1,L111/100,L111))+N111) | Q111: =IF(P111="","",IFERROR(VLOOKUP(P111,PARTNERS!$A$2:$B$30,2,0),"")) | R111: =IF(O111="","",IF(OR(P111="",Q111=""),0,(O111-N111)*IF(Q111>1,Q111/100,Q111))) | S111: =IF(O111="","",O111-R111) | U111: =IF(T111="","",IFERROR(VLOOKUP(T111,REPS!$A$2:$D$40,2,0),"")) | V111: =IF(O111="","",IF(U111="",0,O111*IF(U111>1,U111/100,U111))) | X111: =IF(W111="","",IFERROR(VLOOKUP(W111,REPS!$A$2:$D$40,3,0),"")) | Y111: =IF(O111="","",IF(X111="",0,O111*IF(X111>1,X111/100,X111))) | AA111: =IF(Z111="","",IFERROR(VLOOKUP(Z111,REPS!$A$2:$D$40,4,0),"")) | AB111: =IF(O111="","",IF(AA111="",0,O111*IF(AA111>1,AA111/100,AA111))) | AC111: =IF(O111="","",V111+Y111+AB111) | AD111: =IF(O111="","",O111-R111-AC111) | AG111: =IF(OR(AE111="",AE111=0),0,AE111*IF(U111="",0,IF(U111>1,U111/100,U111))) -> 0 | AH111: =IF(OR(AE111="",AE111=0),0,AE111*IF(X111="",0,IF(X111>1,X111/100,X111))) -> 0 | AI111: =IF(OR(AE111="",AE111=0),0,AE111*IF(AA111="",0,IF(AA111>1,AA111/100,AA111))) -> 0 | AJ111: =AG111+AH111+AI111 -> 0 | AK111: =IF(OR(AE111="",AE111=0),0,AE111-AJ111) -> 0 | AL111: =IF(AD111="","",AD111-AK111) | AM111: =IF(C111="","","Waiting for payment") | AP111: =IF(OR(C111="",I111="",K111=""),"",IF(K111="Monthly",EDATE(C111,ROUND(I111*SETTINGS!$I$8,0)),WORKDAY(C111,ROUND(I111*SETTINGS!$I$8,0)))) | AQ111: =IF(C111="","",IF(AND(AP111<>"",TODAY()>=AP111),"Refi Ready",IF(TODAY()-C111>=SETTINGS!$I$11,"Prospecting","Performing"))) | AR111: =IF(OR(C111="",I111="",K111=""),"",IF(K111="Monthly",EDATE(C111,I111),WORKDAY(C111,I111))) | AT111: =IF(C111="","",IF(AM111="Clawed Back","CLAWED",IF(TODAY()<=C111+SETTINGS!$I$2,"⚠ AT RISK","SAFE"))) | AW111: =AW110+IF(AND(C111<>"",AO111<>"",OR('REP COMMISSION'!$B$3="",T111='REP COMMISSION'!$B$3,W111='REP COMMISSION'!$B$3,Z111='REP COMMISSION'!$B$3)),1,0) -> 0 | AX111: =AX110+IF(AND(C111<>"",OR(F111="LOC - INITIAL",F111="CONSOLIDATION - UPFRONT COMM",F111="REVERSE - TOTAL FUNDING")),1,0) -> 0
A112: =IF(C112<>"","F"&COUNT($C$4:C112),"") | B112: =IF(OR(F112="LOC - INITIAL",F112="CONSOLIDATION - UPFRONT COMM",F112="REVERSE - TOTAL FUNDING"),A112,"") | J112: =IF(AND(G112<>"",H112<>""),G112*H112,"") | N112: =IF(OR(G112="",M112=""),0,IF(M112>100,M112,G112*IF(M112>1,M112/100,M112))) -> 0 | O112: =IF(G112="","",G112*IF(L112="",0,IF(L112>1,L112/100,L112))+N112) | Q112: =IF(P112="","",IFERROR(VLOOKUP(P112,PARTNERS!$A$2:$B$30,2,0),"")) | R112: =IF(O112="","",IF(OR(P112="",Q112=""),0,(O112-N112)*IF(Q112>1,Q112/100,Q112))) | S112: =IF(O112="","",O112-R112) | U112: =IF(T112="","",IFERROR(VLOOKUP(T112,REPS!$A$2:$D$40,2,0),"")) | V112: =IF(O112="","",IF(U112="",0,O112*IF(U112>1,U112/100,U112))) | X112: =IF(W112="","",IFERROR(VLOOKUP(W112,REPS!$A$2:$D$40,3,0),"")) | Y112: =IF(O112="","",IF(X112="",0,O112*IF(X112>1,X112/100,X112))) | AA112: =IF(Z112="","",IFERROR(VLOOKUP(Z112,REPS!$A$2:$D$40,4,0),"")) | AB112: =IF(O112="","",IF(AA112="",0,O112*IF(AA112>1,AA112/100,AA112))) | AC112: =IF(O112="","",V112+Y112+AB112) | AD112: =IF(O112="","",O112-R112-AC112) | AG112: =IF(OR(AE112="",AE112=0),0,AE112*IF(U112="",0,IF(U112>1,U112/100,U112))) -> 0 | AH112: =IF(OR(AE112="",AE112=0),0,AE112*IF(X112="",0,IF(X112>1,X112/100,X112))) -> 0 | AI112: =IF(OR(AE112="",AE112=0),0,AE112*IF(AA112="",0,IF(AA112>1,AA112/100,AA112))) -> 0 | AJ112: =AG112+AH112+AI112 -> 0 | AK112: =IF(OR(AE112="",AE112=0),0,AE112-AJ112) -> 0 | AL112: =IF(AD112="","",AD112-AK112) | AM112: =IF(C112="","","Waiting for payment") | AP112: =IF(OR(C112="",I112="",K112=""),"",IF(K112="Monthly",EDATE(C112,ROUND(I112*SETTINGS!$I$8,0)),WORKDAY(C112,ROUND(I112*SETTINGS!$I$8,0)))) | AQ112: =IF(C112="","",IF(AND(AP112<>"",TODAY()>=AP112),"Refi Ready",IF(TODAY()-C112>=SETTINGS!$I$11,"Prospecting","Performing"))) | AR112: =IF(OR(C112="",I112="",K112=""),"",IF(K112="Monthly",EDATE(C112,I112),WORKDAY(C112,I112))) | AT112: =IF(C112="","",IF(AM112="Clawed Back","CLAWED",IF(TODAY()<=C112+SETTINGS!$I$2,"⚠ AT RISK","SAFE"))) | AW112: =AW111+IF(AND(C112<>"",AO112<>"",OR('REP COMMISSION'!$B$3="",T112='REP COMMISSION'!$B$3,W112='REP COMMISSION'!$B$3,Z112='REP COMMISSION'!$B$3)),1,0) -> 0 | AX112: =AX111+IF(AND(C112<>"",OR(F112="LOC - INITIAL",F112="CONSOLIDATION - UPFRONT COMM",F112="REVERSE - TOTAL FUNDING")),1,0) -> 0
A113: =IF(C113<>"","F"&COUNT($C$4:C113),"") | B113: =IF(OR(F113="LOC - INITIAL",F113="CONSOLIDATION - UPFRONT COMM",F113="REVERSE - TOTAL FUNDING"),A113,"") | J113: =IF(AND(G113<>"",H113<>""),G113*H113,"") | N113: =IF(OR(G113="",M113=""),0,IF(M113>100,M113,G113*IF(M113>1,M113/100,M113))) -> 0 | O113: =IF(G113="","",G113*IF(L113="",0,IF(L113>1,L113/100,L113))+N113) | Q113: =IF(P113="","",IFERROR(VLOOKUP(P113,PARTNERS!$A$2:$B$30,2,0),"")) | R113: =IF(O113="","",IF(OR(P113="",Q113=""),0,(O113-N113)*IF(Q113>1,Q113/100,Q113))) | S113: =IF(O113="","",O113-R113) | U113: =IF(T113="","",IFERROR(VLOOKUP(T113,REPS!$A$2:$D$40,2,0),"")) | V113: =IF(O113="","",IF(U113="",0,O113*IF(U113>1,U113/100,U113))) | X113: =IF(W113="","",IFERROR(VLOOKUP(W113,REPS!$A$2:$D$40,3,0),"")) | Y113: =IF(O113="","",IF(X113="",0,O113*IF(X113>1,X113/100,X113))) | AA113: =IF(Z113="","",IFERROR(VLOOKUP(Z113,REPS!$A$2:$D$40,4,0),"")) | AB113: =IF(O113="","",IF(AA113="",0,O113*IF(AA113>1,AA113/100,AA113))) | AC113: =IF(O113="","",V113+Y113+AB113) | AD113: =IF(O113="","",O113-R113-AC113) | AG113: =IF(OR(AE113="",AE113=0),0,AE113*IF(U113="",0,IF(U113>1,U113/100,U113))) -> 0 | AH113: =IF(OR(AE113="",AE113=0),0,AE113*IF(X113="",0,IF(X113>1,X113/100,X113))) -> 0 | AI113: =IF(OR(AE113="",AE113=0),0,AE113*IF(AA113="",0,IF(AA113>1,AA113/100,AA113))) -> 0 | AJ113: =AG113+AH113+AI113 -> 0 | AK113: =IF(OR(AE113="",AE113=0),0,AE113-AJ113) -> 0 | AL113: =IF(AD113="","",AD113-AK113) | AM113: =IF(C113="","","Waiting for payment") | AP113: =IF(OR(C113="",I113="",K113=""),"",IF(K113="Monthly",EDATE(C113,ROUND(I113*SETTINGS!$I$8,0)),WORKDAY(C113,ROUND(I113*SETTINGS!$I$8,0)))) | AQ113: =IF(C113="","",IF(AND(AP113<>"",TODAY()>=AP113),"Refi Ready",IF(TODAY()-C113>=SETTINGS!$I$11,"Prospecting","Performing"))) | AR113: =IF(OR(C113="",I113="",K113=""),"",IF(K113="Monthly",EDATE(C113,I113),WORKDAY(C113,I113))) | AT113: =IF(C113="","",IF(AM113="Clawed Back","CLAWED",IF(TODAY()<=C113+SETTINGS!$I$2,"⚠ AT RISK","SAFE"))) | AW113: =AW112+IF(AND(C113<>"",AO113<>"",OR('REP COMMISSION'!$B$3="",T113='REP COMMISSION'!$B$3,W113='REP COMMISSION'!$B$3,Z113='REP COMMISSION'!$B$3)),1,0) -> 0 | AX113: =AX112+IF(AND(C113<>"",OR(F113="LOC - INITIAL",F113="CONSOLIDATION - UPFRONT COMM",F113="REVERSE - TOTAL FUNDING")),1,0) -> 0
A114: =IF(C114<>"","F"&COUNT($C$4:C114),"") | B114: =IF(OR(F114="LOC - INITIAL",F114="CONSOLIDATION - UPFRONT COMM",F114="REVERSE - TOTAL FUNDING"),A114,"") | J114: =IF(AND(G114<>"",H114<>""),G114*H114,"") | N114: =IF(OR(G114="",M114=""),0,IF(M114>100,M114,G114*IF(M114>1,M114/100,M114))) -> 0 | O114: =IF(G114="","",G114*IF(L114="",0,IF(L114>1,L114/100,L114))+N114) | Q114: =IF(P114="","",IFERROR(VLOOKUP(P114,PARTNERS!$A$2:$B$30,2,0),"")) | R114: =IF(O114="","",IF(OR(P114="",Q114=""),0,(O114-N114)*IF(Q114>1,Q114/100,Q114))) | S114: =IF(O114="","",O114-R114) | U114: =IF(T114="","",IFERROR(VLOOKUP(T114,REPS!$A$2:$D$40,2,0),"")) | V114: =IF(O114="","",IF(U114="",0,O114*IF(U114>1,U114/100,U114))) | X114: =IF(W114="","",IFERROR(VLOOKUP(W114,REPS!$A$2:$D$40,3,0),"")) | Y114: =IF(O114="","",IF(X114="",0,O114*IF(X114>1,X114/100,X114))) | AA114: =IF(Z114="","",IFERROR(VLOOKUP(Z114,REPS!$A$2:$D$40,4,0),"")) | AB114: =IF(O114="","",IF(AA114="",0,O114*IF(AA114>1,AA114/100,AA114))) | AC114: =IF(O114="","",V114+Y114+AB114) | AD114: =IF(O114="","",O114-R114-AC114) | AG114: =IF(OR(AE114="",AE114=0),0,AE114*IF(U114="",0,IF(U114>1,U114/100,U114))) -> 0 | AH114: =IF(OR(AE114="",AE114=0),0,AE114*IF(X114="",0,IF(X114>1,X114/100,X114))) -> 0 | AI114: =IF(OR(AE114="",AE114=0),0,AE114*IF(AA114="",0,IF(AA114>1,AA114/100,AA114))) -> 0 | AJ114: =AG114+AH114+AI114 -> 0 | AK114: =IF(OR(AE114="",AE114=0),0,AE114-AJ114) -> 0 | AL114: =IF(AD114="","",AD114-AK114) | AM114: =IF(C114="","","Waiting for payment") | AP114: =IF(OR(C114="",I114="",K114=""),"",IF(K114="Monthly",EDATE(C114,ROUND(I114*SETTINGS!$I$8,0)),WORKDAY(C114,ROUND(I114*SETTINGS!$I$8,0)))) | AQ114: =IF(C114="","",IF(AND(AP114<>"",TODAY()>=AP114),"Refi Ready",IF(TODAY()-C114>=SETTINGS!$I$11,"Prospecting","Performing"))) | AR114: =IF(OR(C114="",I114="",K114=""),"",IF(K114="Monthly",EDATE(C114,I114),WORKDAY(C114,I114))) | AT114: =IF(C114="","",IF(AM114="Clawed Back","CLAWED",IF(TODAY()<=C114+SETTINGS!$I$2,"⚠ AT RISK","SAFE"))) | AW114: =AW113+IF(AND(C114<>"",AO114<>"",OR('REP COMMISSION'!$B$3="",T114='REP COMMISSION'!$B$3,W114='REP COMMISSION'!$B$3,Z114='REP COMMISSION'!$B$3)),1,0) -> 0 | AX114: =AX113+IF(AND(C114<>"",OR(F114="LOC - INITIAL",F114="CONSOLIDATION - UPFRONT COMM",F114="REVERSE - TOTAL FUNDING")),1,0) -> 0
A115: =IF(C115<>"","F"&COUNT($C$4:C115),"") | B115: =IF(OR(F115="LOC - INITIAL",F115="CONSOLIDATION - UPFRONT COMM",F115="REVERSE - TOTAL FUNDING"),A115,"") | J115: =IF(AND(G115<>"",H115<>""),G115*H115,"") | N115: =IF(OR(G115="",M115=""),0,IF(M115>100,M115,G115*IF(M115>1,M115/100,M115))) -> 0 | O115: =IF(G115="","",G115*IF(L115="",0,IF(L115>1,L115/100,L115))+N115) | Q115: =IF(P115="","",IFERROR(VLOOKUP(P115,PARTNERS!$A$2:$B$30,2,0),"")) | R115: =IF(O115="","",IF(OR(P115="",Q115=""),0,(O115-N115)*IF(Q115>1,Q115/100,Q115))) | S115: =IF(O115="","",O115-R115) | U115: =IF(T115="","",IFERROR(VLOOKUP(T115,REPS!$A$2:$D$40,2,0),"")) | V115: =IF(O115="","",IF(U115="",0,O115*IF(U115>1,U115/100,U115))) | X115: =IF(W115="","",IFERROR(VLOOKUP(W115,REPS!$A$2:$D$40,3,0),"")) | Y115: =IF(O115="","",IF(X115="",0,O115*IF(X115>1,X115/100,X115))) | AA115: =IF(Z115="","",IFERROR(VLOOKUP(Z115,REPS!$A$2:$D$40,4,0),"")) | AB115: =IF(O115="","",IF(AA115="",0,O115*IF(AA115>1,AA115/100,AA115))) | AC115: =IF(O115="","",V115+Y115+AB115) | AD115: =IF(O115="","",O115-R115-AC115) | AG115: =IF(OR(AE115="",AE115=0),0,AE115*IF(U115="",0,IF(U115>1,U115/100,U115))) -> 0 | AH115: =IF(OR(AE115="",AE115=0),0,AE115*IF(X115="",0,IF(X115>1,X115/100,X115))) -> 0 | AI115: =IF(OR(AE115="",AE115=0),0,AE115*IF(AA115="",0,IF(AA115>1,AA115/100,AA115))) -> 0 | AJ115: =AG115+AH115+AI115 -> 0 | AK115: =IF(OR(AE115="",AE115=0),0,AE115-AJ115) -> 0 | AL115: =IF(AD115="","",AD115-AK115) | AM115: =IF(C115="","","Waiting for payment") | AP115: =IF(OR(C115="",I115="",K115=""),"",IF(K115="Monthly",EDATE(C115,ROUND(I115*SETTINGS!$I$8,0)),WORKDAY(C115,ROUND(I115*SETTINGS!$I$8,0)))) | AQ115: =IF(C115="","",IF(AND(AP115<>"",TODAY()>=AP115),"Refi Ready",IF(TODAY()-C115>=SETTINGS!$I$11,"Prospecting","Performing"))) | AR115: =IF(OR(C115="",I115="",K115=""),"",IF(K115="Monthly",EDATE(C115,I115),WORKDAY(C115,I115))) | AT115: =IF(C115="","",IF(AM115="Clawed Back","CLAWED",IF(TODAY()<=C115+SETTINGS!$I$2,"⚠ AT RISK","SAFE"))) | AW115: =AW114+IF(AND(C115<>"",AO115<>"",OR('REP COMMISSION'!$B$3="",T115='REP COMMISSION'!$B$3,W115='REP COMMISSION'!$B$3,Z115='REP COMMISSION'!$B$3)),1,0) -> 0 | AX115: =AX114+IF(AND(C115<>"",OR(F115="LOC - INITIAL",F115="CONSOLIDATION - UPFRONT COMM",F115="REVERSE - TOTAL FUNDING")),1,0) -> 0
A116: =IF(C116<>"","F"&COUNT($C$4:C116),"") | B116: =IF(OR(F116="LOC - INITIAL",F116="CONSOLIDATION - UPFRONT COMM",F116="REVERSE - TOTAL FUNDING"),A116,"") | J116: =IF(AND(G116<>"",H116<>""),G116*H116,"") | N116: =IF(OR(G116="",M116=""),0,IF(M116>100,M116,G116*IF(M116>1,M116/100,M116))) -> 0 | O116: =IF(G116="","",G116*IF(L116="",0,IF(L116>1,L116/100,L116))+N116) | Q116: =IF(P116="","",IFERROR(VLOOKUP(P116,PARTNERS!$A$2:$B$30,2,0),"")) | R116: =IF(O116="","",IF(OR(P116="",Q116=""),0,(O116-N116)*IF(Q116>1,Q116/100,Q116))) | S116: =IF(O116="","",O116-R116) | U116: =IF(T116="","",IFERROR(VLOOKUP(T116,REPS!$A$2:$D$40,2,0),"")) | V116: =IF(O116="","",IF(U116="",0,O116*IF(U116>1,U116/100,U116))) | X116: =IF(W116="","",IFERROR(VLOOKUP(W116,REPS!$A$2:$D$40,3,0),"")) | Y116: =IF(O116="","",IF(X116="",0,O116*IF(X116>1,X116/100,X116))) | AA116: =IF(Z116="","",IFERROR(VLOOKUP(Z116,REPS!$A$2:$D$40,4,0),"")) | AB116: =IF(O116="","",IF(AA116="",0,O116*IF(AA116>1,AA116/100,AA116))) | AC116: =IF(O116="","",V116+Y116+AB116) | AD116: =IF(O116="","",O116-R116-AC116) | AG116: =IF(OR(AE116="",AE116=0),0,AE116*IF(U116="",0,IF(U116>1,U116/100,U116))) -> 0 | AH116: =IF(OR(AE116="",AE116=0),0,AE116*IF(X116="",0,IF(X116>1,X116/100,X116))) -> 0 | AI116: =IF(OR(AE116="",AE116=0),0,AE116*IF(AA116="",0,IF(AA116>1,AA116/100,AA116))) -> 0 | AJ116: =AG116+AH116+AI116 -> 0 | AK116: =IF(OR(AE116="",AE116=0),0,AE116-AJ116) -> 0 | AL116: =IF(AD116="","",AD116-AK116) | AM116: =IF(C116="","","Waiting for payment") | AP116: =IF(OR(C116="",I116="",K116=""),"",IF(K116="Monthly",EDATE(C116,ROUND(I116*SETTINGS!$I$8,0)),WORKDAY(C116,ROUND(I116*SETTINGS!$I$8,0)))) | AQ116: =IF(C116="","",IF(AND(AP116<>"",TODAY()>=AP116),"Refi Ready",IF(TODAY()-C116>=SETTINGS!$I$11,"Prospecting","Performing"))) | AR116: =IF(OR(C116="",I116="",K116=""),"",IF(K116="Monthly",EDATE(C116,I116),WORKDAY(C116,I116))) | AT116: =IF(C116="","",IF(AM116="Clawed Back","CLAWED",IF(TODAY()<=C116+SETTINGS!$I$2,"⚠ AT RISK","SAFE"))) | AW116: =AW115+IF(AND(C116<>"",AO116<>"",OR('REP COMMISSION'!$B$3="",T116='REP COMMISSION'!$B$3,W116='REP COMMISSION'!$B$3,Z116='REP COMMISSION'!$B$3)),1,0) -> 0 | AX116: =AX115+IF(AND(C116<>"",OR(F116="LOC - INITIAL",F116="CONSOLIDATION - UPFRONT COMM",F116="REVERSE - TOTAL FUNDING")),1,0) -> 0
A117: =IF(C117<>"","F"&COUNT($C$4:C117),"") | B117: =IF(OR(F117="LOC - INITIAL",F117="CONSOLIDATION - UPFRONT COMM",F117="REVERSE - TOTAL FUNDING"),A117,"") | J117: =IF(AND(G117<>"",H117<>""),G117*H117,"") | N117: =IF(OR(G117="",M117=""),0,IF(M117>100,M117,G117*IF(M117>1,M117/100,M117))) -> 0 | O117: =IF(G117="","",G117*IF(L117="",0,IF(L117>1,L117/100,L117))+N117) | Q117: =IF(P117="","",IFERROR(VLOOKUP(P117,PARTNERS!$A$2:$B$30,2,0),"")) | R117: =IF(O117="","",IF(OR(P117="",Q117=""),0,(O117-N117)*IF(Q117>1,Q117/100,Q117))) | S117: =IF(O117="","",O117-R117) | U117: =IF(T117="","",IFERROR(VLOOKUP(T117,REPS!$A$2:$D$40,2,0),"")) | V117: =IF(O117="","",IF(U117="",0,O117*IF(U117>1,U117/100,U117))) | X117: =IF(W117="","",IFERROR(VLOOKUP(W117,REPS!$A$2:$D$40,3,0),"")) | Y117: =IF(O117="","",IF(X117="",0,O117*IF(X117>1,X117/100,X117))) | AA117: =IF(Z117="","",IFERROR(VLOOKUP(Z117,REPS!$A$2:$D$40,4,0),"")) | AB117: =IF(O117="","",IF(AA117="",0,O117*IF(AA117>1,AA117/100,AA117))) | AC117: =IF(O117="","",V117+Y117+AB117) | AD117: =IF(O117="","",O117-R117-AC117) | AG117: =IF(OR(AE117="",AE117=0),0,AE117*IF(U117="",0,IF(U117>1,U117/100,U117))) -> 0 | AH117: =IF(OR(AE117="",AE117=0),0,AE117*IF(X117="",0,IF(X117>1,X117/100,X117))) -> 0 | AI117: =IF(OR(AE117="",AE117=0),0,AE117*IF(AA117="",0,IF(AA117>1,AA117/100,AA117))) -> 0 | AJ117: =AG117+AH117+AI117 -> 0 | AK117: =IF(OR(AE117="",AE117=0),0,AE117-AJ117) -> 0 | AL117: =IF(AD117="","",AD117-AK117) | AM117: =IF(C117="","","Waiting for payment") | AP117: =IF(OR(C117="",I117="",K117=""),"",IF(K117="Monthly",EDATE(C117,ROUND(I117*SETTINGS!$I$8,0)),WORKDAY(C117,ROUND(I117*SETTINGS!$I$8,0)))) | AQ117: =IF(C117="","",IF(AND(AP117<>"",TODAY()>=AP117),"Refi Ready",IF(TODAY()-C117>=SETTINGS!$I$11,"Prospecting","Performing"))) | AR117: =IF(OR(C117="",I117="",K117=""),"",IF(K117="Monthly",EDATE(C117,I117),WORKDAY(C117,I117))) | AT117: =IF(C117="","",IF(AM117="Clawed Back","CLAWED",IF(TODAY()<=C117+SETTINGS!$I$2,"⚠ AT RISK","SAFE"))) | AW117: =AW116+IF(AND(C117<>"",AO117<>"",OR('REP COMMISSION'!$B$3="",T117='REP COMMISSION'!$B$3,W117='REP COMMISSION'!$B$3,Z117='REP COMMISSION'!$B$3)),1,0) -> 0 | AX117: =AX116+IF(AND(C117<>"",OR(F117="LOC - INITIAL",F117="CONSOLIDATION - UPFRONT COMM",F117="REVERSE - TOTAL FUNDING")),1,0) -> 0
... A205: =IF(C205<>"","F"&COUNT($C$4:C205),"") | B205: =IF(OR(F205="LOC - INITIAL",F205="CONSOLIDATION - UPFRONT COMM",F205="REVERSE - TOTAL FUNDING"),A205,"") | J205: =IF(AND(G205<>"",H205<>""),G205*H205,"") | N205: =IF(OR(G205="",M205=""),0,IF(M205>100,M205,G205*IF(M205>1,M205/100,M205))) -> 0 | O205: =IF(G205="","",G205*IF(L205="",0,IF(L205>1,L205/100,L205))+N205) | Q205: =IF(P205="","",IFERROR(VLOOKUP(P205,PARTNERS!$A$2:$B$30,2,0),"")) | R205: =IF(O205="","",IF(OR(P205="",Q205=""),0,(O205-N205)*IF(Q205>1,Q205/100,Q205))) | S205: =IF(O205="","",O205-R205) | U205: =IF(T205="","",IFERROR(VLOOKUP(T205,REPS!$A$2:$D$40,2,0),"")) | V205: =IF(O205="","",IF(U205="",0,O205*IF(U205>1,U205/100,U205))) | X205: =IF(W205="","",IFERROR(VLOOKUP(W205,REPS!$A$2:$D$40,3,0),"")) | Y205: =IF(O205="","",IF(X205="",0,O205*IF(X205>1,X205/100,X205))) | AA205: =IF(Z205="","",IFERROR(VLOOKUP(Z205,REPS!$A$2:$D$40,4,0),"")) | AB205: =IF(O205="","",IF(AA205="",0,O205*IF(AA205>1,AA205/100,AA205))) | AC205: =IF(O205="","",V205+Y205+AB205) | AD205: =IF(O205="","",O205-R205-AC205) | AG205: =IF(OR(AE205="",AE205=0),0,AE205*IF(U205="",0,IF(U205>1,U205/100,U205))) -> 0 | AH205: =IF(OR(AE205="",AE205=0),0,AE205*IF(X205="",0,IF(X205>1,X205/100,X205))) -> 0 | AI205: =IF(OR(AE205="",AE205=0),0,AE205*IF(AA205="",0,IF(AA205>1,AA205/100,AA205))) -> 0 | AJ205: =AG205+AH205+AI205 -> 0 | AK205: =IF(OR(AE205="",AE205=0),0,AE205-AJ205) -> 0 | AL205: =IF(AD205="","",AD205-AK205) | AM205: =IF(C205="","","Waiting for payment") | AP205: =IF(OR(C205="",I205="",K205=""),"",IF(K205="Monthly",EDATE(C205,ROUND(I205*SETTINGS!$I$8,0)),WORKDAY(C205,ROUND(I205*SETTINGS!$I$8,0)))) | AQ205: =IF(C205="","",IF(AND(AP205<>"",TODAY()>=AP205),"Refi Ready",IF(TODAY()-C205>=SETTINGS!$I$11,"Prospecting","Performing"))) | AR205: =IF(OR(C205="",I205="",K205=""),"",IF(K205="Monthly",EDATE(C205,I205),WORKDAY(C205,I205))) | AT205: =IF(C205="","",IF(AM205="Clawed Back","CLAWED",IF(TODAY()<=C205+SETTINGS!$I$2,"⚠ AT RISK","SAFE"))) | AW205: =AW204+IF(AND(C205<>"",AO205<>"",OR('REP COMMISSION'!$B$3="",T205='REP COMMISSION'!$B$3,W205='REP COMMISSION'!$B$3,Z205='REP COMMISSION'!$B$3)),1,0) -> 0 | AX205: =AX204+IF(AND(C205<>"",OR(F205="LOC - INITIAL",F205="CONSOLIDATION - UPFRONT COMM",F205="REVERSE - TOTAL FUNDING")),1,0) -> 0
A206: MAY TOTAL | D206: =COUNT(C106:C205)&" units" -> 0 units | G206: =SUM(G106:G205) -> 0 | N206: =SUM(N106:N205) -> 0 | O206: =SUM(O106:O205) -> 0 | R206: =SUM(R106:R205) -> 0 | S206: =SUM(S106:S205) -> 0 | AC206: =SUM(AC106:AC205) -> 0 | AD206: =SUM(AD106:AD205) -> 0 | AE206: =SUM(AE106:AE205) -> 0 | AJ206: =SUM(AJ106:AJ205) -> 0 | AK206: =SUM(AK106:AK205) -> 0 | AL206: =SUM(AL106:AL205) -> 0 | AW206: =AW205 -> 0 | AX206: =AX205 -> 0
A207: ▼ JUNE 2026 | AW207: =AW206 -> 0 | AX207: =AX206 -> 0
A208: =IF(C208<>"","F"&COUNT($C$4:C208),"") | B208: =IF(OR(F208="LOC - INITIAL",F208="CONSOLIDATION - UPFRONT COMM",F208="REVERSE - TOTAL FUNDING"),A208,"") | J208: =IF(AND(G208<>"",H208<>""),G208*H208,"") | N208: =IF(OR(G208="",M208=""),0,IF(M208>100,M208,G208*IF(M208>1,M208/100,M208))) -> 0 | O208: =IF(G208="","",G208*IF(L208="",0,IF(L208>1,L208/100,L208))+N208) | Q208: =IF(P208="","",IFERROR(VLOOKUP(P208,PARTNERS!$A$2:$B$30,2,0),"")) | R208: =IF(O208="","",IF(OR(P208="",Q208=""),0,(O208-N208)*IF(Q208>1,Q208/100,Q208))) | S208: =IF(O208="","",O208-R208) | U208: =IF(T208="","",IFERROR(VLOOKUP(T208,REPS!$A$2:$D$40,2,0),"")) | V208: =IF(O208="","",IF(U208="",0,O208*IF(U208>1,U208/100,U208))) | X208: =IF(W208="","",IFERROR(VLOOKUP(W208,REPS!$A$2:$D$40,3,0),"")) | Y208: =IF(O208="","",IF(X208="",0,O208*IF(X208>1,X208/100,X208))) | AA208: =IF(Z208="","",IFERROR(VLOOKUP(Z208,REPS!$A$2:$D$40,4,0),"")) | AB208: =IF(O208="","",IF(AA208="",0,O208*IF(AA208>1,AA208/100,AA208))) | AC208: =IF(O208="","",V208+Y208+AB208) | AD208: =IF(O208="","",O208-R208-AC208) | AG208: =IF(OR(AE208="",AE208=0),0,AE208*IF(U208="",0,IF(U208>1,U208/100,U208))) -> 0 | AH208: =IF(OR(AE208="",AE208=0),0,AE208*IF(X208="",0,IF(X208>1,X208/100,X208))) -> 0 | AI208: =IF(OR(AE208="",AE208=0),0,AE208*IF(AA208="",0,IF(AA208>1,AA208/100,AA208))) -> 0 | AJ208: =AG208+AH208+AI208 -> 0 | AK208: =IF(OR(AE208="",AE208=0),0,AE208-AJ208) -> 0 | AL208: =IF(AD208="","",AD208-AK208) | AM208: =IF(C208="","","Waiting for payment") | AP208: =IF(OR(C208="",I208="",K208=""),"",IF(K208="Monthly",EDATE(C208,ROUND(I208*SETTINGS!$I$8,0)),WORKDAY(C208,ROUND(I208*SETTINGS!$I$8,0)))) | AQ208: =IF(C208="","",IF(AND(AP208<>"",TODAY()>=AP208),"Refi Ready",IF(TODAY()-C208>=SETTINGS!$I$11,"Prospecting","Performing"))) | AR208: =IF(OR(C208="",I208="",K208=""),"",IF(K208="Monthly",EDATE(C208,I208),WORKDAY(C208,I208))) | AT208: =IF(C208="","",IF(AM208="Clawed Back","CLAWED",IF(TODAY()<=C208+SETTINGS!$I$2,"⚠ AT RISK","SAFE"))) | AW208: =AW207+IF(AND(C208<>"",AO208<>"",OR('REP COMMISSION'!$B$3="",T208='REP COMMISSION'!$B$3,W208='REP COMMISSION'!$B$3,Z208='REP COMMISSION'!$B$3)),1,0) -> 0 | AX208: =AX207+IF(AND(C208<>"",OR(F208="LOC - INITIAL",F208="CONSOLIDATION - UPFRONT COMM",F208="REVERSE - TOTAL FUNDING")),1,0) -> 0
A209: =IF(C209<>"","F"&COUNT($C$4:C209),"") | B209: =IF(OR(F209="LOC - INITIAL",F209="CONSOLIDATION - UPFRONT COMM",F209="REVERSE - TOTAL FUNDING"),A209,"") | J209: =IF(AND(G209<>"",H209<>""),G209*H209,"") | N209: =IF(OR(G209="",M209=""),0,IF(M209>100,M209,G209*IF(M209>1,M209/100,M209))) -> 0 | O209: =IF(G209="","",G209*IF(L209="",0,IF(L209>1,L209/100,L209))+N209) | Q209: =IF(P209="","",IFERROR(VLOOKUP(P209,PARTNERS!$A$2:$B$30,2,0),"")) | R209: =IF(O209="","",IF(OR(P209="",Q209=""),0,(O209-N209)*IF(Q209>1,Q209/100,Q209))) | S209: =IF(O209="","",O209-R209) | U209: =IF(T209="","",IFERROR(VLOOKUP(T209,REPS!$A$2:$D$40,2,0),"")) | V209: =IF(O209="","",IF(U209="",0,O209*IF(U209>1,U209/100,U209))) | X209: =IF(W209="","",IFERROR(VLOOKUP(W209,REPS!$A$2:$D$40,3,0),"")) | Y209: =IF(O209="","",IF(X209="",0,O209*IF(X209>1,X209/100,X209))) | AA209: =IF(Z209="","",IFERROR(VLOOKUP(Z209,REPS!$A$2:$D$40,4,0),"")) | AB209: =IF(O209="","",IF(AA209="",0,O209*IF(AA209>1,AA209/100,AA209))) | AC209: =IF(O209="","",V209+Y209+AB209) | AD209: =IF(O209="","",O209-R209-AC209) | AG209: =IF(OR(AE209="",AE209=0),0,AE209*IF(U209="",0,IF(U209>1,U209/100,U209))) -> 0 | AH209: =IF(OR(AE209="",AE209=0),0,AE209*IF(X209="",0,IF(X209>1,X209/100,X209))) -> 0 | AI209: =IF(OR(AE209="",AE209=0),0,AE209*IF(AA209="",0,IF(AA209>1,AA209/100,AA209))) -> 0 | AJ209: =AG209+AH209+AI209 -> 0 | AK209: =IF(OR(AE209="",AE209=0),0,AE209-AJ209) -> 0 | AL209: =IF(AD209="","",AD209-AK209) | AM209: =IF(C209="","","Waiting for payment") | AP209: =IF(OR(C209="",I209="",K209=""),"",IF(K209="Monthly",EDATE(C209,ROUND(I209*SETTINGS!$I$8,0)),WORKDAY(C209,ROUND(I209*SETTINGS!$I$8,0)))) | AQ209: =IF(C209="","",IF(AND(AP209<>"",TODAY()>=AP209),"Refi Ready",IF(TODAY()-C209>=SETTINGS!$I$11,"Prospecting","Performing"))) | AR209: =IF(OR(C209="",I209="",K209=""),"",IF(K209="Monthly",EDATE(C209,I209),WORKDAY(C209,I209))) | AT209: =IF(C209="","",IF(AM209="Clawed Back","CLAWED",IF(TODAY()<=C209+SETTINGS!$I$2,"⚠ AT RISK","SAFE"))) | AW209: =AW208+IF(AND(C209<>"",AO209<>"",OR('REP COMMISSION'!$B$3="",T209='REP COMMISSION'!$B$3,W209='REP COMMISSION'!$B$3,Z209='REP COMMISSION'!$B$3)),1,0) -> 0 | AX209: =AX208+IF(AND(C209<>"",OR(F209="LOC - INITIAL",F209="CONSOLIDATION - UPFRONT COMM",F209="REVERSE - TOTAL FUNDING")),1,0) -> 0
A210: =IF(C210<>"","F"&COUNT($C$4:C210),"") | B210: =IF(OR(F210="LOC - INITIAL",F210="CONSOLIDATION - UPFRONT COMM",F210="REVERSE - TOTAL FUNDING"),A210,"") | J210: =IF(AND(G210<>"",H210<>""),G210*H210,"") | N210: =IF(OR(G210="",M210=""),0,IF(M210>100,M210,G210*IF(M210>1,M210/100,M210))) -> 0 | O210: =IF(G210="","",G210*IF(L210="",0,IF(L210>1,L210/100,L210))+N210) | Q210: =IF(P210="","",IFERROR(VLOOKUP(P210,PARTNERS!$A$2:$B$30,2,0),"")) | R210: =IF(O210="","",IF(OR(P210="",Q210=""),0,(O210-N210)*IF(Q210>1,Q210/100,Q210))) | S210: =IF(O210="","",O210-R210) | U210: =IF(T210="","",IFERROR(VLOOKUP(T210,REPS!$A$2:$D$40,2,0),"")) | V210: =IF(O210="","",IF(U210="",0,O210*IF(U210>1,U210/100,U210))) | X210: =IF(W210="","",IFERROR(VLOOKUP(W210,REPS!$A$2:$D$40,3,0),"")) | Y210: =IF(O210="","",IF(X210="",0,O210*IF(X210>1,X210/100,X210))) | AA210: =IF(Z210="","",IFERROR(VLOOKUP(Z210,REPS!$A$2:$D$40,4,0),"")) | AB210: =IF(O210="","",IF(AA210="",0,O210*IF(AA210>1,AA210/100,AA210))) | AC210: =IF(O210="","",V210+Y210+AB210) | AD210: =IF(O210="","",O210-R210-AC210) | AG210: =IF(OR(AE210="",AE210=0),0,AE210*IF(U210="",0,IF(U210>1,U210/100,U210))) -> 0 | AH210: =IF(OR(AE210="",AE210=0),0,AE210*IF(X210="",0,IF(X210>1,X210/100,X210))) -> 0 | AI210: =IF(OR(AE210="",AE210=0),0,AE210*IF(AA210="",0,IF(AA210>1,AA210/100,AA210))) -> 0 | AJ210: =AG210+AH210+AI210 -> 0 | AK210: =IF(OR(AE210="",AE210=0),0,AE210-AJ210) -> 0 | AL210: =IF(AD210="","",AD210-AK210) | AM210: =IF(C210="","","Waiting for payment") | AP210: =IF(OR(C210="",I210="",K210=""),"",IF(K210="Monthly",EDATE(C210,ROUND(I210*SETTINGS!$I$8,0)),WORKDAY(C210,ROUND(I210*SETTINGS!$I$8,0)))) | AQ210: =IF(C210="","",IF(AND(AP210<>"",TODAY()>=AP210),"Refi Ready",IF(TODAY()-C210>=SETTINGS!$I$11,"Prospecting","Performing"))) | AR210: =IF(OR(C210="",I210="",K210=""),"",IF(K210="Monthly",EDATE(C210,I210),WORKDAY(C210,I210))) | AT210: =IF(C210="","",IF(AM210="Clawed Back","CLAWED",IF(TODAY()<=C210+SETTINGS!$I$2,"⚠ AT RISK","SAFE"))) | AW210: =AW209+IF(AND(C210<>"",AO210<>"",OR('REP COMMISSION'!$B$3="",T210='REP COMMISSION'!$B$3,W210='REP COMMISSION'!$B$3,Z210='REP COMMISSION'!$B$3)),1,0) -> 0 | AX210: =AX209+IF(AND(C210<>"",OR(F210="LOC - INITIAL",F210="CONSOLIDATION - UPFRONT COMM",F210="REVERSE - TOTAL FUNDING")),1,0) -> 0
A211: =IF(C211<>"","F"&COUNT($C$4:C211),"") | B211: =IF(OR(F211="LOC - INITIAL",F211="CONSOLIDATION - UPFRONT COMM",F211="REVERSE - TOTAL FUNDING"),A211,"") | J211: =IF(AND(G211<>"",H211<>""),G211*H211,"") | N211: =IF(OR(G211="",M211=""),0,IF(M211>100,M211,G211*IF(M211>1,M211/100,M211))) -> 0 | O211: =IF(G211="","",G211*IF(L211="",0,IF(L211>1,L211/100,L211))+N211) | Q211: =IF(P211="","",IFERROR(VLOOKUP(P211,PARTNERS!$A$2:$B$30,2,0),"")) | R211: =IF(O211="","",IF(OR(P211="",Q211=""),0,(O211-N211)*IF(Q211>1,Q211/100,Q211))) | S211: =IF(O211="","",O211-R211) | U211: =IF(T211="","",IFERROR(VLOOKUP(T211,REPS!$A$2:$D$40,2,0),"")) | V211: =IF(O211="","",IF(U211="",0,O211*IF(U211>1,U211/100,U211))) | X211: =IF(W211="","",IFERROR(VLOOKUP(W211,REPS!$A$2:$D$40,3,0),"")) | Y211: =IF(O211="","",IF(X211="",0,O211*IF(X211>1,X211/100,X211))) | AA211: =IF(Z211="","",IFERROR(VLOOKUP(Z211,REPS!$A$2:$D$40,4,0),"")) | AB211: =IF(O211="","",IF(AA211="",0,O211*IF(AA211>1,AA211/100,AA211))) | AC211: =IF(O211="","",V211+Y211+AB211) | AD211: =IF(O211="","",O211-R211-AC211) | AG211: =IF(OR(AE211="",AE211=0),0,AE211*IF(U211="",0,IF(U211>1,U211/100,U211))) -> 0 | AH211: =IF(OR(AE211="",AE211=0),0,AE211*IF(X211="",0,IF(X211>1,X211/100,X211))) -> 0 | AI211: =IF(OR(AE211="",AE211=0),0,AE211*IF(AA211="",0,IF(AA211>1,AA211/100,AA211))) -> 0 | AJ211: =AG211+AH211+AI211 -> 0 | AK211: =IF(OR(AE211="",AE211=0),0,AE211-AJ211) -> 0 | AL211: =IF(AD211="","",AD211-AK211) | AM211: =IF(C211="","","Waiting for payment") | AP211: =IF(OR(C211="",I211="",K211=""),"",IF(K211="Monthly",EDATE(C211,ROUND(I211*SETTINGS!$I$8,0)),WORKDAY(C211,ROUND(I211*SETTINGS!$I$8,0)))) | AQ211: =IF(C211="","",IF(AND(AP211<>"",TODAY()>=AP211),"Refi Ready",IF(TODAY()-C211>=SETTINGS!$I$11,"Prospecting","Performing"))) | AR211: =IF(OR(C211="",I211="",K211=""),"",IF(K211="Monthly",EDATE(C211,I211),WORKDAY(C211,I211))) | AT211: =IF(C211="","",IF(AM211="Clawed Back","CLAWED",IF(TODAY()<=C211+SETTINGS!$I$2,"⚠ AT RISK","SAFE"))) | AW211: =AW210+IF(AND(C211<>"",AO211<>"",OR('REP COMMISSION'!$B$3="",T211='REP COMMISSION'!$B$3,W211='REP COMMISSION'!$B$3,Z211='REP COMMISSION'!$B$3)),1,0) -> 0 | AX211: =AX210+IF(AND(C211<>"",OR(F211="LOC - INITIAL",F211="CONSOLIDATION - UPFRONT COMM",F211="REVERSE - TOTAL FUNDING")),1,0) -> 0
A212: =IF(C212<>"","F"&COUNT($C$4:C212),"") | B212: =IF(OR(F212="LOC - INITIAL",F212="CONSOLIDATION - UPFRONT COMM",F212="REVERSE - TOTAL FUNDING"),A212,"") | J212: =IF(AND(G212<>"",H212<>""),G212*H212,"") | N212: =IF(OR(G212="",M212=""),0,IF(M212>100,M212,G212*IF(M212>1,M212/100,M212))) -> 0 | O212: =IF(G212="","",G212*IF(L212="",0,IF(L212>1,L212/100,L212))+N212) | Q212: =IF(P212="","",IFERROR(VLOOKUP(P212,PARTNERS!$A$2:$B$30,2,0),"")) | R212: =IF(O212="","",IF(OR(P212="",Q212=""),0,(O212-N212)*IF(Q212>1,Q212/100,Q212))) | S212: =IF(O212="","",O212-R212) | U212: =IF(T212="","",IFERROR(VLOOKUP(T212,REPS!$A$2:$D$40,2,0),"")) | V212: =IF(O212="","",IF(U212="",0,O212*IF(U212>1,U212/100,U212))) | X212: =IF(W212="","",IFERROR(VLOOKUP(W212,REPS!$A$2:$D$40,3,0),"")) | Y212: =IF(O212="","",IF(X212="",0,O212*IF(X212>1,X212/100,X212))) | AA212: =IF(Z212="","",IFERROR(VLOOKUP(Z212,REPS!$A$2:$D$40,4,0),"")) | AB212: =IF(O212="","",IF(AA212="",0,O212*IF(AA212>1,AA212/100,AA212))) | AC212: =IF(O212="","",V212+Y212+AB212) | AD212: =IF(O212="","",O212-R212-AC212) | AG212: =IF(OR(AE212="",AE212=0),0,AE212*IF(U212="",0,IF(U212>1,U212/100,U212))) -> 0 | AH212: =IF(OR(AE212="",AE212=0),0,AE212*IF(X212="",0,IF(X212>1,X212/100,X212))) -> 0 | AI212: =IF(OR(AE212="",AE212=0),0,AE212*IF(AA212="",0,IF(AA212>1,AA212/100,AA212))) -> 0 | AJ212: =AG212+AH212+AI212 -> 0 | AK212: =IF(OR(AE212="",AE212=0),0,AE212-AJ212) -> 0 | AL212: =IF(AD212="","",AD212-AK212) | AM212: =IF(C212="","","Waiting for payment") | AP212: =IF(OR(C212="",I212="",K212=""),"",IF(K212="Monthly",EDATE(C212,ROUND(I212*SETTINGS!$I$8,0)),WORKDAY(C212,ROUND(I212*SETTINGS!$I$8,0)))) | AQ212: =IF(C212="","",IF(AND(AP212<>"",TODAY()>=AP212),"Refi Ready",IF(TODAY()-C212>=SETTINGS!$I$11,"Prospecting","Performing"))) | AR212: =IF(OR(C212="",I212="",K212=""),"",IF(K212="Monthly",EDATE(C212,I212),WORKDAY(C212,I212))) | AT212: =IF(C212="","",IF(AM212="Clawed Back","CLAWED",IF(TODAY()<=C212+SETTINGS!$I$2,"⚠ AT RISK","SAFE"))) | AW212: =AW211+IF(AND(C212<>"",AO212<>"",OR('REP COMMISSION'!$B$3="",T212='REP COMMISSION'!$B$3,W212='REP COMMISSION'!$B$3,Z212='REP COMMISSION'!$B$3)),1,0) -> 0 | AX212: =AX211+IF(AND(C212<>"",OR(F212="LOC - INITIAL",F212="CONSOLIDATION - UPFRONT COMM",F212="REVERSE - TOTAL FUNDING")),1,0) -> 0
A213: =IF(C213<>"","F"&COUNT($C$4:C213),"") | B213: =IF(OR(F213="LOC - INITIAL",F213="CONSOLIDATION - UPFRONT COMM",F213="REVERSE - TOTAL FUNDING"),A213,"") | J213: =IF(AND(G213<>"",H213<>""),G213*H213,"") | N213: =IF(OR(G213="",M213=""),0,IF(M213>100,M213,G213*IF(M213>1,M213/100,M213))) -> 0 | O213: =IF(G213="","",G213*IF(L213="",0,IF(L213>1,L213/100,L213))+N213) | Q213: =IF(P213="","",IFERROR(VLOOKUP(P213,PARTNERS!$A$2:$B$30,2,0),"")) | R213: =IF(O213="","",IF(OR(P213="",Q213=""),0,(O213-N213)*IF(Q213>1,Q213/100,Q213))) | S213: =IF(O213="","",O213-R213) | U213: =IF(T213="","",IFERROR(VLOOKUP(T213,REPS!$A$2:$D$40,2,0),"")) | V213: =IF(O213="","",IF(U213="",0,O213*IF(U213>1,U213/100,U213))) | X213: =IF(W213="","",IFERROR(VLOOKUP(W213,REPS!$A$2:$D$40,3,0),"")) | Y213: =IF(O213="","",IF(X213="",0,O213*IF(X213>1,X213/100,X213))) | AA213: =IF(Z213="","",IFERROR(VLOOKUP(Z213,REPS!$A$2:$D$40,4,0),"")) | AB213: =IF(O213="","",IF(AA213="",0,O213*IF(AA213>1,AA213/100,AA213))) | AC213: =IF(O213="","",V213+Y213+AB213) | AD213: =IF(O213="","",O213-R213-AC213) | AG213: =IF(OR(AE213="",AE213=0),0,AE213*IF(U213="",0,IF(U213>1,U213/100,U213))) -> 0 | AH213: =IF(OR(AE213="",AE213=0),0,AE213*IF(X213="",0,IF(X213>1,X213/100,X213))) -> 0 | AI213: =IF(OR(AE213="",AE213=0),0,AE213*IF(AA213="",0,IF(AA213>1,AA213/100,AA213))) -> 0 | AJ213: =AG213+AH213+AI213 -> 0 | AK213: =IF(OR(AE213="",AE213=0),0,AE213-AJ213) -> 0 | AL213: =IF(AD213="","",AD213-AK213) | AM213: =IF(C213="","","Waiting for payment") | AP213: =IF(OR(C213="",I213="",K213=""),"",IF(K213="Monthly",EDATE(C213,ROUND(I213*SETTINGS!$I$8,0)),WORKDAY(C213,ROUND(I213*SETTINGS!$I$8,0)))) | AQ213: =IF(C213="","",IF(AND(AP213<>"",TODAY()>=AP213),"Refi Ready",IF(TODAY()-C213>=SETTINGS!$I$11,"Prospecting","Performing"))) | AR213: =IF(OR(C213="",I213="",K213=""),"",IF(K213="Monthly",EDATE(C213,I213),WORKDAY(C213,I213))) | AT213: =IF(C213="","",IF(AM213="Clawed Back","CLAWED",IF(TODAY()<=C213+SETTINGS!$I$2,"⚠ AT RISK","SAFE"))) | AW213: =AW212+IF(AND(C213<>"",AO213<>"",OR('REP COMMISSION'!$B$3="",T213='REP COMMISSION'!$B$3,W213='REP COMMISSION'!$B$3,Z213='REP COMMISSION'!$B$3)),1,0) -> 0 | AX213: =AX212+IF(AND(C213<>"",OR(F213="LOC - INITIAL",F213="CONSOLIDATION - UPFRONT COMM",F213="REVERSE - TOTAL FUNDING")),1,0) -> 0
A214: =IF(C214<>"","F"&COUNT($C$4:C214),"") | B214: =IF(OR(F214="LOC - INITIAL",F214="CONSOLIDATION - UPFRONT COMM",F214="REVERSE - TOTAL FUNDING"),A214,"") | J214: =IF(AND(G214<>"",H214<>""),G214*H214,"") | N214: =IF(OR(G214="",M214=""),0,IF(M214>100,M214,G214*IF(M214>1,M214/100,M214))) -> 0 | O214: =IF(G214="","",G214*IF(L214="",0,IF(L214>1,L214/100,L214))+N214) | Q214: =IF(P214="","",IFERROR(VLOOKUP(P214,PARTNERS!$A$2:$B$30,2,0),"")) | R214: =IF(O214="","",IF(OR(P214="",Q214=""),0,(O214-N214)*IF(Q214>1,Q214/100,Q214))) | S214: =IF(O214="","",O214-R214) | U214: =IF(T214="","",IFERROR(VLOOKUP(T214,REPS!$A$2:$D$40,2,0),"")) | V214: =IF(O214="","",IF(U214="",0,O214*IF(U214>1,U214/100,U214))) | X214: =IF(W214="","",IFERROR(VLOOKUP(W214,REPS!$A$2:$D$40,3,0),"")) | Y214: =IF(O214="","",IF(X214="",0,O214*IF(X214>1,X214/100,X214))) | AA214: =IF(Z214="","",IFERROR(VLOOKUP(Z214,REPS!$A$2:$D$40,4,0),"")) | AB214: =IF(O214="","",IF(AA214="",0,O214*IF(AA214>1,AA214/100,AA214))) | AC214: =IF(O214="","",V214+Y214+AB214) | AD214: =IF(O214="","",O214-R214-AC214) | AG214: =IF(OR(AE214="",AE214=0),0,AE214*IF(U214="",0,IF(U214>1,U214/100,U214))) -> 0 | AH214: =IF(OR(AE214="",AE214=0),0,AE214*IF(X214="",0,IF(X214>1,X214/100,X214))) -> 0 | AI214: =IF(OR(AE214="",AE214=0),0,AE214*IF(AA214="",0,IF(AA214>1,AA214/100,AA214))) -> 0 | AJ214: =AG214+AH214+AI214 -> 0 | AK214: =IF(OR(AE214="",AE214=0),0,AE214-AJ214) -> 0 | AL214: =IF(AD214="","",AD214-AK214) | AM214: =IF(C214="","","Waiting for payment") | AP214: =IF(OR(C214="",I214="",K214=""),"",IF(K214="Monthly",EDATE(C214,ROUND(I214*SETTINGS!$I$8,0)),WORKDAY(C214,ROUND(I214*SETTINGS!$I$8,0)))) | AQ214: =IF(C214="","",IF(AND(AP214<>"",TODAY()>=AP214),"Refi Ready",IF(TODAY()-C214>=SETTINGS!$I$11,"Prospecting","Performing"))) | AR214: =IF(OR(C214="",I214="",K214=""),"",IF(K214="Monthly",EDATE(C214,I214),WORKDAY(C214,I214))) | AT214: =IF(C214="","",IF(AM214="Clawed Back","CLAWED",IF(TODAY()<=C214+SETTINGS!$I$2,"⚠ AT RISK","SAFE"))) | AW214: =AW213+IF(AND(C214<>"",AO214<>"",OR('REP COMMISSION'!$B$3="",T214='REP COMMISSION'!$B$3,W214='REP COMMISSION'!$B$3,Z214='REP COMMISSION'!$B$3)),1,0) -> 0 | AX214: =AX213+IF(AND(C214<>"",OR(F214="LOC - INITIAL",F214="CONSOLIDATION - UPFRONT COMM",F214="REVERSE - TOTAL FUNDING")),1,0) -> 0
A215: =IF(C215<>"","F"&COUNT($C$4:C215),"") | B215: =IF(OR(F215="LOC - INITIAL",F215="CONSOLIDATION - UPFRONT COMM",F215="REVERSE - TOTAL FUNDING"),A215,"") | J215: =IF(AND(G215<>"",H215<>""),G215*H215,"") | N215: =IF(OR(G215="",M215=""),0,IF(M215>100,M215,G215*IF(M215>1,M215/100,M215))) -> 0 | O215: =IF(G215="","",G215*IF(L215="",0,IF(L215>1,L215/100,L215))+N215) | Q215: =IF(P215="","",IFERROR(VLOOKUP(P215,PARTNERS!$A$2:$B$30,2,0),"")) | R215: =IF(O215="","",IF(OR(P215="",Q215=""),0,(O215-N215)*IF(Q215>1,Q215/100,Q215))) | S215: =IF(O215="","",O215-R215) | U215: =IF(T215="","",IFERROR(VLOOKUP(T215,REPS!$A$2:$D$40,2,0),"")) | V215: =IF(O215="","",IF(U215="",0,O215*IF(U215>1,U215/100,U215))) | X215: =IF(W215="","",IFERROR(VLOOKUP(W215,REPS!$A$2:$D$40,3,0),"")) | Y215: =IF(O215="","",IF(X215="",0,O215*IF(X215>1,X215/100,X215))) | AA215: =IF(Z215="","",IFERROR(VLOOKUP(Z215,REPS!$A$2:$D$40,4,0),"")) | AB215: =IF(O215="","",IF(AA215="",0,O215*IF(AA215>1,AA215/100,AA215))) | AC215: =IF(O215="","",V215+Y215+AB215) | AD215: =IF(O215="","",O215-R215-AC215) | AG215: =IF(OR(AE215="",AE215=0),0,AE215*IF(U215="",0,IF(U215>1,U215/100,U215))) -> 0 | AH215: =IF(OR(AE215="",AE215=0),0,AE215*IF(X215="",0,IF(X215>1,X215/100,X215))) -> 0 | AI215: =IF(OR(AE215="",AE215=0),0,AE215*IF(AA215="",0,IF(AA215>1,AA215/100,AA215))) -> 0 | AJ215: =AG215+AH215+AI215 -> 0 | AK215: =IF(OR(AE215="",AE215=0),0,AE215-AJ215) -> 0 | AL215: =IF(AD215="","",AD215-AK215) | AM215: =IF(C215="","","Waiting for payment") | AP215: =IF(OR(C215="",I215="",K215=""),"",IF(K215="Monthly",EDATE(C215,ROUND(I215*SETTINGS!$I$8,0)),WORKDAY(C215,ROUND(I215*SETTINGS!$I$8,0)))) | AQ215: =IF(C215="","",IF(AND(AP215<>"",TODAY()>=AP215),"Refi Ready",IF(TODAY()-C215>=SETTINGS!$I$11,"Prospecting","Performing"))) | AR215: =IF(OR(C215="",I215="",K215=""),"",IF(K215="Monthly",EDATE(C215,I215),WORKDAY(C215,I215))) | AT215: =IF(C215="","",IF(AM215="Clawed Back","CLAWED",IF(TODAY()<=C215+SETTINGS!$I$2,"⚠ AT RISK","SAFE"))) | AW215: =AW214+IF(AND(C215<>"",AO215<>"",OR('REP COMMISSION'!$B$3="",T215='REP COMMISSION'!$B$3,W215='REP COMMISSION'!$B$3,Z215='REP COMMISSION'!$B$3)),1,0) -> 0 | AX215: =AX214+IF(AND(C215<>"",OR(F215="LOC - INITIAL",F215="CONSOLIDATION - UPFRONT COMM",F215="REVERSE - TOTAL FUNDING")),1,0) -> 0
A216: =IF(C216<>"","F"&COUNT($C$4:C216),"") | B216: =IF(OR(F216="LOC - INITIAL",F216="CONSOLIDATION - UPFRONT COMM",F216="REVERSE - TOTAL FUNDING"),A216,"") | J216: =IF(AND(G216<>"",H216<>""),G216*H216,"") | N216: =IF(OR(G216="",M216=""),0,IF(M216>100,M216,G216*IF(M216>1,M216/100,M216))) -> 0 | O216: =IF(G216="","",G216*IF(L216="",0,IF(L216>1,L216/100,L216))+N216) | Q216: =IF(P216="","",IFERROR(VLOOKUP(P216,PARTNERS!$A$2:$B$30,2,0),"")) | R216: =IF(O216="","",IF(OR(P216="",Q216=""),0,(O216-N216)*IF(Q216>1,Q216/100,Q216))) | S216: =IF(O216="","",O216-R216) | U216: =IF(T216="","",IFERROR(VLOOKUP(T216,REPS!$A$2:$D$40,2,0),"")) | V216: =IF(O216="","",IF(U216="",0,O216*IF(U216>1,U216/100,U216))) | X216: =IF(W216="","",IFERROR(VLOOKUP(W216,REPS!$A$2:$D$40,3,0),"")) | Y216: =IF(O216="","",IF(X216="",0,O216*IF(X216>1,X216/100,X216))) | AA216: =IF(Z216="","",IFERROR(VLOOKUP(Z216,REPS!$A$2:$D$40,4,0),"")) | AB216: =IF(O216="","",IF(AA216="",0,O216*IF(AA216>1,AA216/100,AA216))) | AC216: =IF(O216="","",V216+Y216+AB216) | AD216: =IF(O216="","",O216-R216-AC216) | AG216: =IF(OR(AE216="",AE216=0),0,AE216*IF(U216="",0,IF(U216>1,U216/100,U216))) -> 0 | AH216: =IF(OR(AE216="",AE216=0),0,AE216*IF(X216="",0,IF(X216>1,X216/100,X216))) -> 0 | AI216: =IF(OR(AE216="",AE216=0),0,AE216*IF(AA216="",0,IF(AA216>1,AA216/100,AA216))) -> 0 | AJ216: =AG216+AH216+AI216 -> 0 | AK216: =IF(OR(AE216="",AE216=0),0,AE216-AJ216) -> 0 | AL216: =IF(AD216="","",AD216-AK216) | AM216: =IF(C216="","","Waiting for payment") | AP216: =IF(OR(C216="",I216="",K216=""),"",IF(K216="Monthly",EDATE(C216,ROUND(I216*SETTINGS!$I$8,0)),WORKDAY(C216,ROUND(I216*SETTINGS!$I$8,0)))) | AQ216: =IF(C216="","",IF(AND(AP216<>"",TODAY()>=AP216),"Refi Ready",IF(TODAY()-C216>=SETTINGS!$I$11,"Prospecting","Performing"))) | AR216: =IF(OR(C216="",I216="",K216=""),"",IF(K216="Monthly",EDATE(C216,I216),WORKDAY(C216,I216))) | AT216: =IF(C216="","",IF(AM216="Clawed Back","CLAWED",IF(TODAY()<=C216+SETTINGS!$I$2,"⚠ AT RISK","SAFE"))) | AW216: =AW215+IF(AND(C216<>"",AO216<>"",OR('REP COMMISSION'!$B$3="",T216='REP COMMISSION'!$B$3,W216='REP COMMISSION'!$B$3,Z216='REP COMMISSION'!$B$3)),1,0) -> 0 | AX216: =AX215+IF(AND(C216<>"",OR(F216="LOC - INITIAL",F216="CONSOLIDATION - UPFRONT COMM",F216="REVERSE - TOTAL FUNDING")),1,0) -> 0
A217: =IF(C217<>"","F"&COUNT($C$4:C217),"") | B217: =IF(OR(F217="LOC - INITIAL",F217="CONSOLIDATION - UPFRONT COMM",F217="REVERSE - TOTAL FUNDING"),A217,"") | J217: =IF(AND(G217<>"",H217<>""),G217*H217,"") | N217: =IF(OR(G217="",M217=""),0,IF(M217>100,M217,G217*IF(M217>1,M217/100,M217))) -> 0 | O217: =IF(G217="","",G217*IF(L217="",0,IF(L217>1,L217/100,L217))+N217) | Q217: =IF(P217="","",IFERROR(VLOOKUP(P217,PARTNERS!$A$2:$B$30,2,0),"")) | R217: =IF(O217="","",IF(OR(P217="",Q217=""),0,(O217-N217)*IF(Q217>1,Q217/100,Q217))) | S217: =IF(O217="","",O217-R217) | U217: =IF(T217="","",IFERROR(VLOOKUP(T217,REPS!$A$2:$D$40,2,0),"")) | V217: =IF(O217="","",IF(U217="",0,O217*IF(U217>1,U217/100,U217))) | X217: =IF(W217="","",IFERROR(VLOOKUP(W217,REPS!$A$2:$D$40,3,0),"")) | Y217: =IF(O217="","",IF(X217="",0,O217*IF(X217>1,X217/100,X217))) | AA217: =IF(Z217="","",IFERROR(VLOOKUP(Z217,REPS!$A$2:$D$40,4,0),"")) | AB217: =IF(O217="","",IF(AA217="",0,O217*IF(AA217>1,AA217/100,AA217))) | AC217: =IF(O217="","",V217+Y217+AB217) | AD217: =IF(O217="","",O217-R217-AC217) | AG217: =IF(OR(AE217="",AE217=0),0,AE217*IF(U217="",0,IF(U217>1,U217/100,U217))) -> 0 | AH217: =IF(OR(AE217="",AE217=0),0,AE217*IF(X217="",0,IF(X217>1,X217/100,X217))) -> 0 | AI217: =IF(OR(AE217="",AE217=0),0,AE217*IF(AA217="",0,IF(AA217>1,AA217/100,AA217))) -> 0 | AJ217: =AG217+AH217+AI217 -> 0 | AK217: =IF(OR(AE217="",AE217=0),0,AE217-AJ217) -> 0 | AL217: =IF(AD217="","",AD217-AK217) | AM217: =IF(C217="","","Waiting for payment") | AP217: =IF(OR(C217="",I217="",K217=""),"",IF(K217="Monthly",EDATE(C217,ROUND(I217*SETTINGS!$I$8,0)),WORKDAY(C217,ROUND(I217*SETTINGS!$I$8,0)))) | AQ217: =IF(C217="","",IF(AND(AP217<>"",TODAY()>=AP217),"Refi Ready",IF(TODAY()-C217>=SETTINGS!$I$11,"Prospecting","Performing"))) | AR217: =IF(OR(C217="",I217="",K217=""),"",IF(K217="Monthly",EDATE(C217,I217),WORKDAY(C217,I217))) | AT217: =IF(C217="","",IF(AM217="Clawed Back","CLAWED",IF(TODAY()<=C217+SETTINGS!$I$2,"⚠ AT RISK","SAFE"))) | AW217: =AW216+IF(AND(C217<>"",AO217<>"",OR('REP COMMISSION'!$B$3="",T217='REP COMMISSION'!$B$3,W217='REP COMMISSION'!$B$3,Z217='REP COMMISSION'!$B$3)),1,0) -> 0 | AX217: =AX216+IF(AND(C217<>"",OR(F217="LOC - INITIAL",F217="CONSOLIDATION - UPFRONT COMM",F217="REVERSE - TOTAL FUNDING")),1,0) -> 0
A218: =IF(C218<>"","F"&COUNT($C$4:C218),"") | B218: =IF(OR(F218="LOC - INITIAL",F218="CONSOLIDATION - UPFRONT COMM",F218="REVERSE - TOTAL FUNDING"),A218,"") | J218: =IF(AND(G218<>"",H218<>""),G218*H218,"") | N218: =IF(OR(G218="",M218=""),0,IF(M218>100,M218,G218*IF(M218>1,M218/100,M218))) -> 0 | O218: =IF(G218="","",G218*IF(L218="",0,IF(L218>1,L218/100,L218))+N218) | Q218: =IF(P218="","",IFERROR(VLOOKUP(P218,PARTNERS!$A$2:$B$30,2,0),"")) | R218: =IF(O218="","",IF(OR(P218="",Q218=""),0,(O218-N218)*IF(Q218>1,Q218/100,Q218))) | S218: =IF(O218="","",O218-R218) | U218: =IF(T218="","",IFERROR(VLOOKUP(T218,REPS!$A$2:$D$40,2,0),"")) | V218: =IF(O218="","",IF(U218="",0,O218*IF(U218>1,U218/100,U218))) | X218: =IF(W218="","",IFERROR(VLOOKUP(W218,REPS!$A$2:$D$40,3,0),"")) | Y218: =IF(O218="","",IF(X218="",0,O218*IF(X218>1,X218/100,X218))) | AA218: =IF(Z218="","",IFERROR(VLOOKUP(Z218,REPS!$A$2:$D$40,4,0),"")) | AB218: =IF(O218="","",IF(AA218="",0,O218*IF(AA218>1,AA218/100,AA218))) | AC218: =IF(O218="","",V218+Y218+AB218) | AD218: =IF(O218="","",O218-R218-AC218) | AG218: =IF(OR(AE218="",AE218=0),0,AE218*IF(U218="",0,IF(U218>1,U218/100,U218))) -> 0 | AH218: =IF(OR(AE218="",AE218=0),0,AE218*IF(X218="",0,IF(X218>1,X218/100,X218))) -> 0 | AI218: =IF(OR(AE218="",AE218=0),0,AE218*IF(AA218="",0,IF(AA218>1,AA218/100,AA218))) -> 0 | AJ218: =AG218+AH218+AI218 -> 0 | AK218: =IF(OR(AE218="",AE218=0),0,AE218-AJ218) -> 0 | AL218: =IF(AD218="","",AD218-AK218) | AM218: =IF(C218="","","Waiting for payment") | AP218: =IF(OR(C218="",I218="",K218=""),"",IF(K218="Monthly",EDATE(C218,ROUND(I218*SETTINGS!$I$8,0)),WORKDAY(C218,ROUND(I218*SETTINGS!$I$8,0)))) | AQ218: =IF(C218="","",IF(AND(AP218<>"",TODAY()>=AP218),"Refi Ready",IF(TODAY()-C218>=SETTINGS!$I$11,"Prospecting","Performing"))) | AR218: =IF(OR(C218="",I218="",K218=""),"",IF(K218="Monthly",EDATE(C218,I218),WORKDAY(C218,I218))) | AT218: =IF(C218="","",IF(AM218="Clawed Back","CLAWED",IF(TODAY()<=C218+SETTINGS!$I$2,"⚠ AT RISK","SAFE"))) | AW218: =AW217+IF(AND(C218<>"",AO218<>"",OR('REP COMMISSION'!$B$3="",T218='REP COMMISSION'!$B$3,W218='REP COMMISSION'!$B$3,Z218='REP COMMISSION'!$B$3)),1,0) -> 0 | AX218: =AX217+IF(AND(C218<>"",OR(F218="LOC - INITIAL",F218="CONSOLIDATION - UPFRONT COMM",F218="REVERSE - TOTAL FUNDING")),1,0) -> 0
A219: =IF(C219<>"","F"&COUNT($C$4:C219),"") | B219: =IF(OR(F219="LOC - INITIAL",F219="CONSOLIDATION - UPFRONT COMM",F219="REVERSE - TOTAL FUNDING"),A219,"") | J219: =IF(AND(G219<>"",H219<>""),G219*H219,"") | N219: =IF(OR(G219="",M219=""),0,IF(M219>100,M219,G219*IF(M219>1,M219/100,M219))) -> 0 | O219: =IF(G219="","",G219*IF(L219="",0,IF(L219>1,L219/100,L219))+N219) | Q219: =IF(P219="","",IFERROR(VLOOKUP(P219,PARTNERS!$A$2:$B$30,2,0),"")) | R219: =IF(O219="","",IF(OR(P219="",Q219=""),0,(O219-N219)*IF(Q219>1,Q219/100,Q219))) | S219: =IF(O219="","",O219-R219) | U219: =IF(T219="","",IFERROR(VLOOKUP(T219,REPS!$A$2:$D$40,2,0),"")) | V219: =IF(O219="","",IF(U219="",0,O219*IF(U219>1,U219/100,U219))) | X219: =IF(W219="","",IFERROR(VLOOKUP(W219,REPS!$A$2:$D$40,3,0),"")) | Y219: =IF(O219="","",IF(X219="",0,O219*IF(X219>1,X219/100,X219))) | AA219: =IF(Z219="","",IFERROR(VLOOKUP(Z219,REPS!$A$2:$D$40,4,0),"")) | AB219: =IF(O219="","",IF(AA219="",0,O219*IF(AA219>1,AA219/100,AA219))) | AC219: =IF(O219="","",V219+Y219+AB219) | AD219: =IF(O219="","",O219-R219-AC219) | AG219: =IF(OR(AE219="",AE219=0),0,AE219*IF(U219="",0,IF(U219>1,U219/100,U219))) -> 0 | AH219: =IF(OR(AE219="",AE219=0),0,AE219*IF(X219="",0,IF(X219>1,X219/100,X219))) -> 0 | AI219: =IF(OR(AE219="",AE219=0),0,AE219*IF(AA219="",0,IF(AA219>1,AA219/100,AA219))) -> 0 | AJ219: =AG219+AH219+AI219 -> 0 | AK219: =IF(OR(AE219="",AE219=0),0,AE219-AJ219) -> 0 | AL219: =IF(AD219="","",AD219-AK219) | AM219: =IF(C219="","","Waiting for payment") | AP219: =IF(OR(C219="",I219="",K219=""),"",IF(K219="Monthly",EDATE(C219,ROUND(I219*SETTINGS!$I$8,0)),WORKDAY(C219,ROUND(I219*SETTINGS!$I$8,0)))) | AQ219: =IF(C219="","",IF(AND(AP219<>"",TODAY()>=AP219),"Refi Ready",IF(TODAY()-C219>=SETTINGS!$I$11,"Prospecting","Performing"))) | AR219: =IF(OR(C219="",I219="",K219=""),"",IF(K219="Monthly",EDATE(C219,I219),WORKDAY(C219,I219))) | AT219: =IF(C219="","",IF(AM219="Clawed Back","CLAWED",IF(TODAY()<=C219+SETTINGS!$I$2,"⚠ AT RISK","SAFE"))) | AW219: =AW218+IF(AND(C219<>"",AO219<>"",OR('REP COMMISSION'!$B$3="",T219='REP COMMISSION'!$B$3,W219='REP COMMISSION'!$B$3,Z219='REP COMMISSION'!$B$3)),1,0) -> 0 | AX219: =AX218+IF(AND(C219<>"",OR(F219="LOC - INITIAL",F219="CONSOLIDATION - UPFRONT COMM",F219="REVERSE - TOTAL FUNDING")),1,0) -> 0
... A307: =IF(C307<>"","F"&COUNT($C$4:C307),"") | B307: =IF(OR(F307="LOC - INITIAL",F307="CONSOLIDATION - UPFRONT COMM",F307="REVERSE - TOTAL FUNDING"),A307,"") | J307: =IF(AND(G307<>"",H307<>""),G307*H307,"") | N307: =IF(OR(G307="",M307=""),0,IF(M307>100,M307,G307*IF(M307>1,M307/100,M307))) -> 0 | O307: =IF(G307="","",G307*IF(L307="",0,IF(L307>1,L307/100,L307))+N307) | Q307: =IF(P307="","",IFERROR(VLOOKUP(P307,PARTNERS!$A$2:$B$30,2,0),"")) | R307: =IF(O307="","",IF(OR(P307="",Q307=""),0,(O307-N307)*IF(Q307>1,Q307/100,Q307))) | S307: =IF(O307="","",O307-R307) | U307: =IF(T307="","",IFERROR(VLOOKUP(T307,REPS!$A$2:$D$40,2,0),"")) | V307: =IF(O307="","",IF(U307="",0,O307*IF(U307>1,U307/100,U307))) | X307: =IF(W307="","",IFERROR(VLOOKUP(W307,REPS!$A$2:$D$40,3,0),"")) | Y307: =IF(O307="","",IF(X307="",0,O307*IF(X307>1,X307/100,X307))) | AA307: =IF(Z307="","",IFERROR(VLOOKUP(Z307,REPS!$A$2:$D$40,4,0),"")) | AB307: =IF(O307="","",IF(AA307="",0,O307*IF(AA307>1,AA307/100,AA307))) | AC307: =IF(O307="","",V307+Y307+AB307) | AD307: =IF(O307="","",O307-R307-AC307) | AG307: =IF(OR(AE307="",AE307=0),0,AE307*IF(U307="",0,IF(U307>1,U307/100,U307))) -> 0 | AH307: =IF(OR(AE307="",AE307=0),0,AE307*IF(X307="",0,IF(X307>1,X307/100,X307))) -> 0 | AI307: =IF(OR(AE307="",AE307=0),0,AE307*IF(AA307="",0,IF(AA307>1,AA307/100,AA307))) -> 0 | AJ307: =AG307+AH307+AI307 -> 0 | AK307: =IF(OR(AE307="",AE307=0),0,AE307-AJ307) -> 0 | AL307: =IF(AD307="","",AD307-AK307) | AM307: =IF(C307="","","Waiting for payment") | AP307: =IF(OR(C307="",I307="",K307=""),"",IF(K307="Monthly",EDATE(C307,ROUND(I307*SETTINGS!$I$8,0)),WORKDAY(C307,ROUND(I307*SETTINGS!$I$8,0)))) | AQ307: =IF(C307="","",IF(AND(AP307<>"",TODAY()>=AP307),"Refi Ready",IF(TODAY()-C307>=SETTINGS!$I$11,"Prospecting","Performing"))) | AR307: =IF(OR(C307="",I307="",K307=""),"",IF(K307="Monthly",EDATE(C307,I307),WORKDAY(C307,I307))) | AT307: =IF(C307="","",IF(AM307="Clawed Back","CLAWED",IF(TODAY()<=C307+SETTINGS!$I$2,"⚠ AT RISK","SAFE"))) | AW307: =AW306+IF(AND(C307<>"",AO307<>"",OR('REP COMMISSION'!$B$3="",T307='REP COMMISSION'!$B$3,W307='REP COMMISSION'!$B$3,Z307='REP COMMISSION'!$B$3)),1,0) -> 0 | AX307: =AX306+IF(AND(C307<>"",OR(F307="LOC - INITIAL",F307="CONSOLIDATION - UPFRONT COMM",F307="REVERSE - TOTAL FUNDING")),1,0) -> 0
A308: JUNE TOTAL | D308: =COUNT(C208:C307)&" units" -> 0 units | G308: =SUM(G208:G307) -> 0 | N308: =SUM(N208:N307) -> 0 | O308: =SUM(O208:O307) -> 0 | R308: =SUM(R208:R307) -> 0 | S308: =SUM(S208:S307) -> 0 | AC308: =SUM(AC208:AC307) -> 0 | AD308: =SUM(AD208:AD307) -> 0 | AE308: =SUM(AE208:AE307) -> 0 | AJ308: =SUM(AJ208:AJ307) -> 0 | AK308: =SUM(AK208:AK307) -> 0 | AL308: =SUM(AL208:AL307) -> 0 | AW308: =AW307 -> 0 | AX308: =AX307 -> 0
A309: ▼ JULY 2026 | AW309: =AW308 -> 0 | AX309: =AX308 -> 0
A310: =IF(C310<>"","F"&COUNT($C$4:C310),"") | B310: =IF(OR(F310="LOC - INITIAL",F310="CONSOLIDATION - UPFRONT COMM",F310="REVERSE - TOTAL FUNDING"),A310,"") | J310: =IF(AND(G310<>"",H310<>""),G310*H310,"") | N310: =IF(OR(G310="",M310=""),0,IF(M310>100,M310,G310*IF(M310>1,M310/100,M310))) -> 0 | O310: =IF(G310="","",G310*IF(L310="",0,IF(L310>1,L310/100,L310))+N310) | Q310: =IF(P310="","",IFERROR(VLOOKUP(P310,PARTNERS!$A$2:$B$30,2,0),"")) | R310: =IF(O310="","",IF(OR(P310="",Q310=""),0,(O310-N310)*IF(Q310>1,Q310/100,Q310))) | S310: =IF(O310="","",O310-R310) | U310: =IF(T310="","",IFERROR(VLOOKUP(T310,REPS!$A$2:$D$40,2,0),"")) | V310: =IF(O310="","",IF(U310="",0,O310*IF(U310>1,U310/100,U310))) | X310: =IF(W310="","",IFERROR(VLOOKUP(W310,REPS!$A$2:$D$40,3,0),"")) | Y310: =IF(O310="","",IF(X310="",0,O310*IF(X310>1,X310/100,X310))) | AA310: =IF(Z310="","",IFERROR(VLOOKUP(Z310,REPS!$A$2:$D$40,4,0),"")) | AB310: =IF(O310="","",IF(AA310="",0,O310*IF(AA310>1,AA310/100,AA310))) | AC310: =IF(O310="","",V310+Y310+AB310) | AD310: =IF(O310="","",O310-R310-AC310) | AG310: =IF(OR(AE310="",AE310=0),0,AE310*IF(U310="",0,IF(U310>1,U310/100,U310))) -> 0 | AH310: =IF(OR(AE310="",AE310=0),0,AE310*IF(X310="",0,IF(X310>1,X310/100,X310))) -> 0 | AI310: =IF(OR(AE310="",AE310=0),0,AE310*IF(AA310="",0,IF(AA310>1,AA310/100,AA310))) -> 0 | AJ310: =AG310+AH310+AI310 -> 0 | AK310: =IF(OR(AE310="",AE310=0),0,AE310-AJ310) -> 0 | AL310: =IF(AD310="","",AD310-AK310) | AM310: =IF(C310="","","Waiting for payment") | AP310: =IF(OR(C310="",I310="",K310=""),"",IF(K310="Monthly",EDATE(C310,ROUND(I310*SETTINGS!$I$8,0)),WORKDAY(C310,ROUND(I310*SETTINGS!$I$8,0)))) | AQ310: =IF(C310="","",IF(AND(AP310<>"",TODAY()>=AP310),"Refi Ready",IF(TODAY()-C310>=SETTINGS!$I$11,"Prospecting","Performing"))) | AR310: =IF(OR(C310="",I310="",K310=""),"",IF(K310="Monthly",EDATE(C310,I310),WORKDAY(C310,I310))) | AT310: =IF(C310="","",IF(AM310="Clawed Back","CLAWED",IF(TODAY()<=C310+SETTINGS!$I$2,"⚠ AT RISK","SAFE"))) | AW310: =AW309+IF(AND(C310<>"",AO310<>"",OR('REP COMMISSION'!$B$3="",T310='REP COMMISSION'!$B$3,W310='REP COMMISSION'!$B$3,Z310='REP COMMISSION'!$B$3)),1,0) -> 0 | AX310: =AX309+IF(AND(C310<>"",OR(F310="LOC - INITIAL",F310="CONSOLIDATION - UPFRONT COMM",F310="REVERSE - TOTAL FUNDING")),1,0) -> 0
A311: =IF(C311<>"","F"&COUNT($C$4:C311),"") | B311: =IF(OR(F311="LOC - INITIAL",F311="CONSOLIDATION - UPFRONT COMM",F311="REVERSE - TOTAL FUNDING"),A311,"") | J311: =IF(AND(G311<>"",H311<>""),G311*H311,"") | N311: =IF(OR(G311="",M311=""),0,IF(M311>100,M311,G311*IF(M311>1,M311/100,M311))) -> 0 | O311: =IF(G311="","",G311*IF(L311="",0,IF(L311>1,L311/100,L311))+N311) | Q311: =IF(P311="","",IFERROR(VLOOKUP(P311,PARTNERS!$A$2:$B$30,2,0),"")) | R311: =IF(O311="","",IF(OR(P311="",Q311=""),0,(O311-N311)*IF(Q311>1,Q311/100,Q311))) | S311: =IF(O311="","",O311-R311) | U311: =IF(T311="","",IFERROR(VLOOKUP(T311,REPS!$A$2:$D$40,2,0),"")) | V311: =IF(O311="","",IF(U311="",0,O311*IF(U311>1,U311/100,U311))) | X311: =IF(W311="","",IFERROR(VLOOKUP(W311,REPS!$A$2:$D$40,3,0),"")) | Y311: =IF(O311="","",IF(X311="",0,O311*IF(X311>1,X311/100,X311))) | AA311: =IF(Z311="","",IFERROR(VLOOKUP(Z311,REPS!$A$2:$D$40,4,0),"")) | AB311: =IF(O311="","",IF(AA311="",0,O311*IF(AA311>1,AA311/100,AA311))) | AC311: =IF(O311="","",V311+Y311+AB311) | AD311: =IF(O311="","",O311-R311-AC311) | AG311: =IF(OR(AE311="",AE311=0),0,AE311*IF(U311="",0,IF(U311>1,U311/100,U311))) -> 0 | AH311: =IF(OR(AE311="",AE311=0),0,AE311*IF(X311="",0,IF(X311>1,X311/100,X311))) -> 0 | AI311: =IF(OR(AE311="",AE311=0),0,AE311*IF(AA311="",0,IF(AA311>1,AA311/100,AA311))) -> 0 | AJ311: =AG311+AH311+AI311 -> 0 | AK311: =IF(OR(AE311="",AE311=0),0,AE311-AJ311) -> 0 | AL311: =IF(AD311="","",AD311-AK311) | AM311: =IF(C311="","","Waiting for payment") | AP311: =IF(OR(C311="",I311="",K311=""),"",IF(K311="Monthly",EDATE(C311,ROUND(I311*SETTINGS!$I$8,0)),WORKDAY(C311,ROUND(I311*SETTINGS!$I$8,0)))) | AQ311: =IF(C311="","",IF(AND(AP311<>"",TODAY()>=AP311),"Refi Ready",IF(TODAY()-C311>=SETTINGS!$I$11,"Prospecting","Performing"))) | AR311: =IF(OR(C311="",I311="",K311=""),"",IF(K311="Monthly",EDATE(C311,I311),WORKDAY(C311,I311))) | AT311: =IF(C311="","",IF(AM311="Clawed Back","CLAWED",IF(TODAY()<=C311+SETTINGS!$I$2,"⚠ AT RISK","SAFE"))) | AW311: =AW310+IF(AND(C311<>"",AO311<>"",OR('REP COMMISSION'!$B$3="",T311='REP COMMISSION'!$B$3,W311='REP COMMISSION'!$B$3,Z311='REP COMMISSION'!$B$3)),1,0) -> 0 | AX311: =AX310+IF(AND(C311<>"",OR(F311="LOC - INITIAL",F311="CONSOLIDATION - UPFRONT COMM",F311="REVERSE - TOTAL FUNDING")),1,0) -> 0
A312: =IF(C312<>"","F"&COUNT($C$4:C312),"") | B312: =IF(OR(F312="LOC - INITIAL",F312="CONSOLIDATION - UPFRONT COMM",F312="REVERSE - TOTAL FUNDING"),A312,"") | J312: =IF(AND(G312<>"",H312<>""),G312*H312,"") | N312: =IF(OR(G312="",M312=""),0,IF(M312>100,M312,G312*IF(M312>1,M312/100,M312))) -> 0 | O312: =IF(G312="","",G312*IF(L312="",0,IF(L312>1,L312/100,L312))+N312) | Q312: =IF(P312="","",IFERROR(VLOOKUP(P312,PARTNERS!$A$2:$B$30,2,0),"")) | R312: =IF(O312="","",IF(OR(P312="",Q312=""),0,(O312-N312)*IF(Q312>1,Q312/100,Q312))) | S312: =IF(O312="","",O312-R312) | U312: =IF(T312="","",IFERROR(VLOOKUP(T312,REPS!$A$2:$D$40,2,0),"")) | V312: =IF(O312="","",IF(U312="",0,O312*IF(U312>1,U312/100,U312))) | X312: =IF(W312="","",IFERROR(VLOOKUP(W312,REPS!$A$2:$D$40,3,0),"")) | Y312: =IF(O312="","",IF(X312="",0,O312*IF(X312>1,X312/100,X312))) | AA312: =IF(Z312="","",IFERROR(VLOOKUP(Z312,REPS!$A$2:$D$40,4,0),"")) | AB312: =IF(O312="","",IF(AA312="",0,O312*IF(AA312>1,AA312/100,AA312))) | AC312: =IF(O312="","",V312+Y312+AB312) | AD312: =IF(O312="","",O312-R312-AC312) | AG312: =IF(OR(AE312="",AE312=0),0,AE312*IF(U312="",0,IF(U312>1,U312/100,U312))) -> 0 | AH312: =IF(OR(AE312="",AE312=0),0,AE312*IF(X312="",0,IF(X312>1,X312/100,X312))) -> 0 | AI312: =IF(OR(AE312="",AE312=0),0,AE312*IF(AA312="",0,IF(AA312>1,AA312/100,AA312))) -> 0 | AJ312: =AG312+AH312+AI312 -> 0 | AK312: =IF(OR(AE312="",AE312=0),0,AE312-AJ312) -> 0 | AL312: =IF(AD312="","",AD312-AK312) | AM312: =IF(C312="","","Waiting for payment") | AP312: =IF(OR(C312="",I312="",K312=""),"",IF(K312="Monthly",EDATE(C312,ROUND(I312*SETTINGS!$I$8,0)),WORKDAY(C312,ROUND(I312*SETTINGS!$I$8,0)))) | AQ312: =IF(C312="","",IF(AND(AP312<>"",TODAY()>=AP312),"Refi Ready",IF(TODAY()-C312>=SETTINGS!$I$11,"Prospecting","Performing"))) | AR312: =IF(OR(C312="",I312="",K312=""),"",IF(K312="Monthly",EDATE(C312,I312),WORKDAY(C312,I312))) | AT312: =IF(C312="","",IF(AM312="Clawed Back","CLAWED",IF(TODAY()<=C312+SETTINGS!$I$2,"⚠ AT RISK","SAFE"))) | AW312: =AW311+IF(AND(C312<>"",AO312<>"",OR('REP COMMISSION'!$B$3="",T312='REP COMMISSION'!$B$3,W312='REP COMMISSION'!$B$3,Z312='REP COMMISSION'!$B$3)),1,0) -> 0 | AX312: =AX311+IF(AND(C312<>"",OR(F312="LOC - INITIAL",F312="CONSOLIDATION - UPFRONT COMM",F312="REVERSE - TOTAL FUNDING")),1,0) -> 0
A313: =IF(C313<>"","F"&COUNT($C$4:C313),"") | B313: =IF(OR(F313="LOC - INITIAL",F313="CONSOLIDATION - UPFRONT COMM",F313="REVERSE - TOTAL FUNDING"),A313,"") | J313: =IF(AND(G313<>"",H313<>""),G313*H313,"") | N313: =IF(OR(G313="",M313=""),0,IF(M313>100,M313,G313*IF(M313>1,M313/100,M313))) -> 0 | O313: =IF(G313="","",G313*IF(L313="",0,IF(L313>1,L313/100,L313))+N313) | Q313: =IF(P313="","",IFERROR(VLOOKUP(P313,PARTNERS!$A$2:$B$30,2,0),"")) | R313: =IF(O313="","",IF(OR(P313="",Q313=""),0,(O313-N313)*IF(Q313>1,Q313/100,Q313))) | S313: =IF(O313="","",O313-R313) | U313: =IF(T313="","",IFERROR(VLOOKUP(T313,REPS!$A$2:$D$40,2,0),"")) | V313: =IF(O313="","",IF(U313="",0,O313*IF(U313>1,U313/100,U313))) | X313: =IF(W313="","",IFERROR(VLOOKUP(W313,REPS!$A$2:$D$40,3,0),"")) | Y313: =IF(O313="","",IF(X313="",0,O313*IF(X313>1,X313/100,X313))) | AA313: =IF(Z313="","",IFERROR(VLOOKUP(Z313,REPS!$A$2:$D$40,4,0),"")) | AB313: =IF(O313="","",IF(AA313="",0,O313*IF(AA313>1,AA313/100,AA313))) | AC313: =IF(O313="","",V313+Y313+AB313) | AD313: =IF(O313="","",O313-R313-AC313) | AG313: =IF(OR(AE313="",AE313=0),0,AE313*IF(U313="",0,IF(U313>1,U313/100,U313))) -> 0 | AH313: =IF(OR(AE313="",AE313=0),0,AE313*IF(X313="",0,IF(X313>1,X313/100,X313))) -> 0 | AI313: =IF(OR(AE313="",AE313=0),0,AE313*IF(AA313="",0,IF(AA313>1,AA313/100,AA313))) -> 0 | AJ313: =AG313+AH313+AI313 -> 0 | AK313: =IF(OR(AE313="",AE313=0),0,AE313-AJ313) -> 0 | AL313: =IF(AD313="","",AD313-AK313) | AM313: =IF(C313="","","Waiting for payment") | AP313: =IF(OR(C313="",I313="",K313=""),"",IF(K313="Monthly",EDATE(C313,ROUND(I313*SETTINGS!$I$8,0)),WORKDAY(C313,ROUND(I313*SETTINGS!$I$8,0)))) | AQ313: =IF(C313="","",IF(AND(AP313<>"",TODAY()>=AP313),"Refi Ready",IF(TODAY()-C313>=SETTINGS!$I$11,"Prospecting","Performing"))) | AR313: =IF(OR(C313="",I313="",K313=""),"",IF(K313="Monthly",EDATE(C313,I313),WORKDAY(C313,I313))) | AT313: =IF(C313="","",IF(AM313="Clawed Back","CLAWED",IF(TODAY()<=C313+SETTINGS!$I$2,"⚠ AT RISK","SAFE"))) | AW313: =AW312+IF(AND(C313<>"",AO313<>"",OR('REP COMMISSION'!$B$3="",T313='REP COMMISSION'!$B$3,W313='REP COMMISSION'!$B$3,Z313='REP COMMISSION'!$B$3)),1,0) -> 0 | AX313: =AX312+IF(AND(C313<>"",OR(F313="LOC - INITIAL",F313="CONSOLIDATION - UPFRONT COMM",F313="REVERSE - TOTAL FUNDING")),1,0) -> 0
A314: =IF(C314<>"","F"&COUNT($C$4:C314),"") | B314: =IF(OR(F314="LOC - INITIAL",F314="CONSOLIDATION - UPFRONT COMM",F314="REVERSE - TOTAL FUNDING"),A314,"") | J314: =IF(AND(G314<>"",H314<>""),G314*H314,"") | N314: =IF(OR(G314="",M314=""),0,IF(M314>100,M314,G314*IF(M314>1,M314/100,M314))) -> 0 | O314: =IF(G314="","",G314*IF(L314="",0,IF(L314>1,L314/100,L314))+N314) | Q314: =IF(P314="","",IFERROR(VLOOKUP(P314,PARTNERS!$A$2:$B$30,2,0),"")) | R314: =IF(O314="","",IF(OR(P314="",Q314=""),0,(O314-N314)*IF(Q314>1,Q314/100,Q314))) | S314: =IF(O314="","",O314-R314) | U314: =IF(T314="","",IFERROR(VLOOKUP(T314,REPS!$A$2:$D$40,2,0),"")) | V314: =IF(O314="","",IF(U314="",0,O314*IF(U314>1,U314/100,U314))) | X314: =IF(W314="","",IFERROR(VLOOKUP(W314,REPS!$A$2:$D$40,3,0),"")) | Y314: =IF(O314="","",IF(X314="",0,O314*IF(X314>1,X314/100,X314))) | AA314: =IF(Z314="","",IFERROR(VLOOKUP(Z314,REPS!$A$2:$D$40,4,0),"")) | AB314: =IF(O314="","",IF(AA314="",0,O314*IF(AA314>1,AA314/100,AA314))) | AC314: =IF(O314="","",V314+Y314+AB314) | AD314: =IF(O314="","",O314-R314-AC314) | AG314: =IF(OR(AE314="",AE314=0),0,AE314*IF(U314="",0,IF(U314>1,U314/100,U314))) -> 0 | AH314: =IF(OR(AE314="",AE314=0),0,AE314*IF(X314="",0,IF(X314>1,X314/100,X314))) -> 0 | AI314: =IF(OR(AE314="",AE314=0),0,AE314*IF(AA314="",0,IF(AA314>1,AA314/100,AA314))) -> 0 | AJ314: =AG314+AH314+AI314 -> 0 | AK314: =IF(OR(AE314="",AE314=0),0,AE314-AJ314) -> 0 | AL314: =IF(AD314="","",AD314-AK314) | AM314: =IF(C314="","","Waiting for payment") | AP314: =IF(OR(C314="",I314="",K314=""),"",IF(K314="Monthly",EDATE(C314,ROUND(I314*SETTINGS!$I$8,0)),WORKDAY(C314,ROUND(I314*SETTINGS!$I$8,0)))) | AQ314: =IF(C314="","",IF(AND(AP314<>"",TODAY()>=AP314),"Refi Ready",IF(TODAY()-C314>=SETTINGS!$I$11,"Prospecting","Performing"))) | AR314: =IF(OR(C314="",I314="",K314=""),"",IF(K314="Monthly",EDATE(C314,I314),WORKDAY(C314,I314))) | AT314: =IF(C314="","",IF(AM314="Clawed Back","CLAWED",IF(TODAY()<=C314+SETTINGS!$I$2,"⚠ AT RISK","SAFE"))) | AW314: =AW313+IF(AND(C314<>"",AO314<>"",OR('REP COMMISSION'!$B$3="",T314='REP COMMISSION'!$B$3,W314='REP COMMISSION'!$B$3,Z314='REP COMMISSION'!$B$3)),1,0) -> 0 | AX314: =AX313+IF(AND(C314<>"",OR(F314="LOC - INITIAL",F314="CONSOLIDATION - UPFRONT COMM",F314="REVERSE - TOTAL FUNDING")),1,0) -> 0
A315: =IF(C315<>"","F"&COUNT($C$4:C315),"") | B315: =IF(OR(F315="LOC - INITIAL",F315="CONSOLIDATION - UPFRONT COMM",F315="REVERSE - TOTAL FUNDING"),A315,"") | J315: =IF(AND(G315<>"",H315<>""),G315*H315,"") | N315: =IF(OR(G315="",M315=""),0,IF(M315>100,M315,G315*IF(M315>1,M315/100,M315))) -> 0 | O315: =IF(G315="","",G315*IF(L315="",0,IF(L315>1,L315/100,L315))+N315) | Q315: =IF(P315="","",IFERROR(VLOOKUP(P315,PARTNERS!$A$2:$B$30,2,0),"")) | R315: =IF(O315="","",IF(OR(P315="",Q315=""),0,(O315-N315)*IF(Q315>1,Q315/100,Q315))) | S315: =IF(O315="","",O315-R315) | U315: =IF(T315="","",IFERROR(VLOOKUP(T315,REPS!$A$2:$D$40,2,0),"")) | V315: =IF(O315="","",IF(U315="",0,O315*IF(U315>1,U315/100,U315))) | X315: =IF(W315="","",IFERROR(VLOOKUP(W315,REPS!$A$2:$D$40,3,0),"")) | Y315: =IF(O315="","",IF(X315="",0,O315*IF(X315>1,X315/100,X315))) | AA315: =IF(Z315="","",IFERROR(VLOOKUP(Z315,REPS!$A$2:$D$40,4,0),"")) | AB315: =IF(O315="","",IF(AA315="",0,O315*IF(AA315>1,AA315/100,AA315))) | AC315: =IF(O315="","",V315+Y315+AB315) | AD315: =IF(O315="","",O315-R315-AC315) | AG315: =IF(OR(AE315="",AE315=0),0,AE315*IF(U315="",0,IF(U315>1,U315/100,U315))) -> 0 | AH315: =IF(OR(AE315="",AE315=0),0,AE315*IF(X315="",0,IF(X315>1,X315/100,X315))) -> 0 | AI315: =IF(OR(AE315="",AE315=0),0,AE315*IF(AA315="",0,IF(AA315>1,AA315/100,AA315))) -> 0 | AJ315: =AG315+AH315+AI315 -> 0 | AK315: =IF(OR(AE315="",AE315=0),0,AE315-AJ315) -> 0 | AL315: =IF(AD315="","",AD315-AK315) | AM315: =IF(C315="","","Waiting for payment") | AP315: =IF(OR(C315="",I315="",K315=""),"",IF(K315="Monthly",EDATE(C315,ROUND(I315*SETTINGS!$I$8,0)),WORKDAY(C315,ROUND(I315*SETTINGS!$I$8,0)))) | AQ315: =IF(C315="","",IF(AND(AP315<>"",TODAY()>=AP315),"Refi Ready",IF(TODAY()-C315>=SETTINGS!$I$11,"Prospecting","Performing"))) | AR315: =IF(OR(C315="",I315="",K315=""),"",IF(K315="Monthly",EDATE(C315,I315),WORKDAY(C315,I315))) | AT315: =IF(C315="","",IF(AM315="Clawed Back","CLAWED",IF(TODAY()<=C315+SETTINGS!$I$2,"⚠ AT RISK","SAFE"))) | AW315: =AW314+IF(AND(C315<>"",AO315<>"",OR('REP COMMISSION'!$B$3="",T315='REP COMMISSION'!$B$3,W315='REP COMMISSION'!$B$3,Z315='REP COMMISSION'!$B$3)),1,0) -> 0 | AX315: =AX314+IF(AND(C315<>"",OR(F315="LOC - INITIAL",F315="CONSOLIDATION - UPFRONT COMM",F315="REVERSE - TOTAL FUNDING")),1,0) -> 0
A316: =IF(C316<>"","F"&COUNT($C$4:C316),"") | B316: =IF(OR(F316="LOC - INITIAL",F316="CONSOLIDATION - UPFRONT COMM",F316="REVERSE - TOTAL FUNDING"),A316,"") | J316: =IF(AND(G316<>"",H316<>""),G316*H316,"") | N316: =IF(OR(G316="",M316=""),0,IF(M316>100,M316,G316*IF(M316>1,M316/100,M316))) -> 0 | O316: =IF(G316="","",G316*IF(L316="",0,IF(L316>1,L316/100,L316))+N316) | Q316: =IF(P316="","",IFERROR(VLOOKUP(P316,PARTNERS!$A$2:$B$30,2,0),"")) | R316: =IF(O316="","",IF(OR(P316="",Q316=""),0,(O316-N316)*IF(Q316>1,Q316/100,Q316))) | S316: =IF(O316="","",O316-R316) | U316: =IF(T316="","",IFERROR(VLOOKUP(T316,REPS!$A$2:$D$40,2,0),"")) | V316: =IF(O316="","",IF(U316="",0,O316*IF(U316>1,U316/100,U316))) | X316: =IF(W316="","",IFERROR(VLOOKUP(W316,REPS!$A$2:$D$40,3,0),"")) | Y316: =IF(O316="","",IF(X316="",0,O316*IF(X316>1,X316/100,X316))) | AA316: =IF(Z316="","",IFERROR(VLOOKUP(Z316,REPS!$A$2:$D$40,4,0),"")) | AB316: =IF(O316="","",IF(AA316="",0,O316*IF(AA316>1,AA316/100,AA316))) | AC316: =IF(O316="","",V316+Y316+AB316) | AD316: =IF(O316="","",O316-R316-AC316) | AG316: =IF(OR(AE316="",AE316=0),0,AE316*IF(U316="",0,IF(U316>1,U316/100,U316))) -> 0 | AH316: =IF(OR(AE316="",AE316=0),0,AE316*IF(X316="",0,IF(X316>1,X316/100,X316))) -> 0 | AI316: =IF(OR(AE316="",AE316=0),0,AE316*IF(AA316="",0,IF(AA316>1,AA316/100,AA316))) -> 0 | AJ316: =AG316+AH316+AI316 -> 0 | AK316: =IF(OR(AE316="",AE316=0),0,AE316-AJ316) -> 0 | AL316: =IF(AD316="","",AD316-AK316) | AM316: =IF(C316="","","Waiting for payment") | AP316: =IF(OR(C316="",I316="",K316=""),"",IF(K316="Monthly",EDATE(C316,ROUND(I316*SETTINGS!$I$8,0)),WORKDAY(C316,ROUND(I316*SETTINGS!$I$8,0)))) | AQ316: =IF(C316="","",IF(AND(AP316<>"",TODAY()>=AP316),"Refi Ready",IF(TODAY()-C316>=SETTINGS!$I$11,"Prospecting","Performing"))) | AR316: =IF(OR(C316="",I316="",K316=""),"",IF(K316="Monthly",EDATE(C316,I316),WORKDAY(C316,I316))) | AT316: =IF(C316="","",IF(AM316="Clawed Back","CLAWED",IF(TODAY()<=C316+SETTINGS!$I$2,"⚠ AT RISK","SAFE"))) | AW316: =AW315+IF(AND(C316<>"",AO316<>"",OR('REP COMMISSION'!$B$3="",T316='REP COMMISSION'!$B$3,W316='REP COMMISSION'!$B$3,Z316='REP COMMISSION'!$B$3)),1,0) -> 0 | AX316: =AX315+IF(AND(C316<>"",OR(F316="LOC - INITIAL",F316="CONSOLIDATION - UPFRONT COMM",F316="REVERSE - TOTAL FUNDING")),1,0) -> 0
A317: =IF(C317<>"","F"&COUNT($C$4:C317),"") | B317: =IF(OR(F317="LOC - INITIAL",F317="CONSOLIDATION - UPFRONT COMM",F317="REVERSE - TOTAL FUNDING"),A317,"") | J317: =IF(AND(G317<>"",H317<>""),G317*H317,"") | N317: =IF(OR(G317="",M317=""),0,IF(M317>100,M317,G317*IF(M317>1,M317/100,M317))) -> 0 | O317: =IF(G317="","",G317*IF(L317="",0,IF(L317>1,L317/100,L317))+N317) | Q317: =IF(P317="","",IFERROR(VLOOKUP(P317,PARTNERS!$A$2:$B$30,2,0),"")) | R317: =IF(O317="","",IF(OR(P317="",Q317=""),0,(O317-N317)*IF(Q317>1,Q317/100,Q317))) | S317: =IF(O317="","",O317-R317) | U317: =IF(T317="","",IFERROR(VLOOKUP(T317,REPS!$A$2:$D$40,2,0),"")) | V317: =IF(O317="","",IF(U317="",0,O317*IF(U317>1,U317/100,U317))) | X317: =IF(W317="","",IFERROR(VLOOKUP(W317,REPS!$A$2:$D$40,3,0),"")) | Y317: =IF(O317="","",IF(X317="",0,O317*IF(X317>1,X317/100,X317))) | AA317: =IF(Z317="","",IFERROR(VLOOKUP(Z317,REPS!$A$2:$D$40,4,0),"")) | AB317: =IF(O317="","",IF(AA317="",0,O317*IF(AA317>1,AA317/100,AA317))) | AC317: =IF(O317="","",V317+Y317+AB317) | AD317: =IF(O317="","",O317-R317-AC317) | AG317: =IF(OR(AE317="",AE317=0),0,AE317*IF(U317="",0,IF(U317>1,U317/100,U317))) -> 0 | AH317: =IF(OR(AE317="",AE317=0),0,AE317*IF(X317="",0,IF(X317>1,X317/100,X317))) -> 0 | AI317: =IF(OR(AE317="",AE317=0),0,AE317*IF(AA317="",0,IF(AA317>1,AA317/100,AA317))) -> 0 | AJ317: =AG317+AH317+AI317 -> 0 | AK317: =IF(OR(AE317="",AE317=0),0,AE317-AJ317) -> 0 | AL317: =IF(AD317="","",AD317-AK317) | AM317: =IF(C317="","","Waiting for payment") | AP317: =IF(OR(C317="",I317="",K317=""),"",IF(K317="Monthly",EDATE(C317,ROUND(I317*SETTINGS!$I$8,0)),WORKDAY(C317,ROUND(I317*SETTINGS!$I$8,0)))) | AQ317: =IF(C317="","",IF(AND(AP317<>"",TODAY()>=AP317),"Refi Ready",IF(TODAY()-C317>=SETTINGS!$I$11,"Prospecting","Performing"))) | AR317: =IF(OR(C317="",I317="",K317=""),"",IF(K317="Monthly",EDATE(C317,I317),WORKDAY(C317,I317))) | AT317: =IF(C317="","",IF(AM317="Clawed Back","CLAWED",IF(TODAY()<=C317+SETTINGS!$I$2,"⚠ AT RISK","SAFE"))) | AW317: =AW316+IF(AND(C317<>"",AO317<>"",OR('REP COMMISSION'!$B$3="",T317='REP COMMISSION'!$B$3,W317='REP COMMISSION'!$B$3,Z317='REP COMMISSION'!$B$3)),1,0) -> 0 | AX317: =AX316+IF(AND(C317<>"",OR(F317="LOC - INITIAL",F317="CONSOLIDATION - UPFRONT COMM",F317="REVERSE - TOTAL FUNDING")),1,0) -> 0
A318: =IF(C318<>"","F"&COUNT($C$4:C318),"") | B318: =IF(OR(F318="LOC - INITIAL",F318="CONSOLIDATION - UPFRONT COMM",F318="REVERSE - TOTAL FUNDING"),A318,"") | J318: =IF(AND(G318<>"",H318<>""),G318*H318,"") | N318: =IF(OR(G318="",M318=""),0,IF(M318>100,M318,G318*IF(M318>1,M318/100,M318))) -> 0 | O318: =IF(G318="","",G318*IF(L318="",0,IF(L318>1,L318/100,L318))+N318) | Q318: =IF(P318="","",IFERROR(VLOOKUP(P318,PARTNERS!$A$2:$B$30,2,0),"")) | R318: =IF(O318="","",IF(OR(P318="",Q318=""),0,(O318-N318)*IF(Q318>1,Q318/100,Q318))) | S318: =IF(O318="","",O318-R318) | U318: =IF(T318="","",IFERROR(VLOOKUP(T318,REPS!$A$2:$D$40,2,0),"")) | V318: =IF(O318="","",IF(U318="",0,O318*IF(U318>1,U318/100,U318))) | X318: =IF(W318="","",IFERROR(VLOOKUP(W318,REPS!$A$2:$D$40,3,0),"")) | Y318: =IF(O318="","",IF(X318="",0,O318*IF(X318>1,X318/100,X318))) | AA318: =IF(Z318="","",IFERROR(VLOOKUP(Z318,REPS!$A$2:$D$40,4,0),"")) | AB318: =IF(O318="","",IF(AA318="",0,O318*IF(AA318>1,AA318/100,AA318))) | AC318: =IF(O318="","",V318+Y318+AB318) | AD318: =IF(O318="","",O318-R318-AC318) | AG318: =IF(OR(AE318="",AE318=0),0,AE318*IF(U318="",0,IF(U318>1,U318/100,U318))) -> 0 | AH318: =IF(OR(AE318="",AE318=0),0,AE318*IF(X318="",0,IF(X318>1,X318/100,X318))) -> 0 | AI318: =IF(OR(AE318="",AE318=0),0,AE318*IF(AA318="",0,IF(AA318>1,AA318/100,AA318))) -> 0 | AJ318: =AG318+AH318+AI318 -> 0 | AK318: =IF(OR(AE318="",AE318=0),0,AE318-AJ318) -> 0 | AL318: =IF(AD318="","",AD318-AK318) | AM318: =IF(C318="","","Waiting for payment") | AP318: =IF(OR(C318="",I318="",K318=""),"",IF(K318="Monthly",EDATE(C318,ROUND(I318*SETTINGS!$I$8,0)),WORKDAY(C318,ROUND(I318*SETTINGS!$I$8,0)))) | AQ318: =IF(C318="","",IF(AND(AP318<>"",TODAY()>=AP318),"Refi Ready",IF(TODAY()-C318>=SETTINGS!$I$11,"Prospecting","Performing"))) | AR318: =IF(OR(C318="",I318="",K318=""),"",IF(K318="Monthly",EDATE(C318,I318),WORKDAY(C318,I318))) | AT318: =IF(C318="","",IF(AM318="Clawed Back","CLAWED",IF(TODAY()<=C318+SETTINGS!$I$2,"⚠ AT RISK","SAFE"))) | AW318: =AW317+IF(AND(C318<>"",AO318<>"",OR('REP COMMISSION'!$B$3="",T318='REP COMMISSION'!$B$3,W318='REP COMMISSION'!$B$3,Z318='REP COMMISSION'!$B$3)),1,0) -> 0 | AX318: =AX317+IF(AND(C318<>"",OR(F318="LOC - INITIAL",F318="CONSOLIDATION - UPFRONT COMM",F318="REVERSE - TOTAL FUNDING")),1,0) -> 0
A319: =IF(C319<>"","F"&COUNT($C$4:C319),"") | B319: =IF(OR(F319="LOC - INITIAL",F319="CONSOLIDATION - UPFRONT COMM",F319="REVERSE - TOTAL FUNDING"),A319,"") | J319: =IF(AND(G319<>"",H319<>""),G319*H319,"") | N319: =IF(OR(G319="",M319=""),0,IF(M319>100,M319,G319*IF(M319>1,M319/100,M319))) -> 0 | O319: =IF(G319="","",G319*IF(L319="",0,IF(L319>1,L319/100,L319))+N319) | Q319: =IF(P319="","",IFERROR(VLOOKUP(P319,PARTNERS!$A$2:$B$30,2,0),"")) | R319: =IF(O319="","",IF(OR(P319="",Q319=""),0,(O319-N319)*IF(Q319>1,Q319/100,Q319))) | S319: =IF(O319="","",O319-R319) | U319: =IF(T319="","",IFERROR(VLOOKUP(T319,REPS!$A$2:$D$40,2,0),"")) | V319: =IF(O319="","",IF(U319="",0,O319*IF(U319>1,U319/100,U319))) | X319: =IF(W319="","",IFERROR(VLOOKUP(W319,REPS!$A$2:$D$40,3,0),"")) | Y319: =IF(O319="","",IF(X319="",0,O319*IF(X319>1,X319/100,X319))) | AA319: =IF(Z319="","",IFERROR(VLOOKUP(Z319,REPS!$A$2:$D$40,4,0),"")) | AB319: =IF(O319="","",IF(AA319="",0,O319*IF(AA319>1,AA319/100,AA319))) | AC319: =IF(O319="","",V319+Y319+AB319) | AD319: =IF(O319="","",O319-R319-AC319) | AG319: =IF(OR(AE319="",AE319=0),0,AE319*IF(U319="",0,IF(U319>1,U319/100,U319))) -> 0 | AH319: =IF(OR(AE319="",AE319=0),0,AE319*IF(X319="",0,IF(X319>1,X319/100,X319))) -> 0 | AI319: =IF(OR(AE319="",AE319=0),0,AE319*IF(AA319="",0,IF(AA319>1,AA319/100,AA319))) -> 0 | AJ319: =AG319+AH319+AI319 -> 0 | AK319: =IF(OR(AE319="",AE319=0),0,AE319-AJ319) -> 0 | AL319: =IF(AD319="","",AD319-AK319) | AM319: =IF(C319="","","Waiting for payment") | AP319: =IF(OR(C319="",I319="",K319=""),"",IF(K319="Monthly",EDATE(C319,ROUND(I319*SETTINGS!$I$8,0)),WORKDAY(C319,ROUND(I319*SETTINGS!$I$8,0)))) | AQ319: =IF(C319="","",IF(AND(AP319<>"",TODAY()>=AP319),"Refi Ready",IF(TODAY()-C319>=SETTINGS!$I$11,"Prospecting","Performing"))) | AR319: =IF(OR(C319="",I319="",K319=""),"",IF(K319="Monthly",EDATE(C319,I319),WORKDAY(C319,I319))) | AT319: =IF(C319="","",IF(AM319="Clawed Back","CLAWED",IF(TODAY()<=C319+SETTINGS!$I$2,"⚠ AT RISK","SAFE"))) | AW319: =AW318+IF(AND(C319<>"",AO319<>"",OR('REP COMMISSION'!$B$3="",T319='REP COMMISSION'!$B$3,W319='REP COMMISSION'!$B$3,Z319='REP COMMISSION'!$B$3)),1,0) -> 0 | AX319: =AX318+IF(AND(C319<>"",OR(F319="LOC - INITIAL",F319="CONSOLIDATION - UPFRONT COMM",F319="REVERSE - TOTAL FUNDING")),1,0) -> 0
A320: =IF(C320<>"","F"&COUNT($C$4:C320),"") | B320: =IF(OR(F320="LOC - INITIAL",F320="CONSOLIDATION - UPFRONT COMM",F320="REVERSE - TOTAL FUNDING"),A320,"") | J320: =IF(AND(G320<>"",H320<>""),G320*H320,"") | N320: =IF(OR(G320="",M320=""),0,IF(M320>100,M320,G320*IF(M320>1,M320/100,M320))) -> 0 | O320: =IF(G320="","",G320*IF(L320="",0,IF(L320>1,L320/100,L320))+N320) | Q320: =IF(P320="","",IFERROR(VLOOKUP(P320,PARTNERS!$A$2:$B$30,2,0),"")) | R320: =IF(O320="","",IF(OR(P320="",Q320=""),0,(O320-N320)*IF(Q320>1,Q320/100,Q320))) | S320: =IF(O320="","",O320-R320) | U320: =IF(T320="","",IFERROR(VLOOKUP(T320,REPS!$A$2:$D$40,2,0),"")) | V320: =IF(O320="","",IF(U320="",0,O320*IF(U320>1,U320/100,U320))) | X320: =IF(W320="","",IFERROR(VLOOKUP(W320,REPS!$A$2:$D$40,3,0),"")) | Y320: =IF(O320="","",IF(X320="",0,O320*IF(X320>1,X320/100,X320))) | AA320: =IF(Z320="","",IFERROR(VLOOKUP(Z320,REPS!$A$2:$D$40,4,0),"")) | AB320: =IF(O320="","",IF(AA320="",0,O320*IF(AA320>1,AA320/100,AA320))) | AC320: =IF(O320="","",V320+Y320+AB320) | AD320: =IF(O320="","",O320-R320-AC320) | AG320: =IF(OR(AE320="",AE320=0),0,AE320*IF(U320="",0,IF(U320>1,U320/100,U320))) -> 0 | AH320: =IF(OR(AE320="",AE320=0),0,AE320*IF(X320="",0,IF(X320>1,X320/100,X320))) -> 0 | AI320: =IF(OR(AE320="",AE320=0),0,AE320*IF(AA320="",0,IF(AA320>1,AA320/100,AA320))) -> 0 | AJ320: =AG320+AH320+AI320 -> 0 | AK320: =IF(OR(AE320="",AE320=0),0,AE320-AJ320) -> 0 | AL320: =IF(AD320="","",AD320-AK320) | AM320: =IF(C320="","","Waiting for payment") | AP320: =IF(OR(C320="",I320="",K320=""),"",IF(K320="Monthly",EDATE(C320,ROUND(I320*SETTINGS!$I$8,0)),WORKDAY(C320,ROUND(I320*SETTINGS!$I$8,0)))) | AQ320: =IF(C320="","",IF(AND(AP320<>"",TODAY()>=AP320),"Refi Ready",IF(TODAY()-C320>=SETTINGS!$I$11,"Prospecting","Performing"))) | AR320: =IF(OR(C320="",I320="",K320=""),"",IF(K320="Monthly",EDATE(C320,I320),WORKDAY(C320,I320))) | AT320: =IF(C320="","",IF(AM320="Clawed Back","CLAWED",IF(TODAY()<=C320+SETTINGS!$I$2,"⚠ AT RISK","SAFE"))) | AW320: =AW319+IF(AND(C320<>"",AO320<>"",OR('REP COMMISSION'!$B$3="",T320='REP COMMISSION'!$B$3,W320='REP COMMISSION'!$B$3,Z320='REP COMMISSION'!$B$3)),1,0) -> 0 | AX320: =AX319+IF(AND(C320<>"",OR(F320="LOC - INITIAL",F320="CONSOLIDATION - UPFRONT COMM",F320="REVERSE - TOTAL FUNDING")),1,0) -> 0
A321: =IF(C321<>"","F"&COUNT($C$4:C321),"") | B321: =IF(OR(F321="LOC - INITIAL",F321="CONSOLIDATION - UPFRONT COMM",F321="REVERSE - TOTAL FUNDING"),A321,"") | J321: =IF(AND(G321<>"",H321<>""),G321*H321,"") | N321: =IF(OR(G321="",M321=""),0,IF(M321>100,M321,G321*IF(M321>1,M321/100,M321))) -> 0 | O321: =IF(G321="","",G321*IF(L321="",0,IF(L321>1,L321/100,L321))+N321) | Q321: =IF(P321="","",IFERROR(VLOOKUP(P321,PARTNERS!$A$2:$B$30,2,0),"")) | R321: =IF(O321="","",IF(OR(P321="",Q321=""),0,(O321-N321)*IF(Q321>1,Q321/100,Q321))) | S321: =IF(O321="","",O321-R321) | U321: =IF(T321="","",IFERROR(VLOOKUP(T321,REPS!$A$2:$D$40,2,0),"")) | V321: =IF(O321="","",IF(U321="",0,O321*IF(U321>1,U321/100,U321))) | X321: =IF(W321="","",IFERROR(VLOOKUP(W321,REPS!$A$2:$D$40,3,0),"")) | Y321: =IF(O321="","",IF(X321="",0,O321*IF(X321>1,X321/100,X321))) | AA321: =IF(Z321="","",IFERROR(VLOOKUP(Z321,REPS!$A$2:$D$40,4,0),"")) | AB321: =IF(O321="","",IF(AA321="",0,O321*IF(AA321>1,AA321/100,AA321))) | AC321: =IF(O321="","",V321+Y321+AB321) | AD321: =IF(O321="","",O321-R321-AC321) | AG321: =IF(OR(AE321="",AE321=0),0,AE321*IF(U321="",0,IF(U321>1,U321/100,U321))) -> 0 | AH321: =IF(OR(AE321="",AE321=0),0,AE321*IF(X321="",0,IF(X321>1,X321/100,X321))) -> 0 | AI321: =IF(OR(AE321="",AE321=0),0,AE321*IF(AA321="",0,IF(AA321>1,AA321/100,AA321))) -> 0 | AJ321: =AG321+AH321+AI321 -> 0 | AK321: =IF(OR(AE321="",AE321=0),0,AE321-AJ321) -> 0 | AL321: =IF(AD321="","",AD321-AK321) | AM321: =IF(C321="","","Waiting for payment") | AP321: =IF(OR(C321="",I321="",K321=""),"",IF(K321="Monthly",EDATE(C321,ROUND(I321*SETTINGS!$I$8,0)),WORKDAY(C321,ROUND(I321*SETTINGS!$I$8,0)))) | AQ321: =IF(C321="","",IF(AND(AP321<>"",TODAY()>=AP321),"Refi Ready",IF(TODAY()-C321>=SETTINGS!$I$11,"Prospecting","Performing"))) | AR321: =IF(OR(C321="",I321="",K321=""),"",IF(K321="Monthly",EDATE(C321,I321),WORKDAY(C321,I321))) | AT321: =IF(C321="","",IF(AM321="Clawed Back","CLAWED",IF(TODAY()<=C321+SETTINGS!$I$2,"⚠ AT RISK","SAFE"))) | AW321: =AW320+IF(AND(C321<>"",AO321<>"",OR('REP COMMISSION'!$B$3="",T321='REP COMMISSION'!$B$3,W321='REP COMMISSION'!$B$3,Z321='REP COMMISSION'!$B$3)),1,0) -> 0 | AX321: =AX320+IF(AND(C321<>"",OR(F321="LOC - INITIAL",F321="CONSOLIDATION - UPFRONT COMM",F321="REVERSE - TOTAL FUNDING")),1,0) -> 0
... A409: =IF(C409<>"","F"&COUNT($C$4:C409),"") | B409: =IF(OR(F409="LOC - INITIAL",F409="CONSOLIDATION - UPFRONT COMM",F409="REVERSE - TOTAL FUNDING"),A409,"") | J409: =IF(AND(G409<>"",H409<>""),G409*H409,"") | N409: =IF(OR(G409="",M409=""),0,IF(M409>100,M409,G409*IF(M409>1,M409/100,M409))) -> 0 | O409: =IF(G409="","",G409*IF(L409="",0,IF(L409>1,L409/100,L409))+N409) | Q409: =IF(P409="","",IFERROR(VLOOKUP(P409,PARTNERS!$A$2:$B$30,2,0),"")) | R409: =IF(O409="","",IF(OR(P409="",Q409=""),0,(O409-N409)*IF(Q409>1,Q409/100,Q409))) | S409: =IF(O409="","",O409-R409) | U409: =IF(T409="","",IFERROR(VLOOKUP(T409,REPS!$A$2:$D$40,2,0),"")) | V409: =IF(O409="","",IF(U409="",0,O409*IF(U409>1,U409/100,U409))) | X409: =IF(W409="","",IFERROR(VLOOKUP(W409,REPS!$A$2:$D$40,3,0),"")) | Y409: =IF(O409="","",IF(X409="",0,O409*IF(X409>1,X409/100,X409))) | AA409: =IF(Z409="","",IFERROR(VLOOKUP(Z409,REPS!$A$2:$D$40,4,0),"")) | AB409: =IF(O409="","",IF(AA409="",0,O409*IF(AA409>1,AA409/100,AA409))) | AC409: =IF(O409="","",V409+Y409+AB409) | AD409: =IF(O409="","",O409-R409-AC409) | AG409: =IF(OR(AE409="",AE409=0),0,AE409*IF(U409="",0,IF(U409>1,U409/100,U409))) -> 0 | AH409: =IF(OR(AE409="",AE409=0),0,AE409*IF(X409="",0,IF(X409>1,X409/100,X409))) -> 0 | AI409: =IF(OR(AE409="",AE409=0),0,AE409*IF(AA409="",0,IF(AA409>1,AA409/100,AA409))) -> 0 | AJ409: =AG409+AH409+AI409 -> 0 | AK409: =IF(OR(AE409="",AE409=0),0,AE409-AJ409) -> 0 | AL409: =IF(AD409="","",AD409-AK409) | AM409: =IF(C409="","","Waiting for payment") | AP409: =IF(OR(C409="",I409="",K409=""),"",IF(K409="Monthly",EDATE(C409,ROUND(I409*SETTINGS!$I$8,0)),WORKDAY(C409,ROUND(I409*SETTINGS!$I$8,0)))) | AQ409: =IF(C409="","",IF(AND(AP409<>"",TODAY()>=AP409),"Refi Ready",IF(TODAY()-C409>=SETTINGS!$I$11,"Prospecting","Performing"))) | AR409: =IF(OR(C409="",I409="",K409=""),"",IF(K409="Monthly",EDATE(C409,I409),WORKDAY(C409,I409))) | AT409: =IF(C409="","",IF(AM409="Clawed Back","CLAWED",IF(TODAY()<=C409+SETTINGS!$I$2,"⚠ AT RISK","SAFE"))) | AW409: =AW408+IF(AND(C409<>"",AO409<>"",OR('REP COMMISSION'!$B$3="",T409='REP COMMISSION'!$B$3,W409='REP COMMISSION'!$B$3,Z409='REP COMMISSION'!$B$3)),1,0) -> 0 | AX409: =AX408+IF(AND(C409<>"",OR(F409="LOC - INITIAL",F409="CONSOLIDATION - UPFRONT COMM",F409="REVERSE - TOTAL FUNDING")),1,0) -> 0
A410: JULY TOTAL | D410: =COUNT(C310:C409)&" units" -> 0 units | G410: =SUM(G310:G409) -> 0 | N410: =SUM(N310:N409) -> 0 | O410: =SUM(O310:O409) -> 0 | R410: =SUM(R310:R409) -> 0 | S410: =SUM(S310:S409) -> 0 | AC410: =SUM(AC310:AC409) -> 0 | AD410: =SUM(AD310:AD409) -> 0 | AE410: =SUM(AE310:AE409) -> 0 | AJ410: =SUM(AJ310:AJ409) -> 0 | AK410: =SUM(AK310:AK409) -> 0 | AL410: =SUM(AL310:AL409) -> 0 | AW410: =AW409 -> 0 | AX410: =AX409 -> 0
A411: ▼ AUGUST 2026 | AW411: =AW410 -> 0 | AX411: =AX410 -> 0
A412: =IF(C412<>"","F"&COUNT($C$4:C412),"") | B412: =IF(OR(F412="LOC - INITIAL",F412="CONSOLIDATION - UPFRONT COMM",F412="REVERSE - TOTAL FUNDING"),A412,"") | J412: =IF(AND(G412<>"",H412<>""),G412*H412,"") | N412: =IF(OR(G412="",M412=""),0,IF(M412>100,M412,G412*IF(M412>1,M412/100,M412))) -> 0 | O412: =IF(G412="","",G412*IF(L412="",0,IF(L412>1,L412/100,L412))+N412) | Q412: =IF(P412="","",IFERROR(VLOOKUP(P412,PARTNERS!$A$2:$B$30,2,0),"")) | R412: =IF(O412="","",IF(OR(P412="",Q412=""),0,(O412-N412)*IF(Q412>1,Q412/100,Q412))) | S412: =IF(O412="","",O412-R412) | U412: =IF(T412="","",IFERROR(VLOOKUP(T412,REPS!$A$2:$D$40,2,0),"")) | V412: =IF(O412="","",IF(U412="",0,O412*IF(U412>1,U412/100,U412))) | X412: =IF(W412="","",IFERROR(VLOOKUP(W412,REPS!$A$2:$D$40,3,0),"")) | Y412: =IF(O412="","",IF(X412="",0,O412*IF(X412>1,X412/100,X412))) | AA412: =IF(Z412="","",IFERROR(VLOOKUP(Z412,REPS!$A$2:$D$40,4,0),"")) | AB412: =IF(O412="","",IF(AA412="",0,O412*IF(AA412>1,AA412/100,AA412))) | AC412: =IF(O412="","",V412+Y412+AB412) | AD412: =IF(O412="","",O412-R412-AC412) | AG412: =IF(OR(AE412="",AE412=0),0,AE412*IF(U412="",0,IF(U412>1,U412/100,U412))) -> 0 | AH412: =IF(OR(AE412="",AE412=0),0,AE412*IF(X412="",0,IF(X412>1,X412/100,X412))) -> 0 | AI412: =IF(OR(AE412="",AE412=0),0,AE412*IF(AA412="",0,IF(AA412>1,AA412/100,AA412))) -> 0 | AJ412: =AG412+AH412+AI412 -> 0 | AK412: =IF(OR(AE412="",AE412=0),0,AE412-AJ412) -> 0 | AL412: =IF(AD412="","",AD412-AK412) | AM412: =IF(C412="","","Waiting for payment") | AP412: =IF(OR(C412="",I412="",K412=""),"",IF(K412="Monthly",EDATE(C412,ROUND(I412*SETTINGS!$I$8,0)),WORKDAY(C412,ROUND(I412*SETTINGS!$I$8,0)))) | AQ412: =IF(C412="","",IF(AND(AP412<>"",TODAY()>=AP412),"Refi Ready",IF(TODAY()-C412>=SETTINGS!$I$11,"Prospecting","Performing"))) | AR412: =IF(OR(C412="",I412="",K412=""),"",IF(K412="Monthly",EDATE(C412,I412),WORKDAY(C412,I412))) | AT412: =IF(C412="","",IF(AM412="Clawed Back","CLAWED",IF(TODAY()<=C412+SETTINGS!$I$2,"⚠ AT RISK","SAFE"))) | AW412: =AW411+IF(AND(C412<>"",AO412<>"",OR('REP COMMISSION'!$B$3="",T412='REP COMMISSION'!$B$3,W412='REP COMMISSION'!$B$3,Z412='REP COMMISSION'!$B$3)),1,0) -> 0 | AX412: =AX411+IF(AND(C412<>"",OR(F412="LOC - INITIAL",F412="CONSOLIDATION - UPFRONT COMM",F412="REVERSE - TOTAL FUNDING")),1,0) -> 0
A413: =IF(C413<>"","F"&COUNT($C$4:C413),"") | B413: =IF(OR(F413="LOC - INITIAL",F413="CONSOLIDATION - UPFRONT COMM",F413="REVERSE - TOTAL FUNDING"),A413,"") | J413: =IF(AND(G413<>"",H413<>""),G413*H413,"") | N413: =IF(OR(G413="",M413=""),0,IF(M413>100,M413,G413*IF(M413>1,M413/100,M413))) -> 0 | O413: =IF(G413="","",G413*IF(L413="",0,IF(L413>1,L413/100,L413))+N413) | Q413: =IF(P413="","",IFERROR(VLOOKUP(P413,PARTNERS!$A$2:$B$30,2,0),"")) | R413: =IF(O413="","",IF(OR(P413="",Q413=""),0,(O413-N413)*IF(Q413>1,Q413/100,Q413))) | S413: =IF(O413="","",O413-R413) | U413: =IF(T413="","",IFERROR(VLOOKUP(T413,REPS!$A$2:$D$40,2,0),"")) | V413: =IF(O413="","",IF(U413="",0,O413*IF(U413>1,U413/100,U413))) | X413: =IF(W413="","",IFERROR(VLOOKUP(W413,REPS!$A$2:$D$40,3,0),"")) | Y413: =IF(O413="","",IF(X413="",0,O413*IF(X413>1,X413/100,X413))) | AA413: =IF(Z413="","",IFERROR(VLOOKUP(Z413,REPS!$A$2:$D$40,4,0),"")) | AB413: =IF(O413="","",IF(AA413="",0,O413*IF(AA413>1,AA413/100,AA413))) | AC413: =IF(O413="","",V413+Y413+AB413) | AD413: =IF(O413="","",O413-R413-AC413) | AG413: =IF(OR(AE413="",AE413=0),0,AE413*IF(U413="",0,IF(U413>1,U413/100,U413))) -> 0 | AH413: =IF(OR(AE413="",AE413=0),0,AE413*IF(X413="",0,IF(X413>1,X413/100,X413))) -> 0 | AI413: =IF(OR(AE413="",AE413=0),0,AE413*IF(AA413="",0,IF(AA413>1,AA413/100,AA413))) -> 0 | AJ413: =AG413+AH413+AI413 -> 0 | AK413: =IF(OR(AE413="",AE413=0),0,AE413-AJ413) -> 0 | AL413: =IF(AD413="","",AD413-AK413) | AM413: =IF(C413="","","Waiting for payment") | AP413: =IF(OR(C413="",I413="",K413=""),"",IF(K413="Monthly",EDATE(C413,ROUND(I413*SETTINGS!$I$8,0)),WORKDAY(C413,ROUND(I413*SETTINGS!$I$8,0)))) | AQ413: =IF(C413="","",IF(AND(AP413<>"",TODAY()>=AP413),"Refi Ready",IF(TODAY()-C413>=SETTINGS!$I$11,"Prospecting","Performing"))) | AR413: =IF(OR(C413="",I413="",K413=""),"",IF(K413="Monthly",EDATE(C413,I413),WORKDAY(C413,I413))) | AT413: =IF(C413="","",IF(AM413="Clawed Back","CLAWED",IF(TODAY()<=C413+SETTINGS!$I$2,"⚠ AT RISK","SAFE"))) | AW413: =AW412+IF(AND(C413<>"",AO413<>"",OR('REP COMMISSION'!$B$3="",T413='REP COMMISSION'!$B$3,W413='REP COMMISSION'!$B$3,Z413='REP COMMISSION'!$B$3)),1,0) -> 0 | AX413: =AX412+IF(AND(C413<>"",OR(F413="LOC - INITIAL",F413="CONSOLIDATION - UPFRONT COMM",F413="REVERSE - TOTAL FUNDING")),1,0) -> 0
A414: =IF(C414<>"","F"&COUNT($C$4:C414),"") | B414: =IF(OR(F414="LOC - INITIAL",F414="CONSOLIDATION - UPFRONT COMM",F414="REVERSE - TOTAL FUNDING"),A414,"") | J414: =IF(AND(G414<>"",H414<>""),G414*H414,"") | N414: =IF(OR(G414="",M414=""),0,IF(M414>100,M414,G414*IF(M414>1,M414/100,M414))) -> 0 | O414: =IF(G414="","",G414*IF(L414="",0,IF(L414>1,L414/100,L414))+N414) | Q414: =IF(P414="","",IFERROR(VLOOKUP(P414,PARTNERS!$A$2:$B$30,2,0),"")) | R414: =IF(O414="","",IF(OR(P414="",Q414=""),0,(O414-N414)*IF(Q414>1,Q414/100,Q414))) | S414: =IF(O414="","",O414-R414) | U414: =IF(T414="","",IFERROR(VLOOKUP(T414,REPS!$A$2:$D$40,2,0),"")) | V414: =IF(O414="","",IF(U414="",0,O414*IF(U414>1,U414/100,U414))) | X414: =IF(W414="","",IFERROR(VLOOKUP(W414,REPS!$A$2:$D$40,3,0),"")) | Y414: =IF(O414="","",IF(X414="",0,O414*IF(X414>1,X414/100,X414))) | AA414: =IF(Z414="","",IFERROR(VLOOKUP(Z414,REPS!$A$2:$D$40,4,0),"")) | AB414: =IF(O414="","",IF(AA414="",0,O414*IF(AA414>1,AA414/100,AA414))) | AC414: =IF(O414="","",V414+Y414+AB414) | AD414: =IF(O414="","",O414-R414-AC414) | AG414: =IF(OR(AE414="",AE414=0),0,AE414*IF(U414="",0,IF(U414>1,U414/100,U414))) -> 0 | AH414: =IF(OR(AE414="",AE414=0),0,AE414*IF(X414="",0,IF(X414>1,X414/100,X414))) -> 0 | AI414: =IF(OR(AE414="",AE414=0),0,AE414*IF(AA414="",0,IF(AA414>1,AA414/100,AA414))) -> 0 | AJ414: =AG414+AH414+AI414 -> 0 | AK414: =IF(OR(AE414="",AE414=0),0,AE414-AJ414) -> 0 | AL414: =IF(AD414="","",AD414-AK414) | AM414: =IF(C414="","","Waiting for payment") | AP414: =IF(OR(C414="",I414="",K414=""),"",IF(K414="Monthly",EDATE(C414,ROUND(I414*SETTINGS!$I$8,0)),WORKDAY(C414,ROUND(I414*SETTINGS!$I$8,0)))) | AQ414: =IF(C414="","",IF(AND(AP414<>"",TODAY()>=AP414),"Refi Ready",IF(TODAY()-C414>=SETTINGS!$I$11,"Prospecting","Performing"))) | AR414: =IF(OR(C414="",I414="",K414=""),"",IF(K414="Monthly",EDATE(C414,I414),WORKDAY(C414,I414))) | AT414: =IF(C414="","",IF(AM414="Clawed Back","CLAWED",IF(TODAY()<=C414+SETTINGS!$I$2,"⚠ AT RISK","SAFE"))) | AW414: =AW413+IF(AND(C414<>"",AO414<>"",OR('REP COMMISSION'!$B$3="",T414='REP COMMISSION'!$B$3,W414='REP COMMISSION'!$B$3,Z414='REP COMMISSION'!$B$3)),1,0) -> 0 | AX414: =AX413+IF(AND(C414<>"",OR(F414="LOC - INITIAL",F414="CONSOLIDATION - UPFRONT COMM",F414="REVERSE - TOTAL FUNDING")),1,0) -> 0
A415: =IF(C415<>"","F"&COUNT($C$4:C415),"") | B415: =IF(OR(F415="LOC - INITIAL",F415="CONSOLIDATION - UPFRONT COMM",F415="REVERSE - TOTAL FUNDING"),A415,"") | J415: =IF(AND(G415<>"",H415<>""),G415*H415,"") | N415: =IF(OR(G415="",M415=""),0,IF(M415>100,M415,G415*IF(M415>1,M415/100,M415))) -> 0 | O415: =IF(G415="","",G415*IF(L415="",0,IF(L415>1,L415/100,L415))+N415) | Q415: =IF(P415="","",IFERROR(VLOOKUP(P415,PARTNERS!$A$2:$B$30,2,0),"")) | R415: =IF(O415="","",IF(OR(P415="",Q415=""),0,(O415-N415)*IF(Q415>1,Q415/100,Q415))) | S415: =IF(O415="","",O415-R415) | U415: =IF(T415="","",IFERROR(VLOOKUP(T415,REPS!$A$2:$D$40,2,0),"")) | V415: =IF(O415="","",IF(U415="",0,O415*IF(U415>1,U415/100,U415))) | X415: =IF(W415="","",IFERROR(VLOOKUP(W415,REPS!$A$2:$D$40,3,0),"")) | Y415: =IF(O415="","",IF(X415="",0,O415*IF(X415>1,X415/100,X415))) | AA415: =IF(Z415="","",IFERROR(VLOOKUP(Z415,REPS!$A$2:$D$40,4,0),"")) | AB415: =IF(O415="","",IF(AA415="",0,O415*IF(AA415>1,AA415/100,AA415))) | AC415: =IF(O415="","",V415+Y415+AB415) | AD415: =IF(O415="","",O415-R415-AC415) | AG415: =IF(OR(AE415="",AE415=0),0,AE415*IF(U415="",0,IF(U415>1,U415/100,U415))) -> 0 | AH415: =IF(OR(AE415="",AE415=0),0,AE415*IF(X415="",0,IF(X415>1,X415/100,X415))) -> 0 | AI415: =IF(OR(AE415="",AE415=0),0,AE415*IF(AA415="",0,IF(AA415>1,AA415/100,AA415))) -> 0 | AJ415: =AG415+AH415+AI415 -> 0 | AK415: =IF(OR(AE415="",AE415=0),0,AE415-AJ415) -> 0 | AL415: =IF(AD415="","",AD415-AK415) | AM415: =IF(C415="","","Waiting for payment") | AP415: =IF(OR(C415="",I415="",K415=""),"",IF(K415="Monthly",EDATE(C415,ROUND(I415*SETTINGS!$I$8,0)),WORKDAY(C415,ROUND(I415*SETTINGS!$I$8,0)))) | AQ415: =IF(C415="","",IF(AND(AP415<>"",TODAY()>=AP415),"Refi Ready",IF(TODAY()-C415>=SETTINGS!$I$11,"Prospecting","Performing"))) | AR415: =IF(OR(C415="",I415="",K415=""),"",IF(K415="Monthly",EDATE(C415,I415),WORKDAY(C415,I415))) | AT415: =IF(C415="","",IF(AM415="Clawed Back","CLAWED",IF(TODAY()<=C415+SETTINGS!$I$2,"⚠ AT RISK","SAFE"))) | AW415: =AW414+IF(AND(C415<>"",AO415<>"",OR('REP COMMISSION'!$B$3="",T415='REP COMMISSION'!$B$3,W415='REP COMMISSION'!$B$3,Z415='REP COMMISSION'!$B$3)),1,0) -> 0 | AX415: =AX414+IF(AND(C415<>"",OR(F415="LOC - INITIAL",F415="CONSOLIDATION - UPFRONT COMM",F415="REVERSE - TOTAL FUNDING")),1,0) -> 0
A416: =IF(C416<>"","F"&COUNT($C$4:C416),"") | B416: =IF(OR(F416="LOC - INITIAL",F416="CONSOLIDATION - UPFRONT COMM",F416="REVERSE - TOTAL FUNDING"),A416,"") | J416: =IF(AND(G416<>"",H416<>""),G416*H416,"") | N416: =IF(OR(G416="",M416=""),0,IF(M416>100,M416,G416*IF(M416>1,M416/100,M416))) -> 0 | O416: =IF(G416="","",G416*IF(L416="",0,IF(L416>1,L416/100,L416))+N416) | Q416: =IF(P416="","",IFERROR(VLOOKUP(P416,PARTNERS!$A$2:$B$30,2,0),"")) | R416: =IF(O416="","",IF(OR(P416="",Q416=""),0,(O416-N416)*IF(Q416>1,Q416/100,Q416))) | S416: =IF(O416="","",O416-R416) | U416: =IF(T416="","",IFERROR(VLOOKUP(T416,REPS!$A$2:$D$40,2,0),"")) | V416: =IF(O416="","",IF(U416="",0,O416*IF(U416>1,U416/100,U416))) | X416: =IF(W416="","",IFERROR(VLOOKUP(W416,REPS!$A$2:$D$40,3,0),"")) | Y416: =IF(O416="","",IF(X416="",0,O416*IF(X416>1,X416/100,X416))) | AA416: =IF(Z416="","",IFERROR(VLOOKUP(Z416,REPS!$A$2:$D$40,4,0),"")) | AB416: =IF(O416="","",IF(AA416="",0,O416*IF(AA416>1,AA416/100,AA416))) | AC416: =IF(O416="","",V416+Y416+AB416) | AD416: =IF(O416="","",O416-R416-AC416) | AG416: =IF(OR(AE416="",AE416=0),0,AE416*IF(U416="",0,IF(U416>1,U416/100,U416))) -> 0 | AH416: =IF(OR(AE416="",AE416=0),0,AE416*IF(X416="",0,IF(X416>1,X416/100,X416))) -> 0 | AI416: =IF(OR(AE416="",AE416=0),0,AE416*IF(AA416="",0,IF(AA416>1,AA416/100,AA416))) -> 0 | AJ416: =AG416+AH416+AI416 -> 0 | AK416: =IF(OR(AE416="",AE416=0),0,AE416-AJ416) -> 0 | AL416: =IF(AD416="","",AD416-AK416) | AM416: =IF(C416="","","Waiting for payment") | AP416: =IF(OR(C416="",I416="",K416=""),"",IF(K416="Monthly",EDATE(C416,ROUND(I416*SETTINGS!$I$8,0)),WORKDAY(C416,ROUND(I416*SETTINGS!$I$8,0)))) | AQ416: =IF(C416="","",IF(AND(AP416<>"",TODAY()>=AP416),"Refi Ready",IF(TODAY()-C416>=SETTINGS!$I$11,"Prospecting","Performing"))) | AR416: =IF(OR(C416="",I416="",K416=""),"",IF(K416="Monthly",EDATE(C416,I416),WORKDAY(C416,I416))) | AT416: =IF(C416="","",IF(AM416="Clawed Back","CLAWED",IF(TODAY()<=C416+SETTINGS!$I$2,"⚠ AT RISK","SAFE"))) | AW416: =AW415+IF(AND(C416<>"",AO416<>"",OR('REP COMMISSION'!$B$3="",T416='REP COMMISSION'!$B$3,W416='REP COMMISSION'!$B$3,Z416='REP COMMISSION'!$B$3)),1,0) -> 0 | AX416: =AX415+IF(AND(C416<>"",OR(F416="LOC - INITIAL",F416="CONSOLIDATION - UPFRONT COMM",F416="REVERSE - TOTAL FUNDING")),1,0) -> 0
A417: =IF(C417<>"","F"&COUNT($C$4:C417),"") | B417: =IF(OR(F417="LOC - INITIAL",F417="CONSOLIDATION - UPFRONT COMM",F417="REVERSE - TOTAL FUNDING"),A417,"") | J417: =IF(AND(G417<>"",H417<>""),G417*H417,"") | N417: =IF(OR(G417="",M417=""),0,IF(M417>100,M417,G417*IF(M417>1,M417/100,M417))) -> 0 | O417: =IF(G417="","",G417*IF(L417="",0,IF(L417>1,L417/100,L417))+N417) | Q417: =IF(P417="","",IFERROR(VLOOKUP(P417,PARTNERS!$A$2:$B$30,2,0),"")) | R417: =IF(O417="","",IF(OR(P417="",Q417=""),0,(O417-N417)*IF(Q417>1,Q417/100,Q417))) | S417: =IF(O417="","",O417-R417) | U417: =IF(T417="","",IFERROR(VLOOKUP(T417,REPS!$A$2:$D$40,2,0),"")) | V417: =IF(O417="","",IF(U417="",0,O417*IF(U417>1,U417/100,U417))) | X417: =IF(W417="","",IFERROR(VLOOKUP(W417,REPS!$A$2:$D$40,3,0),"")) | Y417: =IF(O417="","",IF(X417="",0,O417*IF(X417>1,X417/100,X417))) | AA417: =IF(Z417="","",IFERROR(VLOOKUP(Z417,REPS!$A$2:$D$40,4,0),"")) | AB417: =IF(O417="","",IF(AA417="",0,O417*IF(AA417>1,AA417/100,AA417))) | AC417: =IF(O417="","",V417+Y417+AB417) | AD417: =IF(O417="","",O417-R417-AC417) | AG417: =IF(OR(AE417="",AE417=0),0,AE417*IF(U417="",0,IF(U417>1,U417/100,U417))) -> 0 | AH417: =IF(OR(AE417="",AE417=0),0,AE417*IF(X417="",0,IF(X417>1,X417/100,X417))) -> 0 | AI417: =IF(OR(AE417="",AE417=0),0,AE417*IF(AA417="",0,IF(AA417>1,AA417/100,AA417))) -> 0 | AJ417: =AG417+AH417+AI417 -> 0 | AK417: =IF(OR(AE417="",AE417=0),0,AE417-AJ417) -> 0 | AL417: =IF(AD417="","",AD417-AK417) | AM417: =IF(C417="","","Waiting for payment") | AP417: =IF(OR(C417="",I417="",K417=""),"",IF(K417="Monthly",EDATE(C417,ROUND(I417*SETTINGS!$I$8,0)),WORKDAY(C417,ROUND(I417*SETTINGS!$I$8,0)))) | AQ417: =IF(C417="","",IF(AND(AP417<>"",TODAY()>=AP417),"Refi Ready",IF(TODAY()-C417>=SETTINGS!$I$11,"Prospecting","Performing"))) | AR417: =IF(OR(C417="",I417="",K417=""),"",IF(K417="Monthly",EDATE(C417,I417),WORKDAY(C417,I417))) | AT417: =IF(C417="","",IF(AM417="Clawed Back","CLAWED",IF(TODAY()<=C417+SETTINGS!$I$2,"⚠ AT RISK","SAFE"))) | AW417: =AW416+IF(AND(C417<>"",AO417<>"",OR('REP COMMISSION'!$B$3="",T417='REP COMMISSION'!$B$3,W417='REP COMMISSION'!$B$3,Z417='REP COMMISSION'!$B$3)),1,0) -> 0 | AX417: =AX416+IF(AND(C417<>"",OR(F417="LOC - INITIAL",F417="CONSOLIDATION - UPFRONT COMM",F417="REVERSE - TOTAL FUNDING")),1,0) -> 0
A418: =IF(C418<>"","F"&COUNT($C$4:C418),"") | B418: =IF(OR(F418="LOC - INITIAL",F418="CONSOLIDATION - UPFRONT COMM",F418="REVERSE - TOTAL FUNDING"),A418,"") | J418: =IF(AND(G418<>"",H418<>""),G418*H418,"") | N418: =IF(OR(G418="",M418=""),0,IF(M418>100,M418,G418*IF(M418>1,M418/100,M418))) -> 0 | O418: =IF(G418="","",G418*IF(L418="",0,IF(L418>1,L418/100,L418))+N418) | Q418: =IF(P418="","",IFERROR(VLOOKUP(P418,PARTNERS!$A$2:$B$30,2,0),"")) | R418: =IF(O418="","",IF(OR(P418="",Q418=""),0,(O418-N418)*IF(Q418>1,Q418/100,Q418))) | S418: =IF(O418="","",O418-R418) | U418: =IF(T418="","",IFERROR(VLOOKUP(T418,REPS!$A$2:$D$40,2,0),"")) | V418: =IF(O418="","",IF(U418="",0,O418*IF(U418>1,U418/100,U418))) | X418: =IF(W418="","",IFERROR(VLOOKUP(W418,REPS!$A$2:$D$40,3,0),"")) | Y418: =IF(O418="","",IF(X418="",0,O418*IF(X418>1,X418/100,X418))) | AA418: =IF(Z418="","",IFERROR(VLOOKUP(Z418,REPS!$A$2:$D$40,4,0),"")) | AB418: =IF(O418="","",IF(AA418="",0,O418*IF(AA418>1,AA418/100,AA418))) | AC418: =IF(O418="","",V418+Y418+AB418) | AD418: =IF(O418="","",O418-R418-AC418) | AG418: =IF(OR(AE418="",AE418=0),0,AE418*IF(U418="",0,IF(U418>1,U418/100,U418))) -> 0 | AH418: =IF(OR(AE418="",AE418=0),0,AE418*IF(X418="",0,IF(X418>1,X418/100,X418))) -> 0 | AI418: =IF(OR(AE418="",AE418=0),0,AE418*IF(AA418="",0,IF(AA418>1,AA418/100,AA418))) -> 0 | AJ418: =AG418+AH418+AI418 -> 0 | AK418: =IF(OR(AE418="",AE418=0),0,AE418-AJ418) -> 0 | AL418: =IF(AD418="","",AD418-AK418) | AM418: =IF(C418="","","Waiting for payment") | AP418: =IF(OR(C418="",I418="",K418=""),"",IF(K418="Monthly",EDATE(C418,ROUND(I418*SETTINGS!$I$8,0)),WORKDAY(C418,ROUND(I418*SETTINGS!$I$8,0)))) | AQ418: =IF(C418="","",IF(AND(AP418<>"",TODAY()>=AP418),"Refi Ready",IF(TODAY()-C418>=SETTINGS!$I$11,"Prospecting","Performing"))) | AR418: =IF(OR(C418="",I418="",K418=""),"",IF(K418="Monthly",EDATE(C418,I418),WORKDAY(C418,I418))) | AT418: =IF(C418="","",IF(AM418="Clawed Back","CLAWED",IF(TODAY()<=C418+SETTINGS!$I$2,"⚠ AT RISK","SAFE"))) | AW418: =AW417+IF(AND(C418<>"",AO418<>"",OR('REP COMMISSION'!$B$3="",T418='REP COMMISSION'!$B$3,W418='REP COMMISSION'!$B$3,Z418='REP COMMISSION'!$B$3)),1,0) -> 0 | AX418: =AX417+IF(AND(C418<>"",OR(F418="LOC - INITIAL",F418="CONSOLIDATION - UPFRONT COMM",F418="REVERSE - TOTAL FUNDING")),1,0) -> 0
A419: =IF(C419<>"","F"&COUNT($C$4:C419),"") | B419: =IF(OR(F419="LOC - INITIAL",F419="CONSOLIDATION - UPFRONT COMM",F419="REVERSE - TOTAL FUNDING"),A419,"") | J419: =IF(AND(G419<>"",H419<>""),G419*H419,"") | N419: =IF(OR(G419="",M419=""),0,IF(M419>100,M419,G419*IF(M419>1,M419/100,M419))) -> 0 | O419: =IF(G419="","",G419*IF(L419="",0,IF(L419>1,L419/100,L419))+N419) | Q419: =IF(P419="","",IFERROR(VLOOKUP(P419,PARTNERS!$A$2:$B$30,2,0),"")) | R419: =IF(O419="","",IF(OR(P419="",Q419=""),0,(O419-N419)*IF(Q419>1,Q419/100,Q419))) | S419: =IF(O419="","",O419-R419) | U419: =IF(T419="","",IFERROR(VLOOKUP(T419,REPS!$A$2:$D$40,2,0),"")) | V419: =IF(O419="","",IF(U419="",0,O419*IF(U419>1,U419/100,U419))) | X419: =IF(W419="","",IFERROR(VLOOKUP(W419,REPS!$A$2:$D$40,3,0),"")) | Y419: =IF(O419="","",IF(X419="",0,O419*IF(X419>1,X419/100,X419))) | AA419: =IF(Z419="","",IFERROR(VLOOKUP(Z419,REPS!$A$2:$D$40,4,0),"")) | AB419: =IF(O419="","",IF(AA419="",0,O419*IF(AA419>1,AA419/100,AA419))) | AC419: =IF(O419="","",V419+Y419+AB419) | AD419: =IF(O419="","",O419-R419-AC419) | AG419: =IF(OR(AE419="",AE419=0),0,AE419*IF(U419="",0,IF(U419>1,U419/100,U419))) -> 0 | AH419: =IF(OR(AE419="",AE419=0),0,AE419*IF(X419="",0,IF(X419>1,X419/100,X419))) -> 0 | AI419: =IF(OR(AE419="",AE419=0),0,AE419*IF(AA419="",0,IF(AA419>1,AA419/100,AA419))) -> 0 | AJ419: =AG419+AH419+AI419 -> 0 | AK419: =IF(OR(AE419="",AE419=0),0,AE419-AJ419) -> 0 | AL419: =IF(AD419="","",AD419-AK419) | AM419: =IF(C419="","","Waiting for payment") | AP419: =IF(OR(C419="",I419="",K419=""),"",IF(K419="Monthly",EDATE(C419,ROUND(I419*SETTINGS!$I$8,0)),WORKDAY(C419,ROUND(I419*SETTINGS!$I$8,0)))) | AQ419: =IF(C419="","",IF(AND(AP419<>"",TODAY()>=AP419),"Refi Ready",IF(TODAY()-C419>=SETTINGS!$I$11,"Prospecting","Performing"))) | AR419: =IF(OR(C419="",I419="",K419=""),"",IF(K419="Monthly",EDATE(C419,I419),WORKDAY(C419,I419))) | AT419: =IF(C419="","",IF(AM419="Clawed Back","CLAWED",IF(TODAY()<=C419+SETTINGS!$I$2,"⚠ AT RISK","SAFE"))) | AW419: =AW418+IF(AND(C419<>"",AO419<>"",OR('REP COMMISSION'!$B$3="",T419='REP COMMISSION'!$B$3,W419='REP COMMISSION'!$B$3,Z419='REP COMMISSION'!$B$3)),1,0) -> 0 | AX419: =AX418+IF(AND(C419<>"",OR(F419="LOC - INITIAL",F419="CONSOLIDATION - UPFRONT COMM",F419="REVERSE - TOTAL FUNDING")),1,0) -> 0
A420: =IF(C420<>"","F"&COUNT($C$4:C420),"") | B420: =IF(OR(F420="LOC - INITIAL",F420="CONSOLIDATION - UPFRONT COMM",F420="REVERSE - TOTAL FUNDING"),A420,"") | J420: =IF(AND(G420<>"",H420<>""),G420*H420,"") | N420: =IF(OR(G420="",M420=""),0,IF(M420>100,M420,G420*IF(M420>1,M420/100,M420))) -> 0 | O420: =IF(G420="","",G420*IF(L420="",0,IF(L420>1,L420/100,L420))+N420) | Q420: =IF(P420="","",IFERROR(VLOOKUP(P420,PARTNERS!$A$2:$B$30,2,0),"")) | R420: =IF(O420="","",IF(OR(P420="",Q420=""),0,(O420-N420)*IF(Q420>1,Q420/100,Q420))) | S420: =IF(O420="","",O420-R420) | U420: =IF(T420="","",IFERROR(VLOOKUP(T420,REPS!$A$2:$D$40,2,0),"")) | V420: =IF(O420="","",IF(U420="",0,O420*IF(U420>1,U420/100,U420))) | X420: =IF(W420="","",IFERROR(VLOOKUP(W420,REPS!$A$2:$D$40,3,0),"")) | Y420: =IF(O420="","",IF(X420="",0,O420*IF(X420>1,X420/100,X420))) | AA420: =IF(Z420="","",IFERROR(VLOOKUP(Z420,REPS!$A$2:$D$40,4,0),"")) | AB420: =IF(O420="","",IF(AA420="",0,O420*IF(AA420>1,AA420/100,AA420))) | AC420: =IF(O420="","",V420+Y420+AB420) | AD420: =IF(O420="","",O420-R420-AC420) | AG420: =IF(OR(AE420="",AE420=0),0,AE420*IF(U420="",0,IF(U420>1,U420/100,U420))) -> 0 | AH420: =IF(OR(AE420="",AE420=0),0,AE420*IF(X420="",0,IF(X420>1,X420/100,X420))) -> 0 | AI420: =IF(OR(AE420="",AE420=0),0,AE420*IF(AA420="",0,IF(AA420>1,AA420/100,AA420))) -> 0 | AJ420: =AG420+AH420+AI420 -> 0 | AK420: =IF(OR(AE420="",AE420=0),0,AE420-AJ420) -> 0 | AL420: =IF(AD420="","",AD420-AK420) | AM420: =IF(C420="","","Waiting for payment") | AP420: =IF(OR(C420="",I420="",K420=""),"",IF(K420="Monthly",EDATE(C420,ROUND(I420*SETTINGS!$I$8,0)),WORKDAY(C420,ROUND(I420*SETTINGS!$I$8,0)))) | AQ420: =IF(C420="","",IF(AND(AP420<>"",TODAY()>=AP420),"Refi Ready",IF(TODAY()-C420>=SETTINGS!$I$11,"Prospecting","Performing"))) | AR420: =IF(OR(C420="",I420="",K420=""),"",IF(K420="Monthly",EDATE(C420,I420),WORKDAY(C420,I420))) | AT420: =IF(C420="","",IF(AM420="Clawed Back","CLAWED",IF(TODAY()<=C420+SETTINGS!$I$2,"⚠ AT RISK","SAFE"))) | AW420: =AW419+IF(AND(C420<>"",AO420<>"",OR('REP COMMISSION'!$B$3="",T420='REP COMMISSION'!$B$3,W420='REP COMMISSION'!$B$3,Z420='REP COMMISSION'!$B$3)),1,0) -> 0 | AX420: =AX419+IF(AND(C420<>"",OR(F420="LOC - INITIAL",F420="CONSOLIDATION - UPFRONT COMM",F420="REVERSE - TOTAL FUNDING")),1,0) -> 0
A421: =IF(C421<>"","F"&COUNT($C$4:C421),"") | B421: =IF(OR(F421="LOC - INITIAL",F421="CONSOLIDATION - UPFRONT COMM",F421="REVERSE - TOTAL FUNDING"),A421,"") | J421: =IF(AND(G421<>"",H421<>""),G421*H421,"") | N421: =IF(OR(G421="",M421=""),0,IF(M421>100,M421,G421*IF(M421>1,M421/100,M421))) -> 0 | O421: =IF(G421="","",G421*IF(L421="",0,IF(L421>1,L421/100,L421))+N421) | Q421: =IF(P421="","",IFERROR(VLOOKUP(P421,PARTNERS!$A$2:$B$30,2,0),"")) | R421: =IF(O421="","",IF(OR(P421="",Q421=""),0,(O421-N421)*IF(Q421>1,Q421/100,Q421))) | S421: =IF(O421="","",O421-R421) | U421: =IF(T421="","",IFERROR(VLOOKUP(T421,REPS!$A$2:$D$40,2,0),"")) | V421: =IF(O421="","",IF(U421="",0,O421*IF(U421>1,U421/100,U421))) | X421: =IF(W421="","",IFERROR(VLOOKUP(W421,REPS!$A$2:$D$40,3,0),"")) | Y421: =IF(O421="","",IF(X421="",0,O421*IF(X421>1,X421/100,X421))) | AA421: =IF(Z421="","",IFERROR(VLOOKUP(Z421,REPS!$A$2:$D$40,4,0),"")) | AB421: =IF(O421="","",IF(AA421="",0,O421*IF(AA421>1,AA421/100,AA421))) | AC421: =IF(O421="","",V421+Y421+AB421) | AD421: =IF(O421="","",O421-R421-AC421) | AG421: =IF(OR(AE421="",AE421=0),0,AE421*IF(U421="",0,IF(U421>1,U421/100,U421))) -> 0 | AH421: =IF(OR(AE421="",AE421=0),0,AE421*IF(X421="",0,IF(X421>1,X421/100,X421))) -> 0 | AI421: =IF(OR(AE421="",AE421=0),0,AE421*IF(AA421="",0,IF(AA421>1,AA421/100,AA421))) -> 0 | AJ421: =AG421+AH421+AI421 -> 0 | AK421: =IF(OR(AE421="",AE421=0),0,AE421-AJ421) -> 0 | AL421: =IF(AD421="","",AD421-AK421) | AM421: =IF(C421="","","Waiting for payment") | AP421: =IF(OR(C421="",I421="",K421=""),"",IF(K421="Monthly",EDATE(C421,ROUND(I421*SETTINGS!$I$8,0)),WORKDAY(C421,ROUND(I421*SETTINGS!$I$8,0)))) | AQ421: =IF(C421="","",IF(AND(AP421<>"",TODAY()>=AP421),"Refi Ready",IF(TODAY()-C421>=SETTINGS!$I$11,"Prospecting","Performing"))) | AR421: =IF(OR(C421="",I421="",K421=""),"",IF(K421="Monthly",EDATE(C421,I421),WORKDAY(C421,I421))) | AT421: =IF(C421="","",IF(AM421="Clawed Back","CLAWED",IF(TODAY()<=C421+SETTINGS!$I$2,"⚠ AT RISK","SAFE"))) | AW421: =AW420+IF(AND(C421<>"",AO421<>"",OR('REP COMMISSION'!$B$3="",T421='REP COMMISSION'!$B$3,W421='REP COMMISSION'!$B$3,Z421='REP COMMISSION'!$B$3)),1,0) -> 0 | AX421: =AX420+IF(AND(C421<>"",OR(F421="LOC - INITIAL",F421="CONSOLIDATION - UPFRONT COMM",F421="REVERSE - TOTAL FUNDING")),1,0) -> 0
A422: =IF(C422<>"","F"&COUNT($C$4:C422),"") | B422: =IF(OR(F422="LOC - INITIAL",F422="CONSOLIDATION - UPFRONT COMM",F422="REVERSE - TOTAL FUNDING"),A422,"") | J422: =IF(AND(G422<>"",H422<>""),G422*H422,"") | N422: =IF(OR(G422="",M422=""),0,IF(M422>100,M422,G422*IF(M422>1,M422/100,M422))) -> 0 | O422: =IF(G422="","",G422*IF(L422="",0,IF(L422>1,L422/100,L422))+N422) | Q422: =IF(P422="","",IFERROR(VLOOKUP(P422,PARTNERS!$A$2:$B$30,2,0),"")) | R422: =IF(O422="","",IF(OR(P422="",Q422=""),0,(O422-N422)*IF(Q422>1,Q422/100,Q422))) | S422: =IF(O422="","",O422-R422) | U422: =IF(T422="","",IFERROR(VLOOKUP(T422,REPS!$A$2:$D$40,2,0),"")) | V422: =IF(O422="","",IF(U422="",0,O422*IF(U422>1,U422/100,U422))) | X422: =IF(W422="","",IFERROR(VLOOKUP(W422,REPS!$A$2:$D$40,3,0),"")) | Y422: =IF(O422="","",IF(X422="",0,O422*IF(X422>1,X422/100,X422))) | AA422: =IF(Z422="","",IFERROR(VLOOKUP(Z422,REPS!$A$2:$D$40,4,0),"")) | AB422: =IF(O422="","",IF(AA422="",0,O422*IF(AA422>1,AA422/100,AA422))) | AC422: =IF(O422="","",V422+Y422+AB422) | AD422: =IF(O422="","",O422-R422-AC422) | AG422: =IF(OR(AE422="",AE422=0),0,AE422*IF(U422="",0,IF(U422>1,U422/100,U422))) -> 0 | AH422: =IF(OR(AE422="",AE422=0),0,AE422*IF(X422="",0,IF(X422>1,X422/100,X422))) -> 0 | AI422: =IF(OR(AE422="",AE422=0),0,AE422*IF(AA422="",0,IF(AA422>1,AA422/100,AA422))) -> 0 | AJ422: =AG422+AH422+AI422 -> 0 | AK422: =IF(OR(AE422="",AE422=0),0,AE422-AJ422) -> 0 | AL422: =IF(AD422="","",AD422-AK422) | AM422: =IF(C422="","","Waiting for payment") | AP422: =IF(OR(C422="",I422="",K422=""),"",IF(K422="Monthly",EDATE(C422,ROUND(I422*SETTINGS!$I$8,0)),WORKDAY(C422,ROUND(I422*SETTINGS!$I$8,0)))) | AQ422: =IF(C422="","",IF(AND(AP422<>"",TODAY()>=AP422),"Refi Ready",IF(TODAY()-C422>=SETTINGS!$I$11,"Prospecting","Performing"))) | AR422: =IF(OR(C422="",I422="",K422=""),"",IF(K422="Monthly",EDATE(C422,I422),WORKDAY(C422,I422))) | AT422: =IF(C422="","",IF(AM422="Clawed Back","CLAWED",IF(TODAY()<=C422+SETTINGS!$I$2,"⚠ AT RISK","SAFE"))) | AW422: =AW421+IF(AND(C422<>"",AO422<>"",OR('REP COMMISSION'!$B$3="",T422='REP COMMISSION'!$B$3,W422='REP COMMISSION'!$B$3,Z422='REP COMMISSION'!$B$3)),1,0) -> 0 | AX422: =AX421+IF(AND(C422<>"",OR(F422="LOC - INITIAL",F422="CONSOLIDATION - UPFRONT COMM",F422="REVERSE - TOTAL FUNDING")),1,0) -> 0
A423: =IF(C423<>"","F"&COUNT($C$4:C423),"") | B423: =IF(OR(F423="LOC - INITIAL",F423="CONSOLIDATION - UPFRONT COMM",F423="REVERSE - TOTAL FUNDING"),A423,"") | J423: =IF(AND(G423<>"",H423<>""),G423*H423,"") | N423: =IF(OR(G423="",M423=""),0,IF(M423>100,M423,G423*IF(M423>1,M423/100,M423))) -> 0 | O423: =IF(G423="","",G423*IF(L423="",0,IF(L423>1,L423/100,L423))+N423) | Q423: =IF(P423="","",IFERROR(VLOOKUP(P423,PARTNERS!$A$2:$B$30,2,0),"")) | R423: =IF(O423="","",IF(OR(P423="",Q423=""),0,(O423-N423)*IF(Q423>1,Q423/100,Q423))) | S423: =IF(O423="","",O423-R423) | U423: =IF(T423="","",IFERROR(VLOOKUP(T423,REPS!$A$2:$D$40,2,0),"")) | V423: =IF(O423="","",IF(U423="",0,O423*IF(U423>1,U423/100,U423))) | X423: =IF(W423="","",IFERROR(VLOOKUP(W423,REPS!$A$2:$D$40,3,0),"")) | Y423: =IF(O423="","",IF(X423="",0,O423*IF(X423>1,X423/100,X423))) | AA423: =IF(Z423="","",IFERROR(VLOOKUP(Z423,REPS!$A$2:$D$40,4,0),"")) | AB423: =IF(O423="","",IF(AA423="",0,O423*IF(AA423>1,AA423/100,AA423))) | AC423: =IF(O423="","",V423+Y423+AB423) | AD423: =IF(O423="","",O423-R423-AC423) | AG423: =IF(OR(AE423="",AE423=0),0,AE423*IF(U423="",0,IF(U423>1,U423/100,U423))) -> 0 | AH423: =IF(OR(AE423="",AE423=0),0,AE423*IF(X423="",0,IF(X423>1,X423/100,X423))) -> 0 | AI423: =IF(OR(AE423="",AE423=0),0,AE423*IF(AA423="",0,IF(AA423>1,AA423/100,AA423))) -> 0 | AJ423: =AG423+AH423+AI423 -> 0 | AK423: =IF(OR(AE423="",AE423=0),0,AE423-AJ423) -> 0 | AL423: =IF(AD423="","",AD423-AK423) | AM423: =IF(C423="","","Waiting for payment") | AP423: =IF(OR(C423="",I423="",K423=""),"",IF(K423="Monthly",EDATE(C423,ROUND(I423*SETTINGS!$I$8,0)),WORKDAY(C423,ROUND(I423*SETTINGS!$I$8,0)))) | AQ423: =IF(C423="","",IF(AND(AP423<>"",TODAY()>=AP423),"Refi Ready",IF(TODAY()-C423>=SETTINGS!$I$11,"Prospecting","Performing"))) | AR423: =IF(OR(C423="",I423="",K423=""),"",IF(K423="Monthly",EDATE(C423,I423),WORKDAY(C423,I423))) | AT423: =IF(C423="","",IF(AM423="Clawed Back","CLAWED",IF(TODAY()<=C423+SETTINGS!$I$2,"⚠ AT RISK","SAFE"))) | AW423: =AW422+IF(AND(C423<>"",AO423<>"",OR('REP COMMISSION'!$B$3="",T423='REP COMMISSION'!$B$3,W423='REP COMMISSION'!$B$3,Z423='REP COMMISSION'!$B$3)),1,0) -> 0 | AX423: =AX422+IF(AND(C423<>"",OR(F423="LOC - INITIAL",F423="CONSOLIDATION - UPFRONT COMM",F423="REVERSE - TOTAL FUNDING")),1,0) -> 0
... A511: =IF(C511<>"","F"&COUNT($C$4:C511),"") | B511: =IF(OR(F511="LOC - INITIAL",F511="CONSOLIDATION - UPFRONT COMM",F511="REVERSE - TOTAL FUNDING"),A511,"") | J511: =IF(AND(G511<>"",H511<>""),G511*H511,"") | N511: =IF(OR(G511="",M511=""),0,IF(M511>100,M511,G511*IF(M511>1,M511/100,M511))) -> 0 | O511: =IF(G511="","",G511*IF(L511="",0,IF(L511>1,L511/100,L511))+N511) | Q511: =IF(P511="","",IFERROR(VLOOKUP(P511,PARTNERS!$A$2:$B$30,2,0),"")) | R511: =IF(O511="","",IF(OR(P511="",Q511=""),0,(O511-N511)*IF(Q511>1,Q511/100,Q511))) | S511: =IF(O511="","",O511-R511) | U511: =IF(T511="","",IFERROR(VLOOKUP(T511,REPS!$A$2:$D$40,2,0),"")) | V511: =IF(O511="","",IF(U511="",0,O511*IF(U511>1,U511/100,U511))) | X511: =IF(W511="","",IFERROR(VLOOKUP(W511,REPS!$A$2:$D$40,3,0),"")) | Y511: =IF(O511="","",IF(X511="",0,O511*IF(X511>1,X511/100,X511))) | AA511: =IF(Z511="","",IFERROR(VLOOKUP(Z511,REPS!$A$2:$D$40,4,0),"")) | AB511: =IF(O511="","",IF(AA511="",0,O511*IF(AA511>1,AA511/100,AA511))) | AC511: =IF(O511="","",V511+Y511+AB511) | AD511: =IF(O511="","",O511-R511-AC511) | AG511: =IF(OR(AE511="",AE511=0),0,AE511*IF(U511="",0,IF(U511>1,U511/100,U511))) -> 0 | AH511: =IF(OR(AE511="",AE511=0),0,AE511*IF(X511="",0,IF(X511>1,X511/100,X511))) -> 0 | AI511: =IF(OR(AE511="",AE511=0),0,AE511*IF(AA511="",0,IF(AA511>1,AA511/100,AA511))) -> 0 | AJ511: =AG511+AH511+AI511 -> 0 | AK511: =IF(OR(AE511="",AE511=0),0,AE511-AJ511) -> 0 | AL511: =IF(AD511="","",AD511-AK511) | AM511: =IF(C511="","","Waiting for payment") | AP511: =IF(OR(C511="",I511="",K511=""),"",IF(K511="Monthly",EDATE(C511,ROUND(I511*SETTINGS!$I$8,0)),WORKDAY(C511,ROUND(I511*SETTINGS!$I$8,0)))) | AQ511: =IF(C511="","",IF(AND(AP511<>"",TODAY()>=AP511),"Refi Ready",IF(TODAY()-C511>=SETTINGS!$I$11,"Prospecting","Performing"))) | AR511: =IF(OR(C511="",I511="",K511=""),"",IF(K511="Monthly",EDATE(C511,I511),WORKDAY(C511,I511))) | AT511: =IF(C511="","",IF(AM511="Clawed Back","CLAWED",IF(TODAY()<=C511+SETTINGS!$I$2,"⚠ AT RISK","SAFE"))) | AW511: =AW510+IF(AND(C511<>"",AO511<>"",OR('REP COMMISSION'!$B$3="",T511='REP COMMISSION'!$B$3,W511='REP COMMISSION'!$B$3,Z511='REP COMMISSION'!$B$3)),1,0) -> 0 | AX511: =AX510+IF(AND(C511<>"",OR(F511="LOC - INITIAL",F511="CONSOLIDATION - UPFRONT COMM",F511="REVERSE - TOTAL FUNDING")),1,0) -> 0
A512: AUGUST TOTAL | D512: =COUNT(C412:C511)&" units" -> 0 units | G512: =SUM(G412:G511) -> 0 | N512: =SUM(N412:N511) -> 0 | O512: =SUM(O412:O511) -> 0 | R512: =SUM(R412:R511) -> 0 | S512: =SUM(S412:S511) -> 0 | AC512: =SUM(AC412:AC511) -> 0 | AD512: =SUM(AD412:AD511) -> 0 | AE512: =SUM(AE412:AE511) -> 0 | AJ512: =SUM(AJ412:AJ511) -> 0 | AK512: =SUM(AK412:AK511) -> 0 | AL512: =SUM(AL412:AL511) -> 0 | AW512: =AW511 -> 0 | AX512: =AX511 -> 0
A513: ▼ SEPTEMBER 2026 | AW513: =AW512 -> 0 | AX513: =AX512 -> 0
A514: =IF(C514<>"","F"&COUNT($C$4:C514),"") | B514: =IF(OR(F514="LOC - INITIAL",F514="CONSOLIDATION - UPFRONT COMM",F514="REVERSE - TOTAL FUNDING"),A514,"") | J514: =IF(AND(G514<>"",H514<>""),G514*H514,"") | N514: =IF(OR(G514="",M514=""),0,IF(M514>100,M514,G514*IF(M514>1,M514/100,M514))) -> 0 | O514: =IF(G514="","",G514*IF(L514="",0,IF(L514>1,L514/100,L514))+N514) | Q514: =IF(P514="","",IFERROR(VLOOKUP(P514,PARTNERS!$A$2:$B$30,2,0),"")) | R514: =IF(O514="","",IF(OR(P514="",Q514=""),0,(O514-N514)*IF(Q514>1,Q514/100,Q514))) | S514: =IF(O514="","",O514-R514) | U514: =IF(T514="","",IFERROR(VLOOKUP(T514,REPS!$A$2:$D$40,2,0),"")) | V514: =IF(O514="","",IF(U514="",0,O514*IF(U514>1,U514/100,U514))) | X514: =IF(W514="","",IFERROR(VLOOKUP(W514,REPS!$A$2:$D$40,3,0),"")) | Y514: =IF(O514="","",IF(X514="",0,O514*IF(X514>1,X514/100,X514))) | AA514: =IF(Z514="","",IFERROR(VLOOKUP(Z514,REPS!$A$2:$D$40,4,0),"")) | AB514: =IF(O514="","",IF(AA514="",0,O514*IF(AA514>1,AA514/100,AA514))) | AC514: =IF(O514="","",V514+Y514+AB514) | AD514: =IF(O514="","",O514-R514-AC514) | AG514: =IF(OR(AE514="",AE514=0),0,AE514*IF(U514="",0,IF(U514>1,U514/100,U514))) -> 0 | AH514: =IF(OR(AE514="",AE514=0),0,AE514*IF(X514="",0,IF(X514>1,X514/100,X514))) -> 0 | AI514: =IF(OR(AE514="",AE514=0),0,AE514*IF(AA514="",0,IF(AA514>1,AA514/100,AA514))) -> 0 | AJ514: =AG514+AH514+AI514 -> 0 | AK514: =IF(OR(AE514="",AE514=0),0,AE514-AJ514) -> 0 | AL514: =IF(AD514="","",AD514-AK514) | AM514: =IF(C514="","","Waiting for payment") | AP514: =IF(OR(C514="",I514="",K514=""),"",IF(K514="Monthly",EDATE(C514,ROUND(I514*SETTINGS!$I$8,0)),WORKDAY(C514,ROUND(I514*SETTINGS!$I$8,0)))) | AQ514: =IF(C514="","",IF(AND(AP514<>"",TODAY()>=AP514),"Refi Ready",IF(TODAY()-C514>=SETTINGS!$I$11,"Prospecting","Performing"))) | AR514: =IF(OR(C514="",I514="",K514=""),"",IF(K514="Monthly",EDATE(C514,I514),WORKDAY(C514,I514))) | AT514: =IF(C514="","",IF(AM514="Clawed Back","CLAWED",IF(TODAY()<=C514+SETTINGS!$I$2,"⚠ AT RISK","SAFE"))) | AW514: =AW513+IF(AND(C514<>"",AO514<>"",OR('REP COMMISSION'!$B$3="",T514='REP COMMISSION'!$B$3,W514='REP COMMISSION'!$B$3,Z514='REP COMMISSION'!$B$3)),1,0) -> 0 | AX514: =AX513+IF(AND(C514<>"",OR(F514="LOC - INITIAL",F514="CONSOLIDATION - UPFRONT COMM",F514="REVERSE - TOTAL FUNDING")),1,0) -> 0
A515: =IF(C515<>"","F"&COUNT($C$4:C515),"") | B515: =IF(OR(F515="LOC - INITIAL",F515="CONSOLIDATION - UPFRONT COMM",F515="REVERSE - TOTAL FUNDING"),A515,"") | J515: =IF(AND(G515<>"",H515<>""),G515*H515,"") | N515: =IF(OR(G515="",M515=""),0,IF(M515>100,M515,G515*IF(M515>1,M515/100,M515))) -> 0 | O515: =IF(G515="","",G515*IF(L515="",0,IF(L515>1,L515/100,L515))+N515) | Q515: =IF(P515="","",IFERROR(VLOOKUP(P515,PARTNERS!$A$2:$B$30,2,0),"")) | R515: =IF(O515="","",IF(OR(P515="",Q515=""),0,(O515-N515)*IF(Q515>1,Q515/100,Q515))) | S515: =IF(O515="","",O515-R515) | U515: =IF(T515="","",IFERROR(VLOOKUP(T515,REPS!$A$2:$D$40,2,0),"")) | V515: =IF(O515="","",IF(U515="",0,O515*IF(U515>1,U515/100,U515))) | X515: =IF(W515="","",IFERROR(VLOOKUP(W515,REPS!$A$2:$D$40,3,0),"")) | Y515: =IF(O515="","",IF(X515="",0,O515*IF(X515>1,X515/100,X515))) | AA515: =IF(Z515="","",IFERROR(VLOOKUP(Z515,REPS!$A$2:$D$40,4,0),"")) | AB515: =IF(O515="","",IF(AA515="",0,O515*IF(AA515>1,AA515/100,AA515))) | AC515: =IF(O515="","",V515+Y515+AB515) | AD515: =IF(O515="","",O515-R515-AC515) | AG515: =IF(OR(AE515="",AE515=0),0,AE515*IF(U515="",0,IF(U515>1,U515/100,U515))) -> 0 | AH515: =IF(OR(AE515="",AE515=0),0,AE515*IF(X515="",0,IF(X515>1,X515/100,X515))) -> 0 | AI515: =IF(OR(AE515="",AE515=0),0,AE515*IF(AA515="",0,IF(AA515>1,AA515/100,AA515))) -> 0 | AJ515: =AG515+AH515+AI515 -> 0 | AK515: =IF(OR(AE515="",AE515=0),0,AE515-AJ515) -> 0 | AL515: =IF(AD515="","",AD515-AK515) | AM515: =IF(C515="","","Waiting for payment") | AP515: =IF(OR(C515="",I515="",K515=""),"",IF(K515="Monthly",EDATE(C515,ROUND(I515*SETTINGS!$I$8,0)),WORKDAY(C515,ROUND(I515*SETTINGS!$I$8,0)))) | AQ515: =IF(C515="","",IF(AND(AP515<>"",TODAY()>=AP515),"Refi Ready",IF(TODAY()-C515>=SETTINGS!$I$11,"Prospecting","Performing"))) | AR515: =IF(OR(C515="",I515="",K515=""),"",IF(K515="Monthly",EDATE(C515,I515),WORKDAY(C515,I515))) | AT515: =IF(C515="","",IF(AM515="Clawed Back","CLAWED",IF(TODAY()<=C515+SETTINGS!$I$2,"⚠ AT RISK","SAFE"))) | AW515: =AW514+IF(AND(C515<>"",AO515<>"",OR('REP COMMISSION'!$B$3="",T515='REP COMMISSION'!$B$3,W515='REP COMMISSION'!$B$3,Z515='REP COMMISSION'!$B$3)),1,0) -> 0 | AX515: =AX514+IF(AND(C515<>"",OR(F515="LOC - INITIAL",F515="CONSOLIDATION - UPFRONT COMM",F515="REVERSE - TOTAL FUNDING")),1,0) -> 0
A516: =IF(C516<>"","F"&COUNT($C$4:C516),"") | B516: =IF(OR(F516="LOC - INITIAL",F516="CONSOLIDATION - UPFRONT COMM",F516="REVERSE - TOTAL FUNDING"),A516,"") | J516: =IF(AND(G516<>"",H516<>""),G516*H516,"") | N516: =IF(OR(G516="",M516=""),0,IF(M516>100,M516,G516*IF(M516>1,M516/100,M516))) -> 0 | O516: =IF(G516="","",G516*IF(L516="",0,IF(L516>1,L516/100,L516))+N516) | Q516: =IF(P516="","",IFERROR(VLOOKUP(P516,PARTNERS!$A$2:$B$30,2,0),"")) | R516: =IF(O516="","",IF(OR(P516="",Q516=""),0,(O516-N516)*IF(Q516>1,Q516/100,Q516))) | S516: =IF(O516="","",O516-R516) | U516: =IF(T516="","",IFERROR(VLOOKUP(T516,REPS!$A$2:$D$40,2,0),"")) | V516: =IF(O516="","",IF(U516="",0,O516*IF(U516>1,U516/100,U516))) | X516: =IF(W516="","",IFERROR(VLOOKUP(W516,REPS!$A$2:$D$40,3,0),"")) | Y516: =IF(O516="","",IF(X516="",0,O516*IF(X516>1,X516/100,X516))) | AA516: =IF(Z516="","",IFERROR(VLOOKUP(Z516,REPS!$A$2:$D$40,4,0),"")) | AB516: =IF(O516="","",IF(AA516="",0,O516*IF(AA516>1,AA516/100,AA516))) | AC516: =IF(O516="","",V516+Y516+AB516) | AD516: =IF(O516="","",O516-R516-AC516) | AG516: =IF(OR(AE516="",AE516=0),0,AE516*IF(U516="",0,IF(U516>1,U516/100,U516))) -> 0 | AH516: =IF(OR(AE516="",AE516=0),0,AE516*IF(X516="",0,IF(X516>1,X516/100,X516))) -> 0 | AI516: =IF(OR(AE516="",AE516=0),0,AE516*IF(AA516="",0,IF(AA516>1,AA516/100,AA516))) -> 0 | AJ516: =AG516+AH516+AI516 -> 0 | AK516: =IF(OR(AE516="",AE516=0),0,AE516-AJ516) -> 0 | AL516: =IF(AD516="","",AD516-AK516) | AM516: =IF(C516="","","Waiting for payment") | AP516: =IF(OR(C516="",I516="",K516=""),"",IF(K516="Monthly",EDATE(C516,ROUND(I516*SETTINGS!$I$8,0)),WORKDAY(C516,ROUND(I516*SETTINGS!$I$8,0)))) | AQ516: =IF(C516="","",IF(AND(AP516<>"",TODAY()>=AP516),"Refi Ready",IF(TODAY()-C516>=SETTINGS!$I$11,"Prospecting","Performing"))) | AR516: =IF(OR(C516="",I516="",K516=""),"",IF(K516="Monthly",EDATE(C516,I516),WORKDAY(C516,I516))) | AT516: =IF(C516="","",IF(AM516="Clawed Back","CLAWED",IF(TODAY()<=C516+SETTINGS!$I$2,"⚠ AT RISK","SAFE"))) | AW516: =AW515+IF(AND(C516<>"",AO516<>"",OR('REP COMMISSION'!$B$3="",T516='REP COMMISSION'!$B$3,W516='REP COMMISSION'!$B$3,Z516='REP COMMISSION'!$B$3)),1,0) -> 0 | AX516: =AX515+IF(AND(C516<>"",OR(F516="LOC - INITIAL",F516="CONSOLIDATION - UPFRONT COMM",F516="REVERSE - TOTAL FUNDING")),1,0) -> 0
A517: =IF(C517<>"","F"&COUNT($C$4:C517),"") | B517: =IF(OR(F517="LOC - INITIAL",F517="CONSOLIDATION - UPFRONT COMM",F517="REVERSE - TOTAL FUNDING"),A517,"") | J517: =IF(AND(G517<>"",H517<>""),G517*H517,"") | N517: =IF(OR(G517="",M517=""),0,IF(M517>100,M517,G517*IF(M517>1,M517/100,M517))) -> 0 | O517: =IF(G517="","",G517*IF(L517="",0,IF(L517>1,L517/100,L517))+N517) | Q517: =IF(P517="","",IFERROR(VLOOKUP(P517,PARTNERS!$A$2:$B$30,2,0),"")) | R517: =IF(O517="","",IF(OR(P517="",Q517=""),0,(O517-N517)*IF(Q517>1,Q517/100,Q517))) | S517: =IF(O517="","",O517-R517) | U517: =IF(T517="","",IFERROR(VLOOKUP(T517,REPS!$A$2:$D$40,2,0),"")) | V517: =IF(O517="","",IF(U517="",0,O517*IF(U517>1,U517/100,U517))) | X517: =IF(W517="","",IFERROR(VLOOKUP(W517,REPS!$A$2:$D$40,3,0),"")) | Y517: =IF(O517="","",IF(X517="",0,O517*IF(X517>1,X517/100,X517))) | AA517: =IF(Z517="","",IFERROR(VLOOKUP(Z517,REPS!$A$2:$D$40,4,0),"")) | AB517: =IF(O517="","",IF(AA517="",0,O517*IF(AA517>1,AA517/100,AA517))) | AC517: =IF(O517="","",V517+Y517+AB517) | AD517: =IF(O517="","",O517-R517-AC517) | AG517: =IF(OR(AE517="",AE517=0),0,AE517*IF(U517="",0,IF(U517>1,U517/100,U517))) -> 0 | AH517: =IF(OR(AE517="",AE517=0),0,AE517*IF(X517="",0,IF(X517>1,X517/100,X517))) -> 0 | AI517: =IF(OR(AE517="",AE517=0),0,AE517*IF(AA517="",0,IF(AA517>1,AA517/100,AA517))) -> 0 | AJ517: =AG517+AH517+AI517 -> 0 | AK517: =IF(OR(AE517="",AE517=0),0,AE517-AJ517) -> 0 | AL517: =IF(AD517="","",AD517-AK517) | AM517: =IF(C517="","","Waiting for payment") | AP517: =IF(OR(C517="",I517="",K517=""),"",IF(K517="Monthly",EDATE(C517,ROUND(I517*SETTINGS!$I$8,0)),WORKDAY(C517,ROUND(I517*SETTINGS!$I$8,0)))) | AQ517: =IF(C517="","",IF(AND(AP517<>"",TODAY()>=AP517),"Refi Ready",IF(TODAY()-C517>=SETTINGS!$I$11,"Prospecting","Performing"))) | AR517: =IF(OR(C517="",I517="",K517=""),"",IF(K517="Monthly",EDATE(C517,I517),WORKDAY(C517,I517))) | AT517: =IF(C517="","",IF(AM517="Clawed Back","CLAWED",IF(TODAY()<=C517+SETTINGS!$I$2,"⚠ AT RISK","SAFE"))) | AW517: =AW516+IF(AND(C517<>"",AO517<>"",OR('REP COMMISSION'!$B$3="",T517='REP COMMISSION'!$B$3,W517='REP COMMISSION'!$B$3,Z517='REP COMMISSION'!$B$3)),1,0) -> 0 | AX517: =AX516+IF(AND(C517<>"",OR(F517="LOC - INITIAL",F517="CONSOLIDATION - UPFRONT COMM",F517="REVERSE - TOTAL FUNDING")),1,0) -> 0
A518: =IF(C518<>"","F"&COUNT($C$4:C518),"") | B518: =IF(OR(F518="LOC - INITIAL",F518="CONSOLIDATION - UPFRONT COMM",F518="REVERSE - TOTAL FUNDING"),A518,"") | J518: =IF(AND(G518<>"",H518<>""),G518*H518,"") | N518: =IF(OR(G518="",M518=""),0,IF(M518>100,M518,G518*IF(M518>1,M518/100,M518))) -> 0 | O518: =IF(G518="","",G518*IF(L518="",0,IF(L518>1,L518/100,L518))+N518) | Q518: =IF(P518="","",IFERROR(VLOOKUP(P518,PARTNERS!$A$2:$B$30,2,0),"")) | R518: =IF(O518="","",IF(OR(P518="",Q518=""),0,(O518-N518)*IF(Q518>1,Q518/100,Q518))) | S518: =IF(O518="","",O518-R518) | U518: =IF(T518="","",IFERROR(VLOOKUP(T518,REPS!$A$2:$D$40,2,0),"")) | V518: =IF(O518="","",IF(U518="",0,O518*IF(U518>1,U518/100,U518))) | X518: =IF(W518="","",IFERROR(VLOOKUP(W518,REPS!$A$2:$D$40,3,0),"")) | Y518: =IF(O518="","",IF(X518="",0,O518*IF(X518>1,X518/100,X518))) | AA518: =IF(Z518="","",IFERROR(VLOOKUP(Z518,REPS!$A$2:$D$40,4,0),"")) | AB518: =IF(O518="","",IF(AA518="",0,O518*IF(AA518>1,AA518/100,AA518))) | AC518: =IF(O518="","",V518+Y518+AB518) | AD518: =IF(O518="","",O518-R518-AC518) | AG518: =IF(OR(AE518="",AE518=0),0,AE518*IF(U518="",0,IF(U518>1,U518/100,U518))) -> 0 | AH518: =IF(OR(AE518="",AE518=0),0,AE518*IF(X518="",0,IF(X518>1,X518/100,X518))) -> 0 | AI518: =IF(OR(AE518="",AE518=0),0,AE518*IF(AA518="",0,IF(AA518>1,AA518/100,AA518))) -> 0 | AJ518: =AG518+AH518+AI518 -> 0 | AK518: =IF(OR(AE518="",AE518=0),0,AE518-AJ518) -> 0 | AL518: =IF(AD518="","",AD518-AK518) | AM518: =IF(C518="","","Waiting for payment") | AP518: =IF(OR(C518="",I518="",K518=""),"",IF(K518="Monthly",EDATE(C518,ROUND(I518*SETTINGS!$I$8,0)),WORKDAY(C518,ROUND(I518*SETTINGS!$I$8,0)))) | AQ518: =IF(C518="","",IF(AND(AP518<>"",TODAY()>=AP518),"Refi Ready",IF(TODAY()-C518>=SETTINGS!$I$11,"Prospecting","Performing"))) | AR518: =IF(OR(C518="",I518="",K518=""),"",IF(K518="Monthly",EDATE(C518,I518),WORKDAY(C518,I518))) | AT518: =IF(C518="","",IF(AM518="Clawed Back","CLAWED",IF(TODAY()<=C518+SETTINGS!$I$2,"⚠ AT RISK","SAFE"))) | AW518: =AW517+IF(AND(C518<>"",AO518<>"",OR('REP COMMISSION'!$B$3="",T518='REP COMMISSION'!$B$3,W518='REP COMMISSION'!$B$3,Z518='REP COMMISSION'!$B$3)),1,0) -> 0 | AX518: =AX517+IF(AND(C518<>"",OR(F518="LOC - INITIAL",F518="CONSOLIDATION - UPFRONT COMM",F518="REVERSE - TOTAL FUNDING")),1,0) -> 0
A519: =IF(C519<>"","F"&COUNT($C$4:C519),"") | B519: =IF(OR(F519="LOC - INITIAL",F519="CONSOLIDATION - UPFRONT COMM",F519="REVERSE - TOTAL FUNDING"),A519,"") | J519: =IF(AND(G519<>"",H519<>""),G519*H519,"") | N519: =IF(OR(G519="",M519=""),0,IF(M519>100,M519,G519*IF(M519>1,M519/100,M519))) -> 0 | O519: =IF(G519="","",G519*IF(L519="",0,IF(L519>1,L519/100,L519))+N519) | Q519: =IF(P519="","",IFERROR(VLOOKUP(P519,PARTNERS!$A$2:$B$30,2,0),"")) | R519: =IF(O519="","",IF(OR(P519="",Q519=""),0,(O519-N519)*IF(Q519>1,Q519/100,Q519))) | S519: =IF(O519="","",O519-R519) | U519: =IF(T519="","",IFERROR(VLOOKUP(T519,REPS!$A$2:$D$40,2,0),"")) | V519: =IF(O519="","",IF(U519="",0,O519*IF(U519>1,U519/100,U519))) | X519: =IF(W519="","",IFERROR(VLOOKUP(W519,REPS!$A$2:$D$40,3,0),"")) | Y519: =IF(O519="","",IF(X519="",0,O519*IF(X519>1,X519/100,X519))) | AA519: =IF(Z519="","",IFERROR(VLOOKUP(Z519,REPS!$A$2:$D$40,4,0),"")) | AB519: =IF(O519="","",IF(AA519="",0,O519*IF(AA519>1,AA519/100,AA519))) | AC519: =IF(O519="","",V519+Y519+AB519) | AD519: =IF(O519="","",O519-R519-AC519) | AG519: =IF(OR(AE519="",AE519=0),0,AE519*IF(U519="",0,IF(U519>1,U519/100,U519))) -> 0 | AH519: =IF(OR(AE519="",AE519=0),0,AE519*IF(X519="",0,IF(X519>1,X519/100,X519))) -> 0 | AI519: =IF(OR(AE519="",AE519=0),0,AE519*IF(AA519="",0,IF(AA519>1,AA519/100,AA519))) -> 0 | AJ519: =AG519+AH519+AI519 -> 0 | AK519: =IF(OR(AE519="",AE519=0),0,AE519-AJ519) -> 0 | AL519: =IF(AD519="","",AD519-AK519) | AM519: =IF(C519="","","Waiting for payment") | AP519: =IF(OR(C519="",I519="",K519=""),"",IF(K519="Monthly",EDATE(C519,ROUND(I519*SETTINGS!$I$8,0)),WORKDAY(C519,ROUND(I519*SETTINGS!$I$8,0)))) | AQ519: =IF(C519="","",IF(AND(AP519<>"",TODAY()>=AP519),"Refi Ready",IF(TODAY()-C519>=SETTINGS!$I$11,"Prospecting","Performing"))) | AR519: =IF(OR(C519="",I519="",K519=""),"",IF(K519="Monthly",EDATE(C519,I519),WORKDAY(C519,I519))) | AT519: =IF(C519="","",IF(AM519="Clawed Back","CLAWED",IF(TODAY()<=C519+SETTINGS!$I$2,"⚠ AT RISK","SAFE"))) | AW519: =AW518+IF(AND(C519<>"",AO519<>"",OR('REP COMMISSION'!$B$3="",T519='REP COMMISSION'!$B$3,W519='REP COMMISSION'!$B$3,Z519='REP COMMISSION'!$B$3)),1,0) -> 0 | AX519: =AX518+IF(AND(C519<>"",OR(F519="LOC - INITIAL",F519="CONSOLIDATION - UPFRONT COMM",F519="REVERSE - TOTAL FUNDING")),1,0) -> 0
A520: =IF(C520<>"","F"&COUNT($C$4:C520),"") | B520: =IF(OR(F520="LOC - INITIAL",F520="CONSOLIDATION - UPFRONT COMM",F520="REVERSE - TOTAL FUNDING"),A520,"") | J520: =IF(AND(G520<>"",H520<>""),G520*H520,"") | N520: =IF(OR(G520="",M520=""),0,IF(M520>100,M520,G520*IF(M520>1,M520/100,M520))) -> 0 | O520: =IF(G520="","",G520*IF(L520="",0,IF(L520>1,L520/100,L520))+N520) | Q520: =IF(P520="","",IFERROR(VLOOKUP(P520,PARTNERS!$A$2:$B$30,2,0),"")) | R520: =IF(O520="","",IF(OR(P520="",Q520=""),0,(O520-N520)*IF(Q520>1,Q520/100,Q520))) | S520: =IF(O520="","",O520-R520) | U520: =IF(T520="","",IFERROR(VLOOKUP(T520,REPS!$A$2:$D$40,2,0),"")) | V520: =IF(O520="","",IF(U520="",0,O520*IF(U520>1,U520/100,U520))) | X520: =IF(W520="","",IFERROR(VLOOKUP(W520,REPS!$A$2:$D$40,3,0),"")) | Y520: =IF(O520="","",IF(X520="",0,O520*IF(X520>1,X520/100,X520))) | AA520: =IF(Z520="","",IFERROR(VLOOKUP(Z520,REPS!$A$2:$D$40,4,0),"")) | AB520: =IF(O520="","",IF(AA520="",0,O520*IF(AA520>1,AA520/100,AA520))) | AC520: =IF(O520="","",V520+Y520+AB520) | AD520: =IF(O520="","",O520-R520-AC520) | AG520: =IF(OR(AE520="",AE520=0),0,AE520*IF(U520="",0,IF(U520>1,U520/100,U520))) -> 0 | AH520: =IF(OR(AE520="",AE520=0),0,AE520*IF(X520="",0,IF(X520>1,X520/100,X520))) -> 0 | AI520: =IF(OR(AE520="",AE520=0),0,AE520*IF(AA520="",0,IF(AA520>1,AA520/100,AA520))) -> 0 | AJ520: =AG520+AH520+AI520 -> 0 | AK520: =IF(OR(AE520="",AE520=0),0,AE520-AJ520) -> 0 | AL520: =IF(AD520="","",AD520-AK520) | AM520: =IF(C520="","","Waiting for payment") | AP520: =IF(OR(C520="",I520="",K520=""),"",IF(K520="Monthly",EDATE(C520,ROUND(I520*SETTINGS!$I$8,0)),WORKDAY(C520,ROUND(I520*SETTINGS!$I$8,0)))) | AQ520: =IF(C520="","",IF(AND(AP520<>"",TODAY()>=AP520),"Refi Ready",IF(TODAY()-C520>=SETTINGS!$I$11,"Prospecting","Performing"))) | AR520: =IF(OR(C520="",I520="",K520=""),"",IF(K520="Monthly",EDATE(C520,I520),WORKDAY(C520,I520))) | AT520: =IF(C520="","",IF(AM520="Clawed Back","CLAWED",IF(TODAY()<=C520+SETTINGS!$I$2,"⚠ AT RISK","SAFE"))) | AW520: =AW519+IF(AND(C520<>"",AO520<>"",OR('REP COMMISSION'!$B$3="",T520='REP COMMISSION'!$B$3,W520='REP COMMISSION'!$B$3,Z520='REP COMMISSION'!$B$3)),1,0) -> 0 | AX520: =AX519+IF(AND(C520<>"",OR(F520="LOC - INITIAL",F520="CONSOLIDATION - UPFRONT COMM",F520="REVERSE - TOTAL FUNDING")),1,0) -> 0
A521: =IF(C521<>"","F"&COUNT($C$4:C521),"") | B521: =IF(OR(F521="LOC - INITIAL",F521="CONSOLIDATION - UPFRONT COMM",F521="REVERSE - TOTAL FUNDING"),A521,"") | J521: =IF(AND(G521<>"",H521<>""),G521*H521,"") | N521: =IF(OR(G521="",M521=""),0,IF(M521>100,M521,G521*IF(M521>1,M521/100,M521))) -> 0 | O521: =IF(G521="","",G521*IF(L521="",0,IF(L521>1,L521/100,L521))+N521) | Q521: =IF(P521="","",IFERROR(VLOOKUP(P521,PARTNERS!$A$2:$B$30,2,0),"")) | R521: =IF(O521="","",IF(OR(P521="",Q521=""),0,(O521-N521)*IF(Q521>1,Q521/100,Q521))) | S521: =IF(O521="","",O521-R521) | U521: =IF(T521="","",IFERROR(VLOOKUP(T521,REPS!$A$2:$D$40,2,0),"")) | V521: =IF(O521="","",IF(U521="",0,O521*IF(U521>1,U521/100,U521))) | X521: =IF(W521="","",IFERROR(VLOOKUP(W521,REPS!$A$2:$D$40,3,0),"")) | Y521: =IF(O521="","",IF(X521="",0,O521*IF(X521>1,X521/100,X521))) | AA521: =IF(Z521="","",IFERROR(VLOOKUP(Z521,REPS!$A$2:$D$40,4,0),"")) | AB521: =IF(O521="","",IF(AA521="",0,O521*IF(AA521>1,AA521/100,AA521))) | AC521: =IF(O521="","",V521+Y521+AB521) | AD521: =IF(O521="","",O521-R521-AC521) | AG521: =IF(OR(AE521="",AE521=0),0,AE521*IF(U521="",0,IF(U521>1,U521/100,U521))) -> 0 | AH521: =IF(OR(AE521="",AE521=0),0,AE521*IF(X521="",0,IF(X521>1,X521/100,X521))) -> 0 | AI521: =IF(OR(AE521="",AE521=0),0,AE521*IF(AA521="",0,IF(AA521>1,AA521/100,AA521))) -> 0 | AJ521: =AG521+AH521+AI521 -> 0 | AK521: =IF(OR(AE521="",AE521=0),0,AE521-AJ521) -> 0 | AL521: =IF(AD521="","",AD521-AK521) | AM521: =IF(C521="","","Waiting for payment") | AP521: =IF(OR(C521="",I521="",K521=""),"",IF(K521="Monthly",EDATE(C521,ROUND(I521*SETTINGS!$I$8,0)),WORKDAY(C521,ROUND(I521*SETTINGS!$I$8,0)))) | AQ521: =IF(C521="","",IF(AND(AP521<>"",TODAY()>=AP521),"Refi Ready",IF(TODAY()-C521>=SETTINGS!$I$11,"Prospecting","Performing"))) | AR521: =IF(OR(C521="",I521="",K521=""),"",IF(K521="Monthly",EDATE(C521,I521),WORKDAY(C521,I521))) | AT521: =IF(C521="","",IF(AM521="Clawed Back","CLAWED",IF(TODAY()<=C521+SETTINGS!$I$2,"⚠ AT RISK","SAFE"))) | AW521: =AW520+IF(AND(C521<>"",AO521<>"",OR('REP COMMISSION'!$B$3="",T521='REP COMMISSION'!$B$3,W521='REP COMMISSION'!$B$3,Z521='REP COMMISSION'!$B$3)),1,0) -> 0 | AX521: =AX520+IF(AND(C521<>"",OR(F521="LOC - INITIAL",F521="CONSOLIDATION - UPFRONT COMM",F521="REVERSE - TOTAL FUNDING")),1,0) -> 0
A522: =IF(C522<>"","F"&COUNT($C$4:C522),"") | B522: =IF(OR(F522="LOC - INITIAL",F522="CONSOLIDATION - UPFRONT COMM",F522="REVERSE - TOTAL FUNDING"),A522,"") | J522: =IF(AND(G522<>"",H522<>""),G522*H522,"") | N522: =IF(OR(G522="",M522=""),0,IF(M522>100,M522,G522*IF(M522>1,M522/100,M522))) -> 0 | O522: =IF(G522="","",G522*IF(L522="",0,IF(L522>1,L522/100,L522))+N522) | Q522: =IF(P522="","",IFERROR(VLOOKUP(P522,PARTNERS!$A$2:$B$30,2,0),"")) | R522: =IF(O522="","",IF(OR(P522="",Q522=""),0,(O522-N522)*IF(Q522>1,Q522/100,Q522))) | S522: =IF(O522="","",O522-R522) | U522: =IF(T522="","",IFERROR(VLOOKUP(T522,REPS!$A$2:$D$40,2,0),"")) | V522: =IF(O522="","",IF(U522="",0,O522*IF(U522>1,U522/100,U522))) | X522: =IF(W522="","",IFERROR(VLOOKUP(W522,REPS!$A$2:$D$40,3,0),"")) | Y522: =IF(O522="","",IF(X522="",0,O522*IF(X522>1,X522/100,X522))) | AA522: =IF(Z522="","",IFERROR(VLOOKUP(Z522,REPS!$A$2:$D$40,4,0),"")) | AB522: =IF(O522="","",IF(AA522="",0,O522*IF(AA522>1,AA522/100,AA522))) | AC522: =IF(O522="","",V522+Y522+AB522) | AD522: =IF(O522="","",O522-R522-AC522) | AG522: =IF(OR(AE522="",AE522=0),0,AE522*IF(U522="",0,IF(U522>1,U522/100,U522))) -> 0 | AH522: =IF(OR(AE522="",AE522=0),0,AE522*IF(X522="",0,IF(X522>1,X522/100,X522))) -> 0 | AI522: =IF(OR(AE522="",AE522=0),0,AE522*IF(AA522="",0,IF(AA522>1,AA522/100,AA522))) -> 0 | AJ522: =AG522+AH522+AI522 -> 0 | AK522: =IF(OR(AE522="",AE522=0),0,AE522-AJ522) -> 0 | AL522: =IF(AD522="","",AD522-AK522) | AM522: =IF(C522="","","Waiting for payment") | AP522: =IF(OR(C522="",I522="",K522=""),"",IF(K522="Monthly",EDATE(C522,ROUND(I522*SETTINGS!$I$8,0)),WORKDAY(C522,ROUND(I522*SETTINGS!$I$8,0)))) | AQ522: =IF(C522="","",IF(AND(AP522<>"",TODAY()>=AP522),"Refi Ready",IF(TODAY()-C522>=SETTINGS!$I$11,"Prospecting","Performing"))) | AR522: =IF(OR(C522="",I522="",K522=""),"",IF(K522="Monthly",EDATE(C522,I522),WORKDAY(C522,I522))) | AT522: =IF(C522="","",IF(AM522="Clawed Back","CLAWED",IF(TODAY()<=C522+SETTINGS!$I$2,"⚠ AT RISK","SAFE"))) | AW522: =AW521+IF(AND(C522<>"",AO522<>"",OR('REP COMMISSION'!$B$3="",T522='REP COMMISSION'!$B$3,W522='REP COMMISSION'!$B$3,Z522='REP COMMISSION'!$B$3)),1,0) -> 0 | AX522: =AX521+IF(AND(C522<>"",OR(F522="LOC - INITIAL",F522="CONSOLIDATION - UPFRONT COMM",F522="REVERSE - TOTAL FUNDING")),1,0) -> 0
A523: =IF(C523<>"","F"&COUNT($C$4:C523),"") | B523: =IF(OR(F523="LOC - INITIAL",F523="CONSOLIDATION - UPFRONT COMM",F523="REVERSE - TOTAL FUNDING"),A523,"") | J523: =IF(AND(G523<>"",H523<>""),G523*H523,"") | N523: =IF(OR(G523="",M523=""),0,IF(M523>100,M523,G523*IF(M523>1,M523/100,M523))) -> 0 | O523: =IF(G523="","",G523*IF(L523="",0,IF(L523>1,L523/100,L523))+N523) | Q523: =IF(P523="","",IFERROR(VLOOKUP(P523,PARTNERS!$A$2:$B$30,2,0),"")) | R523: =IF(O523="","",IF(OR(P523="",Q523=""),0,(O523-N523)*IF(Q523>1,Q523/100,Q523))) | S523: =IF(O523="","",O523-R523) | U523: =IF(T523="","",IFERROR(VLOOKUP(T523,REPS!$A$2:$D$40,2,0),"")) | V523: =IF(O523="","",IF(U523="",0,O523*IF(U523>1,U523/100,U523))) | X523: =IF(W523="","",IFERROR(VLOOKUP(W523,REPS!$A$2:$D$40,3,0),"")) | Y523: =IF(O523="","",IF(X523="",0,O523*IF(X523>1,X523/100,X523))) | AA523: =IF(Z523="","",IFERROR(VLOOKUP(Z523,REPS!$A$2:$D$40,4,0),"")) | AB523: =IF(O523="","",IF(AA523="",0,O523*IF(AA523>1,AA523/100,AA523))) | AC523: =IF(O523="","",V523+Y523+AB523) | AD523: =IF(O523="","",O523-R523-AC523) | AG523: =IF(OR(AE523="",AE523=0),0,AE523*IF(U523="",0,IF(U523>1,U523/100,U523))) -> 0 | AH523: =IF(OR(AE523="",AE523=0),0,AE523*IF(X523="",0,IF(X523>1,X523/100,X523))) -> 0 | AI523: =IF(OR(AE523="",AE523=0),0,AE523*IF(AA523="",0,IF(AA523>1,AA523/100,AA523))) -> 0 | AJ523: =AG523+AH523+AI523 -> 0 | AK523: =IF(OR(AE523="",AE523=0),0,AE523-AJ523) -> 0 | AL523: =IF(AD523="","",AD523-AK523) | AM523: =IF(C523="","","Waiting for payment") | AP523: =IF(OR(C523="",I523="",K523=""),"",IF(K523="Monthly",EDATE(C523,ROUND(I523*SETTINGS!$I$8,0)),WORKDAY(C523,ROUND(I523*SETTINGS!$I$8,0)))) | AQ523: =IF(C523="","",IF(AND(AP523<>"",TODAY()>=AP523),"Refi Ready",IF(TODAY()-C523>=SETTINGS!$I$11,"Prospecting","Performing"))) | AR523: =IF(OR(C523="",I523="",K523=""),"",IF(K523="Monthly",EDATE(C523,I523),WORKDAY(C523,I523))) | AT523: =IF(C523="","",IF(AM523="Clawed Back","CLAWED",IF(TODAY()<=C523+SETTINGS!$I$2,"⚠ AT RISK","SAFE"))) | AW523: =AW522+IF(AND(C523<>"",AO523<>"",OR('REP COMMISSION'!$B$3="",T523='REP COMMISSION'!$B$3,W523='REP COMMISSION'!$B$3,Z523='REP COMMISSION'!$B$3)),1,0) -> 0 | AX523: =AX522+IF(AND(C523<>"",OR(F523="LOC - INITIAL",F523="CONSOLIDATION - UPFRONT COMM",F523="REVERSE - TOTAL FUNDING")),1,0) -> 0
A524: =IF(C524<>"","F"&COUNT($C$4:C524),"") | B524: =IF(OR(F524="LOC - INITIAL",F524="CONSOLIDATION - UPFRONT COMM",F524="REVERSE - TOTAL FUNDING"),A524,"") | J524: =IF(AND(G524<>"",H524<>""),G524*H524,"") | N524: =IF(OR(G524="",M524=""),0,IF(M524>100,M524,G524*IF(M524>1,M524/100,M524))) -> 0 | O524: =IF(G524="","",G524*IF(L524="",0,IF(L524>1,L524/100,L524))+N524) | Q524: =IF(P524="","",IFERROR(VLOOKUP(P524,PARTNERS!$A$2:$B$30,2,0),"")) | R524: =IF(O524="","",IF(OR(P524="",Q524=""),0,(O524-N524)*IF(Q524>1,Q524/100,Q524))) | S524: =IF(O524="","",O524-R524) | U524: =IF(T524="","",IFERROR(VLOOKUP(T524,REPS!$A$2:$D$40,2,0),"")) | V524: =IF(O524="","",IF(U524="",0,O524*IF(U524>1,U524/100,U524))) | X524: =IF(W524="","",IFERROR(VLOOKUP(W524,REPS!$A$2:$D$40,3,0),"")) | Y524: =IF(O524="","",IF(X524="",0,O524*IF(X524>1,X524/100,X524))) | AA524: =IF(Z524="","",IFERROR(VLOOKUP(Z524,REPS!$A$2:$D$40,4,0),"")) | AB524: =IF(O524="","",IF(AA524="",0,O524*IF(AA524>1,AA524/100,AA524))) | AC524: =IF(O524="","",V524+Y524+AB524) | AD524: =IF(O524="","",O524-R524-AC524) | AG524: =IF(OR(AE524="",AE524=0),0,AE524*IF(U524="",0,IF(U524>1,U524/100,U524))) -> 0 | AH524: =IF(OR(AE524="",AE524=0),0,AE524*IF(X524="",0,IF(X524>1,X524/100,X524))) -> 0 | AI524: =IF(OR(AE524="",AE524=0),0,AE524*IF(AA524="",0,IF(AA524>1,AA524/100,AA524))) -> 0 | AJ524: =AG524+AH524+AI524 -> 0 | AK524: =IF(OR(AE524="",AE524=0),0,AE524-AJ524) -> 0 | AL524: =IF(AD524="","",AD524-AK524) | AM524: =IF(C524="","","Waiting for payment") | AP524: =IF(OR(C524="",I524="",K524=""),"",IF(K524="Monthly",EDATE(C524,ROUND(I524*SETTINGS!$I$8,0)),WORKDAY(C524,ROUND(I524*SETTINGS!$I$8,0)))) | AQ524: =IF(C524="","",IF(AND(AP524<>"",TODAY()>=AP524),"Refi Ready",IF(TODAY()-C524>=SETTINGS!$I$11,"Prospecting","Performing"))) | AR524: =IF(OR(C524="",I524="",K524=""),"",IF(K524="Monthly",EDATE(C524,I524),WORKDAY(C524,I524))) | AT524: =IF(C524="","",IF(AM524="Clawed Back","CLAWED",IF(TODAY()<=C524+SETTINGS!$I$2,"⚠ AT RISK","SAFE"))) | AW524: =AW523+IF(AND(C524<>"",AO524<>"",OR('REP COMMISSION'!$B$3="",T524='REP COMMISSION'!$B$3,W524='REP COMMISSION'!$B$3,Z524='REP COMMISSION'!$B$3)),1,0) -> 0 | AX524: =AX523+IF(AND(C524<>"",OR(F524="LOC - INITIAL",F524="CONSOLIDATION - UPFRONT COMM",F524="REVERSE - TOTAL FUNDING")),1,0) -> 0
A525: =IF(C525<>"","F"&COUNT($C$4:C525),"") | B525: =IF(OR(F525="LOC - INITIAL",F525="CONSOLIDATION - UPFRONT COMM",F525="REVERSE - TOTAL FUNDING"),A525,"") | J525: =IF(AND(G525<>"",H525<>""),G525*H525,"") | N525: =IF(OR(G525="",M525=""),0,IF(M525>100,M525,G525*IF(M525>1,M525/100,M525))) -> 0 | O525: =IF(G525="","",G525*IF(L525="",0,IF(L525>1,L525/100,L525))+N525) | Q525: =IF(P525="","",IFERROR(VLOOKUP(P525,PARTNERS!$A$2:$B$30,2,0),"")) | R525: =IF(O525="","",IF(OR(P525="",Q525=""),0,(O525-N525)*IF(Q525>1,Q525/100,Q525))) | S525: =IF(O525="","",O525-R525) | U525: =IF(T525="","",IFERROR(VLOOKUP(T525,REPS!$A$2:$D$40,2,0),"")) | V525: =IF(O525="","",IF(U525="",0,O525*IF(U525>1,U525/100,U525))) | X525: =IF(W525="","",IFERROR(VLOOKUP(W525,REPS!$A$2:$D$40,3,0),"")) | Y525: =IF(O525="","",IF(X525="",0,O525*IF(X525>1,X525/100,X525))) | AA525: =IF(Z525="","",IFERROR(VLOOKUP(Z525,REPS!$A$2:$D$40,4,0),"")) | AB525: =IF(O525="","",IF(AA525="",0,O525*IF(AA525>1,AA525/100,AA525))) | AC525: =IF(O525="","",V525+Y525+AB525) | AD525: =IF(O525="","",O525-R525-AC525) | AG525: =IF(OR(AE525="",AE525=0),0,AE525*IF(U525="",0,IF(U525>1,U525/100,U525))) -> 0 | AH525: =IF(OR(AE525="",AE525=0),0,AE525*IF(X525="",0,IF(X525>1,X525/100,X525))) -> 0 | AI525: =IF(OR(AE525="",AE525=0),0,AE525*IF(AA525="",0,IF(AA525>1,AA525/100,AA525))) -> 0 | AJ525: =AG525+AH525+AI525 -> 0 | AK525: =IF(OR(AE525="",AE525=0),0,AE525-AJ525) -> 0 | AL525: =IF(AD525="","",AD525-AK525) | AM525: =IF(C525="","","Waiting for payment") | AP525: =IF(OR(C525="",I525="",K525=""),"",IF(K525="Monthly",EDATE(C525,ROUND(I525*SETTINGS!$I$8,0)),WORKDAY(C525,ROUND(I525*SETTINGS!$I$8,0)))) | AQ525: =IF(C525="","",IF(AND(AP525<>"",TODAY()>=AP525),"Refi Ready",IF(TODAY()-C525>=SETTINGS!$I$11,"Prospecting","Performing"))) | AR525: =IF(OR(C525="",I525="",K525=""),"",IF(K525="Monthly",EDATE(C525,I525),WORKDAY(C525,I525))) | AT525: =IF(C525="","",IF(AM525="Clawed Back","CLAWED",IF(TODAY()<=C525+SETTINGS!$I$2,"⚠ AT RISK","SAFE"))) | AW525: =AW524+IF(AND(C525<>"",AO525<>"",OR('REP COMMISSION'!$B$3="",T525='REP COMMISSION'!$B$3,W525='REP COMMISSION'!$B$3,Z525='REP COMMISSION'!$B$3)),1,0) -> 0 | AX525: =AX524+IF(AND(C525<>"",OR(F525="LOC - INITIAL",F525="CONSOLIDATION - UPFRONT COMM",F525="REVERSE - TOTAL FUNDING")),1,0) -> 0
... A613: =IF(C613<>"","F"&COUNT($C$4:C613),"") | B613: =IF(OR(F613="LOC - INITIAL",F613="CONSOLIDATION - UPFRONT COMM",F613="REVERSE - TOTAL FUNDING"),A613,"") | J613: =IF(AND(G613<>"",H613<>""),G613*H613,"") | N613: =IF(OR(G613="",M613=""),0,IF(M613>100,M613,G613*IF(M613>1,M613/100,M613))) -> 0 | O613: =IF(G613="","",G613*IF(L613="",0,IF(L613>1,L613/100,L613))+N613) | Q613: =IF(P613="","",IFERROR(VLOOKUP(P613,PARTNERS!$A$2:$B$30,2,0),"")) | R613: =IF(O613="","",IF(OR(P613="",Q613=""),0,(O613-N613)*IF(Q613>1,Q613/100,Q613))) | S613: =IF(O613="","",O613-R613) | U613: =IF(T613="","",IFERROR(VLOOKUP(T613,REPS!$A$2:$D$40,2,0),"")) | V613: =IF(O613="","",IF(U613="",0,O613*IF(U613>1,U613/100,U613))) | X613: =IF(W613="","",IFERROR(VLOOKUP(W613,REPS!$A$2:$D$40,3,0),"")) | Y613: =IF(O613="","",IF(X613="",0,O613*IF(X613>1,X613/100,X613))) | AA613: =IF(Z613="","",IFERROR(VLOOKUP(Z613,REPS!$A$2:$D$40,4,0),"")) | AB613: =IF(O613="","",IF(AA613="",0,O613*IF(AA613>1,AA613/100,AA613))) | AC613: =IF(O613="","",V613+Y613+AB613) | AD613: =IF(O613="","",O613-R613-AC613) | AG613: =IF(OR(AE613="",AE613=0),0,AE613*IF(U613="",0,IF(U613>1,U613/100,U613))) -> 0 | AH613: =IF(OR(AE613="",AE613=0),0,AE613*IF(X613="",0,IF(X613>1,X613/100,X613))) -> 0 | AI613: =IF(OR(AE613="",AE613=0),0,AE613*IF(AA613="",0,IF(AA613>1,AA613/100,AA613))) -> 0 | AJ613: =AG613+AH613+AI613 -> 0 | AK613: =IF(OR(AE613="",AE613=0),0,AE613-AJ613) -> 0 | AL613: =IF(AD613="","",AD613-AK613) | AM613: =IF(C613="","","Waiting for payment") | AP613: =IF(OR(C613="",I613="",K613=""),"",IF(K613="Monthly",EDATE(C613,ROUND(I613*SETTINGS!$I$8,0)),WORKDAY(C613,ROUND(I613*SETTINGS!$I$8,0)))) | AQ613: =IF(C613="","",IF(AND(AP613<>"",TODAY()>=AP613),"Refi Ready",IF(TODAY()-C613>=SETTINGS!$I$11,"Prospecting","Performing"))) | AR613: =IF(OR(C613="",I613="",K613=""),"",IF(K613="Monthly",EDATE(C613,I613),WORKDAY(C613,I613))) | AT613: =IF(C613="","",IF(AM613="Clawed Back","CLAWED",IF(TODAY()<=C613+SETTINGS!$I$2,"⚠ AT RISK","SAFE"))) | AW613: =AW612+IF(AND(C613<>"",AO613<>"",OR('REP COMMISSION'!$B$3="",T613='REP COMMISSION'!$B$3,W613='REP COMMISSION'!$B$3,Z613='REP COMMISSION'!$B$3)),1,0) -> 0 | AX613: =AX612+IF(AND(C613<>"",OR(F613="LOC - INITIAL",F613="CONSOLIDATION - UPFRONT COMM",F613="REVERSE - TOTAL FUNDING")),1,0) -> 0
A614: SEPTEMBER TOTAL | D614: =COUNT(C514:C613)&" units" -> 0 units | G614: =SUM(G514:G613) -> 0 | N614: =SUM(N514:N613) -> 0 | O614: =SUM(O514:O613) -> 0 | R614: =SUM(R514:R613) -> 0 | S614: =SUM(S514:S613) -> 0 | AC614: =SUM(AC514:AC613) -> 0 | AD614: =SUM(AD514:AD613) -> 0 | AE614: =SUM(AE514:AE613) -> 0 | AJ614: =SUM(AJ514:AJ613) -> 0 | AK614: =SUM(AK514:AK613) -> 0 | AL614: =SUM(AL514:AL613) -> 0 | AW614: =AW613 -> 0 | AX614: =AX613 -> 0
A615: ▼ OCTOBER 2026 | AW615: =AW614 -> 0 | AX615: =AX614 -> 0
A616: =IF(C616<>"","F"&COUNT($C$4:C616),"") | B616: =IF(OR(F616="LOC - INITIAL",F616="CONSOLIDATION - UPFRONT COMM",F616="REVERSE - TOTAL FUNDING"),A616,"") | J616: =IF(AND(G616<>"",H616<>""),G616*H616,"") | N616: =IF(OR(G616="",M616=""),0,IF(M616>100,M616,G616*IF(M616>1,M616/100,M616))) -> 0 | O616: =IF(G616="","",G616*IF(L616="",0,IF(L616>1,L616/100,L616))+N616) | Q616: =IF(P616="","",IFERROR(VLOOKUP(P616,PARTNERS!$A$2:$B$30,2,0),"")) | R616: =IF(O616="","",IF(OR(P616="",Q616=""),0,(O616-N616)*IF(Q616>1,Q616/100,Q616))) | S616: =IF(O616="","",O616-R616) | U616: =IF(T616="","",IFERROR(VLOOKUP(T616,REPS!$A$2:$D$40,2,0),"")) | V616: =IF(O616="","",IF(U616="",0,O616*IF(U616>1,U616/100,U616))) | X616: =IF(W616="","",IFERROR(VLOOKUP(W616,REPS!$A$2:$D$40,3,0),"")) | Y616: =IF(O616="","",IF(X616="",0,O616*IF(X616>1,X616/100,X616))) | AA616: =IF(Z616="","",IFERROR(VLOOKUP(Z616,REPS!$A$2:$D$40,4,0),"")) | AB616: =IF(O616="","",IF(AA616="",0,O616*IF(AA616>1,AA616/100,AA616))) | AC616: =IF(O616="","",V616+Y616+AB616) | AD616: =IF(O616="","",O616-R616-AC616) | AG616: =IF(OR(AE616="",AE616=0),0,AE616*IF(U616="",0,IF(U616>1,U616/100,U616))) -> 0 | AH616: =IF(OR(AE616="",AE616=0),0,AE616*IF(X616="",0,IF(X616>1,X616/100,X616))) -> 0 | AI616: =IF(OR(AE616="",AE616=0),0,AE616*IF(AA616="",0,IF(AA616>1,AA616/100,AA616))) -> 0 | AJ616: =AG616+AH616+AI616 -> 0 | AK616: =IF(OR(AE616="",AE616=0),0,AE616-AJ616) -> 0 | AL616: =IF(AD616="","",AD616-AK616) | AM616: =IF(C616="","","Waiting for payment") | AP616: =IF(OR(C616="",I616="",K616=""),"",IF(K616="Monthly",EDATE(C616,ROUND(I616*SETTINGS!$I$8,0)),WORKDAY(C616,ROUND(I616*SETTINGS!$I$8,0)))) | AQ616: =IF(C616="","",IF(AND(AP616<>"",TODAY()>=AP616),"Refi Ready",IF(TODAY()-C616>=SETTINGS!$I$11,"Prospecting","Performing"))) | AR616: =IF(OR(C616="",I616="",K616=""),"",IF(K616="Monthly",EDATE(C616,I616),WORKDAY(C616,I616))) | AT616: =IF(C616="","",IF(AM616="Clawed Back","CLAWED",IF(TODAY()<=C616+SETTINGS!$I$2,"⚠ AT RISK","SAFE"))) | AW616: =AW615+IF(AND(C616<>"",AO616<>"",OR('REP COMMISSION'!$B$3="",T616='REP COMMISSION'!$B$3,W616='REP COMMISSION'!$B$3,Z616='REP COMMISSION'!$B$3)),1,0) -> 0 | AX616: =AX615+IF(AND(C616<>"",OR(F616="LOC - INITIAL",F616="CONSOLIDATION - UPFRONT COMM",F616="REVERSE - TOTAL FUNDING")),1,0) -> 0
A617: =IF(C617<>"","F"&COUNT($C$4:C617),"") | B617: =IF(OR(F617="LOC - INITIAL",F617="CONSOLIDATION - UPFRONT COMM",F617="REVERSE - TOTAL FUNDING"),A617,"") | J617: =IF(AND(G617<>"",H617<>""),G617*H617,"") | N617: =IF(OR(G617="",M617=""),0,IF(M617>100,M617,G617*IF(M617>1,M617/100,M617))) -> 0 | O617: =IF(G617="","",G617*IF(L617="",0,IF(L617>1,L617/100,L617))+N617) | Q617: =IF(P617="","",IFERROR(VLOOKUP(P617,PARTNERS!$A$2:$B$30,2,0),"")) | R617: =IF(O617="","",IF(OR(P617="",Q617=""),0,(O617-N617)*IF(Q617>1,Q617/100,Q617))) | S617: =IF(O617="","",O617-R617) | U617: =IF(T617="","",IFERROR(VLOOKUP(T617,REPS!$A$2:$D$40,2,0),"")) | V617: =IF(O617="","",IF(U617="",0,O617*IF(U617>1,U617/100,U617))) | X617: =IF(W617="","",IFERROR(VLOOKUP(W617,REPS!$A$2:$D$40,3,0),"")) | Y617: =IF(O617="","",IF(X617="",0,O617*IF(X617>1,X617/100,X617))) | AA617: =IF(Z617="","",IFERROR(VLOOKUP(Z617,REPS!$A$2:$D$40,4,0),"")) | AB617: =IF(O617="","",IF(AA617="",0,O617*IF(AA617>1,AA617/100,AA617))) | AC617: =IF(O617="","",V617+Y617+AB617) | AD617: =IF(O617="","",O617-R617-AC617) | AG617: =IF(OR(AE617="",AE617=0),0,AE617*IF(U617="",0,IF(U617>1,U617/100,U617))) -> 0 | AH617: =IF(OR(AE617="",AE617=0),0,AE617*IF(X617="",0,IF(X617>1,X617/100,X617))) -> 0 | AI617: =IF(OR(AE617="",AE617=0),0,AE617*IF(AA617="",0,IF(AA617>1,AA617/100,AA617))) -> 0 | AJ617: =AG617+AH617+AI617 -> 0 | AK617: =IF(OR(AE617="",AE617=0),0,AE617-AJ617) -> 0 | AL617: =IF(AD617="","",AD617-AK617) | AM617: =IF(C617="","","Waiting for payment") | AP617: =IF(OR(C617="",I617="",K617=""),"",IF(K617="Monthly",EDATE(C617,ROUND(I617*SETTINGS!$I$8,0)),WORKDAY(C617,ROUND(I617*SETTINGS!$I$8,0)))) | AQ617: =IF(C617="","",IF(AND(AP617<>"",TODAY()>=AP617),"Refi Ready",IF(TODAY()-C617>=SETTINGS!$I$11,"Prospecting","Performing"))) | AR617: =IF(OR(C617="",I617="",K617=""),"",IF(K617="Monthly",EDATE(C617,I617),WORKDAY(C617,I617))) | AT617: =IF(C617="","",IF(AM617="Clawed Back","CLAWED",IF(TODAY()<=C617+SETTINGS!$I$2,"⚠ AT RISK","SAFE"))) | AW617: =AW616+IF(AND(C617<>"",AO617<>"",OR('REP COMMISSION'!$B$3="",T617='REP COMMISSION'!$B$3,W617='REP COMMISSION'!$B$3,Z617='REP COMMISSION'!$B$3)),1,0) -> 0 | AX617: =AX616+IF(AND(C617<>"",OR(F617="LOC - INITIAL",F617="CONSOLIDATION - UPFRONT COMM",F617="REVERSE - TOTAL FUNDING")),1,0) -> 0
A618: =IF(C618<>"","F"&COUNT($C$4:C618),"") | B618: =IF(OR(F618="LOC - INITIAL",F618="CONSOLIDATION - UPFRONT COMM",F618="REVERSE - TOTAL FUNDING"),A618,"") | J618: =IF(AND(G618<>"",H618<>""),G618*H618,"") | N618: =IF(OR(G618="",M618=""),0,IF(M618>100,M618,G618*IF(M618>1,M618/100,M618))) -> 0 | O618: =IF(G618="","",G618*IF(L618="",0,IF(L618>1,L618/100,L618))+N618) | Q618: =IF(P618="","",IFERROR(VLOOKUP(P618,PARTNERS!$A$2:$B$30,2,0),"")) | R618: =IF(O618="","",IF(OR(P618="",Q618=""),0,(O618-N618)*IF(Q618>1,Q618/100,Q618))) | S618: =IF(O618="","",O618-R618) | U618: =IF(T618="","",IFERROR(VLOOKUP(T618,REPS!$A$2:$D$40,2,0),"")) | V618: =IF(O618="","",IF(U618="",0,O618*IF(U618>1,U618/100,U618))) | X618: =IF(W618="","",IFERROR(VLOOKUP(W618,REPS!$A$2:$D$40,3,0),"")) | Y618: =IF(O618="","",IF(X618="",0,O618*IF(X618>1,X618/100,X618))) | AA618: =IF(Z618="","",IFERROR(VLOOKUP(Z618,REPS!$A$2:$D$40,4,0),"")) | AB618: =IF(O618="","",IF(AA618="",0,O618*IF(AA618>1,AA618/100,AA618))) | AC618: =IF(O618="","",V618+Y618+AB618) | AD618: =IF(O618="","",O618-R618-AC618) | AG618: =IF(OR(AE618="",AE618=0),0,AE618*IF(U618="",0,IF(U618>1,U618/100,U618))) -> 0 | AH618: =IF(OR(AE618="",AE618=0),0,AE618*IF(X618="",0,IF(X618>1,X618/100,X618))) -> 0 | AI618: =IF(OR(AE618="",AE618=0),0,AE618*IF(AA618="",0,IF(AA618>1,AA618/100,AA618))) -> 0 | AJ618: =AG618+AH618+AI618 -> 0 | AK618: =IF(OR(AE618="",AE618=0),0,AE618-AJ618) -> 0 | AL618: =IF(AD618="","",AD618-AK618) | AM618: =IF(C618="","","Waiting for payment") | AP618: =IF(OR(C618="",I618="",K618=""),"",IF(K618="Monthly",EDATE(C618,ROUND(I618*SETTINGS!$I$8,0)),WORKDAY(C618,ROUND(I618*SETTINGS!$I$8,0)))) | AQ618: =IF(C618="","",IF(AND(AP618<>"",TODAY()>=AP618),"Refi Ready",IF(TODAY()-C618>=SETTINGS!$I$11,"Prospecting","Performing"))) | AR618: =IF(OR(C618="",I618="",K618=""),"",IF(K618="Monthly",EDATE(C618,I618),WORKDAY(C618,I618))) | AT618: =IF(C618="","",IF(AM618="Clawed Back","CLAWED",IF(TODAY()<=C618+SETTINGS!$I$2,"⚠ AT RISK","SAFE"))) | AW618: =AW617+IF(AND(C618<>"",AO618<>"",OR('REP COMMISSION'!$B$3="",T618='REP COMMISSION'!$B$3,W618='REP COMMISSION'!$B$3,Z618='REP COMMISSION'!$B$3)),1,0) -> 0 | AX618: =AX617+IF(AND(C618<>"",OR(F618="LOC - INITIAL",F618="CONSOLIDATION - UPFRONT COMM",F618="REVERSE - TOTAL FUNDING")),1,0) -> 0
A619: =IF(C619<>"","F"&COUNT($C$4:C619),"") | B619: =IF(OR(F619="LOC - INITIAL",F619="CONSOLIDATION - UPFRONT COMM",F619="REVERSE - TOTAL FUNDING"),A619,"") | J619: =IF(AND(G619<>"",H619<>""),G619*H619,"") | N619: =IF(OR(G619="",M619=""),0,IF(M619>100,M619,G619*IF(M619>1,M619/100,M619))) -> 0 | O619: =IF(G619="","",G619*IF(L619="",0,IF(L619>1,L619/100,L619))+N619) | Q619: =IF(P619="","",IFERROR(VLOOKUP(P619,PARTNERS!$A$2:$B$30,2,0),"")) | R619: =IF(O619="","",IF(OR(P619="",Q619=""),0,(O619-N619)*IF(Q619>1,Q619/100,Q619))) | S619: =IF(O619="","",O619-R619) | U619: =IF(T619="","",IFERROR(VLOOKUP(T619,REPS!$A$2:$D$40,2,0),"")) | V619: =IF(O619="","",IF(U619="",0,O619*IF(U619>1,U619/100,U619))) | X619: =IF(W619="","",IFERROR(VLOOKUP(W619,REPS!$A$2:$D$40,3,0),"")) | Y619: =IF(O619="","",IF(X619="",0,O619*IF(X619>1,X619/100,X619))) | AA619: =IF(Z619="","",IFERROR(VLOOKUP(Z619,REPS!$A$2:$D$40,4,0),"")) | AB619: =IF(O619="","",IF(AA619="",0,O619*IF(AA619>1,AA619/100,AA619))) | AC619: =IF(O619="","",V619+Y619+AB619) | AD619: =IF(O619="","",O619-R619-AC619) | AG619: =IF(OR(AE619="",AE619=0),0,AE619*IF(U619="",0,IF(U619>1,U619/100,U619))) -> 0 | AH619: =IF(OR(AE619="",AE619=0),0,AE619*IF(X619="",0,IF(X619>1,X619/100,X619))) -> 0 | AI619: =IF(OR(AE619="",AE619=0),0,AE619*IF(AA619="",0,IF(AA619>1,AA619/100,AA619))) -> 0 | AJ619: =AG619+AH619+AI619 -> 0 | AK619: =IF(OR(AE619="",AE619=0),0,AE619-AJ619) -> 0 | AL619: =IF(AD619="","",AD619-AK619) | AM619: =IF(C619="","","Waiting for payment") | AP619: =IF(OR(C619="",I619="",K619=""),"",IF(K619="Monthly",EDATE(C619,ROUND(I619*SETTINGS!$I$8,0)),WORKDAY(C619,ROUND(I619*SETTINGS!$I$8,0)))) | AQ619: =IF(C619="","",IF(AND(AP619<>"",TODAY()>=AP619),"Refi Ready",IF(TODAY()-C619>=SETTINGS!$I$11,"Prospecting","Performing"))) | AR619: =IF(OR(C619="",I619="",K619=""),"",IF(K619="Monthly",EDATE(C619,I619),WORKDAY(C619,I619))) | AT619: =IF(C619="","",IF(AM619="Clawed Back","CLAWED",IF(TODAY()<=C619+SETTINGS!$I$2,"⚠ AT RISK","SAFE"))) | AW619: =AW618+IF(AND(C619<>"",AO619<>"",OR('REP COMMISSION'!$B$3="",T619='REP COMMISSION'!$B$3,W619='REP COMMISSION'!$B$3,Z619='REP COMMISSION'!$B$3)),1,0) -> 0 | AX619: =AX618+IF(AND(C619<>"",OR(F619="LOC - INITIAL",F619="CONSOLIDATION - UPFRONT COMM",F619="REVERSE - TOTAL FUNDING")),1,0) -> 0
A620: =IF(C620<>"","F"&COUNT($C$4:C620),"") | B620: =IF(OR(F620="LOC - INITIAL",F620="CONSOLIDATION - UPFRONT COMM",F620="REVERSE - TOTAL FUNDING"),A620,"") | J620: =IF(AND(G620<>"",H620<>""),G620*H620,"") | N620: =IF(OR(G620="",M620=""),0,IF(M620>100,M620,G620*IF(M620>1,M620/100,M620))) -> 0 | O620: =IF(G620="","",G620*IF(L620="",0,IF(L620>1,L620/100,L620))+N620) | Q620: =IF(P620="","",IFERROR(VLOOKUP(P620,PARTNERS!$A$2:$B$30,2,0),"")) | R620: =IF(O620="","",IF(OR(P620="",Q620=""),0,(O620-N620)*IF(Q620>1,Q620/100,Q620))) | S620: =IF(O620="","",O620-R620) | U620: =IF(T620="","",IFERROR(VLOOKUP(T620,REPS!$A$2:$D$40,2,0),"")) | V620: =IF(O620="","",IF(U620="",0,O620*IF(U620>1,U620/100,U620))) | X620: =IF(W620="","",IFERROR(VLOOKUP(W620,REPS!$A$2:$D$40,3,0),"")) | Y620: =IF(O620="","",IF(X620="",0,O620*IF(X620>1,X620/100,X620))) | AA620: =IF(Z620="","",IFERROR(VLOOKUP(Z620,REPS!$A$2:$D$40,4,0),"")) | AB620: =IF(O620="","",IF(AA620="",0,O620*IF(AA620>1,AA620/100,AA620))) | AC620: =IF(O620="","",V620+Y620+AB620) | AD620: =IF(O620="","",O620-R620-AC620) | AG620: =IF(OR(AE620="",AE620=0),0,AE620*IF(U620="",0,IF(U620>1,U620/100,U620))) -> 0 | AH620: =IF(OR(AE620="",AE620=0),0,AE620*IF(X620="",0,IF(X620>1,X620/100,X620))) -> 0 | AI620: =IF(OR(AE620="",AE620=0),0,AE620*IF(AA620="",0,IF(AA620>1,AA620/100,AA620))) -> 0 | AJ620: =AG620+AH620+AI620 -> 0 | AK620: =IF(OR(AE620="",AE620=0),0,AE620-AJ620) -> 0 | AL620: =IF(AD620="","",AD620-AK620) | AM620: =IF(C620="","","Waiting for payment") | AP620: =IF(OR(C620="",I620="",K620=""),"",IF(K620="Monthly",EDATE(C620,ROUND(I620*SETTINGS!$I$8,0)),WORKDAY(C620,ROUND(I620*SETTINGS!$I$8,0)))) | AQ620: =IF(C620="","",IF(AND(AP620<>"",TODAY()>=AP620),"Refi Ready",IF(TODAY()-C620>=SETTINGS!$I$11,"Prospecting","Performing"))) | AR620: =IF(OR(C620="",I620="",K620=""),"",IF(K620="Monthly",EDATE(C620,I620),WORKDAY(C620,I620))) | AT620: =IF(C620="","",IF(AM620="Clawed Back","CLAWED",IF(TODAY()<=C620+SETTINGS!$I$2,"⚠ AT RISK","SAFE"))) | AW620: =AW619+IF(AND(C620<>"",AO620<>"",OR('REP COMMISSION'!$B$3="",T620='REP COMMISSION'!$B$3,W620='REP COMMISSION'!$B$3,Z620='REP COMMISSION'!$B$3)),1,0) -> 0 | AX620: =AX619+IF(AND(C620<>"",OR(F620="LOC - INITIAL",F620="CONSOLIDATION - UPFRONT COMM",F620="REVERSE - TOTAL FUNDING")),1,0) -> 0
A621: =IF(C621<>"","F"&COUNT($C$4:C621),"") | B621: =IF(OR(F621="LOC - INITIAL",F621="CONSOLIDATION - UPFRONT COMM",F621="REVERSE - TOTAL FUNDING"),A621,"") | J621: =IF(AND(G621<>"",H621<>""),G621*H621,"") | N621: =IF(OR(G621="",M621=""),0,IF(M621>100,M621,G621*IF(M621>1,M621/100,M621))) -> 0 | O621: =IF(G621="","",G621*IF(L621="",0,IF(L621>1,L621/100,L621))+N621) | Q621: =IF(P621="","",IFERROR(VLOOKUP(P621,PARTNERS!$A$2:$B$30,2,0),"")) | R621: =IF(O621="","",IF(OR(P621="",Q621=""),0,(O621-N621)*IF(Q621>1,Q621/100,Q621))) | S621: =IF(O621="","",O621-R621) | U621: =IF(T621="","",IFERROR(VLOOKUP(T621,REPS!$A$2:$D$40,2,0),"")) | V621: =IF(O621="","",IF(U621="",0,O621*IF(U621>1,U621/100,U621))) | X621: =IF(W621="","",IFERROR(VLOOKUP(W621,REPS!$A$2:$D$40,3,0),"")) | Y621: =IF(O621="","",IF(X621="",0,O621*IF(X621>1,X621/100,X621))) | AA621: =IF(Z621="","",IFERROR(VLOOKUP(Z621,REPS!$A$2:$D$40,4,0),"")) | AB621: =IF(O621="","",IF(AA621="",0,O621*IF(AA621>1,AA621/100,AA621))) | AC621: =IF(O621="","",V621+Y621+AB621) | AD621: =IF(O621="","",O621-R621-AC621) | AG621: =IF(OR(AE621="",AE621=0),0,AE621*IF(U621="",0,IF(U621>1,U621/100,U621))) -> 0 | AH621: =IF(OR(AE621="",AE621=0),0,AE621*IF(X621="",0,IF(X621>1,X621/100,X621))) -> 0 | AI621: =IF(OR(AE621="",AE621=0),0,AE621*IF(AA621="",0,IF(AA621>1,AA621/100,AA621))) -> 0 | AJ621: =AG621+AH621+AI621 -> 0 | AK621: =IF(OR(AE621="",AE621=0),0,AE621-AJ621) -> 0 | AL621: =IF(AD621="","",AD621-AK621) | AM621: =IF(C621="","","Waiting for payment") | AP621: =IF(OR(C621="",I621="",K621=""),"",IF(K621="Monthly",EDATE(C621,ROUND(I621*SETTINGS!$I$8,0)),WORKDAY(C621,ROUND(I621*SETTINGS!$I$8,0)))) | AQ621: =IF(C621="","",IF(AND(AP621<>"",TODAY()>=AP621),"Refi Ready",IF(TODAY()-C621>=SETTINGS!$I$11,"Prospecting","Performing"))) | AR621: =IF(OR(C621="",I621="",K621=""),"",IF(K621="Monthly",EDATE(C621,I621),WORKDAY(C621,I621))) | AT621: =IF(C621="","",IF(AM621="Clawed Back","CLAWED",IF(TODAY()<=C621+SETTINGS!$I$2,"⚠ AT RISK","SAFE"))) | AW621: =AW620+IF(AND(C621<>"",AO621<>"",OR('REP COMMISSION'!$B$3="",T621='REP COMMISSION'!$B$3,W621='REP COMMISSION'!$B$3,Z621='REP COMMISSION'!$B$3)),1,0) -> 0 | AX621: =AX620+IF(AND(C621<>"",OR(F621="LOC - INITIAL",F621="CONSOLIDATION - UPFRONT COMM",F621="REVERSE - TOTAL FUNDING")),1,0) -> 0
A622: =IF(C622<>"","F"&COUNT($C$4:C622),"") | B622: =IF(OR(F622="LOC - INITIAL",F622="CONSOLIDATION - UPFRONT COMM",F622="REVERSE - TOTAL FUNDING"),A622,"") | J622: =IF(AND(G622<>"",H622<>""),G622*H622,"") | N622: =IF(OR(G622="",M622=""),0,IF(M622>100,M622,G622*IF(M622>1,M622/100,M622))) -> 0 | O622: =IF(G622="","",G622*IF(L622="",0,IF(L622>1,L622/100,L622))+N622) | Q622: =IF(P622="","",IFERROR(VLOOKUP(P622,PARTNERS!$A$2:$B$30,2,0),"")) | R622: =IF(O622="","",IF(OR(P622="",Q622=""),0,(O622-N622)*IF(Q622>1,Q622/100,Q622))) | S622: =IF(O622="","",O622-R622) | U622: =IF(T622="","",IFERROR(VLOOKUP(T622,REPS!$A$2:$D$40,2,0),"")) | V622: =IF(O622="","",IF(U622="",0,O622*IF(U622>1,U622/100,U622))) | X622: =IF(W622="","",IFERROR(VLOOKUP(W622,REPS!$A$2:$D$40,3,0),"")) | Y622: =IF(O622="","",IF(X622="",0,O622*IF(X622>1,X622/100,X622))) | AA622: =IF(Z622="","",IFERROR(VLOOKUP(Z622,REPS!$A$2:$D$40,4,0),"")) | AB622: =IF(O622="","",IF(AA622="",0,O622*IF(AA622>1,AA622/100,AA622))) | AC622: =IF(O622="","",V622+Y622+AB622) | AD622: =IF(O622="","",O622-R622-AC622) | AG622: =IF(OR(AE622="",AE622=0),0,AE622*IF(U622="",0,IF(U622>1,U622/100,U622))) -> 0 | AH622: =IF(OR(AE622="",AE622=0),0,AE622*IF(X622="",0,IF(X622>1,X622/100,X622))) -> 0 | AI622: =IF(OR(AE622="",AE622=0),0,AE622*IF(AA622="",0,IF(AA622>1,AA622/100,AA622))) -> 0 | AJ622: =AG622+AH622+AI622 -> 0 | AK622: =IF(OR(AE622="",AE622=0),0,AE622-AJ622) -> 0 | AL622: =IF(AD622="","",AD622-AK622) | AM622: =IF(C622="","","Waiting for payment") | AP622: =IF(OR(C622="",I622="",K622=""),"",IF(K622="Monthly",EDATE(C622,ROUND(I622*SETTINGS!$I$8,0)),WORKDAY(C622,ROUND(I622*SETTINGS!$I$8,0)))) | AQ622: =IF(C622="","",IF(AND(AP622<>"",TODAY()>=AP622),"Refi Ready",IF(TODAY()-C622>=SETTINGS!$I$11,"Prospecting","Performing"))) | AR622: =IF(OR(C622="",I622="",K622=""),"",IF(K622="Monthly",EDATE(C622,I622),WORKDAY(C622,I622))) | AT622: =IF(C622="","",IF(AM622="Clawed Back","CLAWED",IF(TODAY()<=C622+SETTINGS!$I$2,"⚠ AT RISK","SAFE"))) | AW622: =AW621+IF(AND(C622<>"",AO622<>"",OR('REP COMMISSION'!$B$3="",T622='REP COMMISSION'!$B$3,W622='REP COMMISSION'!$B$3,Z622='REP COMMISSION'!$B$3)),1,0) -> 0 | AX622: =AX621+IF(AND(C622<>"",OR(F622="LOC - INITIAL",F622="CONSOLIDATION - UPFRONT COMM",F622="REVERSE - TOTAL FUNDING")),1,0) -> 0
...

Sheet FUNDED DEALS 2027
A1: 2027 GRAND TOTAL | D1: =SUM(COUNT(C4:C103),COUNT(C106:C205),COUNT(C208:C307),COUNT(C310:C409),COUNT(C412:C511),COUNT(C514:C613),COUNT(C616:C715),COUNT(C718:C817),COUNT(C820:C919),COUNT(C922:C1021),COUNT(C1024:C1123),COUNT(C1126:C1225))&" units" -> 0 units | G1: =G104+G206+G308+G410+G512+G614+G716+G818+G920+G1022+G1124+G1226 -> 0 | N1: =N104+N206+N308+N410+N512+N614+N716+N818+N920+N1022+N1124+N1226 -> 0 | O1: =O104+O206+O308+O410+O512+O614+O716+O818+O920+O1022+O1124+O1226 -> 0 | R1: =R104+R206+R308+R410+R512+R614+R716+R818+R920+R1022+R1124+R1226 -> 0 | S1: =S104+S206+S308+S410+S512+S614+S716+S818+S920+S1022+S1124+S1226 -> 0 | AC1: =AC104+AC206+AC308+AC410+AC512+AC614+AC716+AC818+AC920+AC1022+AC1124+AC1226 -> 0 | AD1: =AD104+AD206+AD308+AD410+AD512+AD614+AD716+AD818+AD920+AD1022+AD1124+AD1226 -> 0 | AE1: =AE104+AE206+AE308+AE410+AE512+AE614+AE716+AE818+AE920+AE1022+AE1124+AE1226 -> 0 | AJ1: =AJ104+AJ206+AJ308+AJ410+AJ512+AJ614+AJ716+AJ818+AJ920+AJ1022+AJ1124+AJ1226 -> 0 | AK1: =AK104+AK206+AK308+AK410+AK512+AK614+AK716+AK818+AK920+AK1022+AK1124+AK1226 -> 0 | AL1: =AL104+AL206+AL308+AL410+AL512+AL614+AL716+AL818+AL920+AL1022+AL1124+AL1226 -> 0
A2: Deal ID | B2: Parent Deal | C2: Date | D2: Business Name | E2: Lender | F2: Product | G2: Funded / Draw Amount ($) | H2: Factor Rate | I2: Term (bus. days) | J2: Payback ($) | K2: Frequency | L2: Comm % | M2: PSF (% or $) | N2: PSF $ (auto) | O2: Gross Commission ($) | P2: Referral Partner | Q2: Referral % | R2: Referral Fee ($) | S2: Net Comm After Referral ($) | T2: Opener | U2: Opener % | V2: Opener $ | W2: Closer | X2: Closer % | Y2: Closer $ | Z2: Override Rep | AA2: Override % | AB2: Override $ | AC2: Total Rep Payout ($) | AD2: HOUSE NET ($) | AE2: Clawback $ | AF2: Clawback Date | AG2: Opener CB $ | AH2: Closer CB $ | AI2: Override CB $ | AJ2: Rep Clawback $ | AK2: House Clawback $ | AL2: House Net After Clawback ($) | AM2: Commission Status | AN2: Lender Paid Date | AO2: Rep Paid Date | AP2: Est. Renewal (40% in) | AQ2: Deal Status | AR2: Maturity Date | AS2: Notes | AT2: CB Risk | AU2: Lead Source
A3: ▼ JANUARY 2027 | AW3: 0 | AX3: 0
